Workbook

Sheet BOM A320 FFS
A1: EDT | B1: CODIGO INDRA | C1: REF HW | D1: Alternativo | E1: Alternativo RS | F1: DESCRIPCIÓN MATERIAL | G1: P/N FABRICANTE | H1: FABRICANTE | I1: PROVEEDOR | J1: QTY | K1: P.U.
A2: DATA PACKAGE, SW PACKAGE, LICENCIAS | F2: A320 neo std 2.0.0 Simpack | H2: AIRBUS | I2: AIRBUS GO5 | J2: 1 | K2: 2578500
A3: CABINA | F3: Hardware Package | H3: AIRBUS | I3: AIRBUS GO5 | J3: 1 | K3: 1140000
A4: SISTEMA DE MOVIMIENTO | B4: 1390705229900 | F4: MOTION KIT,3RD GEN,MB-E-6DOF-60.0-14000KG | G4: CC91958-000A-075-0 | H4: MOOG | I4: MOOG | J4: 1 | K4: 480000
A5: CABINA | F5: EQUIP SE1 FCU/3XRPM/ATC/BPI/DDRMI/ISIS | H5: THALES | I5: THALES | J5: 1 | K5: 223899.6
A6: BASEFRAME Y AFTCABIN | F6: FABRICACION BASE FRAME Y AFTER CABIN | H6: TALLERES XUQUER, SL | I6: TALLERES XUQUER, SL | J6: 1 | K6: 180000
A7: DATA PACKAGE, SW PACKAGE, LICENCIAS | B7: 3166035600000 | C7: N/A | D7: N/A | E7: N/A | F7: HONEYWELL LIC SW SIMULADOR FMS A320 FFS | G7: PS4087600-907 | H7: HONEYWELL | I7: HONEYWELL | J7: 1 | K7: =#REF!*#REF! -> #REF!
A8: DATA PACKAGE, SW PACKAGE, LICENCIAS | B8: 3166097300005 | F8: LIC SW FG FUNCTION ROYALTY/SIM C/DONGLE | H8: THALES | I8: THALES | J8: 1 | K8: 108814
A9: DATA PACKAGE, SW PACKAGE, LICENCIAS | B9: 3166097300007 | F9: LIC SW EIS 2 FUNCTION REPLICATION FEE | H9: THALES | I9: THALES | J9: 1 | K9: 99704
A10: DATA PACKAGE, SW PACKAGE, LICENCIAS | B10: 1390700590500 | F10: EGPWC A320 STD 2.0 - Simulado | G10: 69000942-151 | H10: HONEYWELL | I10: HONEYWELL | J10: 1 | K10: 82800
A11: SISTEMA DE CONTROL DE FUERZAS | B11: TBD | F11: CLS A320 | G11: CA55977-049 | H11: MOOG | I11: MOOG | J11: 1 | K11: 82432
A12: BASEFRAME Y AFTCABIN | B12: 8570100000000 | F12: MODIFICACIONES BASEFRAME Y AFTERCABIN 2018-2024 | H12: TALLERES XUQUER, SL | I12: TALLERES XUQUER, SL | J12: 1 | K12: 69500
A13: DATA PACKAGE, SW PACKAGE, LICENCIAS | B13: 1390700590501 | C13: N/A | D13: N/A | E13: N/A | F13: HONEYWELL SISTEMA EGPWS MKVA 115VAC P/A320/330/340 | I13: HONEYWELL | J13: 1 | K13: =#REF!*#REF! -> #REF!
A14: DISPLAY | B14: 1390701501301 | F14: Soporte Espejo | G14: 0712061000001 | H14: XUQUER | I14: XUQUER | J14: 1 | K14: 60665
A15: DISPLAY | B15: 0973585290100 | C15: A0301 | F15: SOPORTE ESPEJO | H15: XUQUER | I15: XUQUER | J15: 1 | K15: 60665
A16: DATA PACKAGE, SW PACKAGE, LICENCIAS | B16: 3166097300006 | F16: LIC SW FG FUNCTION STANDARD FEE | H16: THALES | I16: THALES | J16: 1 | K16: 59792
A17: CABINA | F17: DCDU | G17: 401MFD4-3 | H17: GE AVIATION / SYSTEMS LTD | I17: GE AVIATION / SYSTEMS LTD | J17: 2 | K17: 44400
A18: DISPLAY | B18: 1390701501308 | F18: BPS matizada 40 | G18: 0712064000001 | H18: XUQUER | I18: XUQUER | J18: 1 | K18: 38605
A19: DISPLAY | B19: 0973585290800 | C19: A0308 | F19: BPS MATIZADA | H19: XUQUER | I19: XUQUER | J19: 1 | K19: 38605
A20: DATA PACKAGE, SW PACKAGE, LICENCIAS | F20: A320 Std 2.1.0 HW Update Kit without TOS Option | H20: AIRBUS | I20: AIRBUS GO5 | J20: 1 | K20: 35000
A21: DISPLAY | B21: 3140301350000 | F21: PROYECTOR LED DLP 4K UHD P10 WQXGA | G21: 101-1112 | H21: NORXE | I21: NORXE | J21: 3 | K21: 33000
A22: COCKPIT | F22: FABRICACION CABINA COMPLETA | H22: TALLERES XUQUER, SL | I22: TALLERES XUQUER, SL | J22: 1 | K22: 29390.4
A23: SISTEMAS AUXILIARES | B23: 1264011783500 | F23: UPS | G23: GVSUPS80KHS/221213-12728957 | H23: Schneider Electric | I23: SCHNEIDER ELECTRIC | J23: 1 | K23: 25000
A24: DISPLAY | B24: 1390701501306 | F24: Panel Posterior | G24: 0712062000001 | H24: XUQUER | I24: XUQUER | J24: 1 | K24: 19854
A25: DISPLAY | B25: 0973585290600 | C25: A0306 | F25: PANEL POSTERIOR | H25: XUQUER | I25: XUQUER | J25: 1 | K25: 19854
A26: CABINA | B26: 1390701500700 | F26: MCDU | G26: GR-SEQ27901 | H26: GRABYSUR | I26: GRABYSUR | J26: 2 | K26: 19200
A27: SISTEMAS AUXILIARES | B27: 0972825430000.00 / TBD | F27: POWER RACK | G27: 0972825430000.00 / TBD | H27: ISC / INDRA | I27: ISC /AEMSYS | J27: 1 | K27: 19000
A28: CABINA | B28: 9999000322010 | F28: DU NO REC | H28: GRABYSUR | I28: GRABYSUR | J28: 1 | K28: 18000
A29: DISPLAY | B29: 1390701501302 | F29: Cierre superior | G29: 0918686422200 | H29: XUQUER | I29: XUQUER | J29: 1 | K29: 16655
A30: DISPLAY | B30: 0973585290200 | C30: A0302 | F30: CIERRE SUPERIOR | H30: XUQUER | I30: XUQUER | J30: 1 | K30: 16655
A31: DISPLAY | B31: 1390701501307 | F31: Estructura de proyectores, bandejas de proyectores y soportes mascaras | G31: 0712063000001 | H31: XUQUER | I31: XUQUER | J31: 1 | K31: 13236
A32: DISPLAY | B32: 0973585290700 | C32: A0307 | F32: ESTRUCTURA PROY BANDEJA PROY SOPORT MASC | H32: XUQUER | I32: XUQUER | J32: 1 | K32: 13236
A33: DISPLAY | B33: 1390701501304 | F33: Cierre Posterior Superior + Anillo adaptación | G33: 0913385042700 | H33: XUQUER | I33: XUQUER | J33: 1 | K33: 11802
A34: DISPLAY | B34: 0973585290400 | C34: A0304 | F34: CIERRE POST SUP + ANILLOS ADAPT | H34: XUQUER | I34: XUQUER | J34: 1 | K34: 11802
A35: SISTEMA DE MOVIMIENTO | B35: 1390701501200 | F35: PASARELA | G35: 0712100000001 | H35: TALLERES XUQUER, SL | I35: TALLERES XUQUER, SL | J35: 1 | K35: 10108.8
A36: ASIENTO IOS | B36: 1390705801395 | F36: FFIOS PANEL A320 | G36: GR-SEQ40411 | H36: GRABYSUR | I36: GRABYSUR | J36: 1 | K36: 8150.76
A37: DISPLAY | B37: 1390701501303 | F37: Soporte pantalla bps | G37: 0918686423300 | H37: XUQUER | I37: XUQUER | J37: 1 | K37: 7941
A38: DISPLAY | B38: 0973585290300 | C38: A0303 | F38: SOPORTE PANTALLA BPS | H38: XUQUER | I38: XUQUER | J38: 1 | K38: 7941
A39: COMPUTADORES | B39: 3010201822301 | F39: ORDENADOR ENRACABLE Z4 RTXA6000 (GAMA HIGH PC - TIPO IG) | G39: 52258736/7178862 | H39: HP | I39: HP /DELL / SUPERMICRO | J39: 5 | K39: 7000
A40: SISTEMAS AUXILIARES | B40: 1264611110000 | F40: Convertidor 115Vac 400Hz | G40: LF3-400 | H40: MAGNUS POWER | I40: ENELEC | J40: 1 | K40: 7000
A41: DISPLAY | B41: 3140390474100 | F41: LENS PROYECTOR GRANDE 1.20-1.60:1 WQ | G41: N2 | H41: NORXE | I41: NORXE | J41: 3 | K41: 6600
A42: DISPLAY | B42: 1312600040400 | F42: PANTALLA RETROPROYECCION 6306X2305MM AER | G42: CUTM2249CAV10 | H42: STEEWART FILMSCREEN C | I42: STEEWART FILMSCREEN C | J42: 1 | K42: 6333
A43: COCKPIT | F43: FABRICACION CIRCUIT BREAKER PANEL | H43: TALLERES XUQUER, SL | I43: TALLERES XUQUER, SL | J43: 1 | K43: 6240
A44: CABINA | B44: 1390704693802 | F44: DU | G44: TBD | H44: GRABYSUR | I44: GRABYSUR | J44: 6 | K44: 6050
A45: SISTEMA DE CONTROL DE FUERZAS | F45: CONJUNTO CLS COMPLETO | H45: TALLERES XUQUER, SL | I45: TALLERES XUQUER, SL | J45: 1 | K45: 6000
A46: COMPUTADORES | B46: 3010201822302 | F46: ORDENADOR ENRACABLE Z4 T1000 (GAMA HIGH PC - TIPO SENCILLO) | G46: 52258775/7178862 | H46: HP | I46: HP /DELL / SUPERMICRO | J46: 7 | K46: 5500
A47: COMPUTADORES | B47: 3010201822302 | F47: ORDENADOR ENRACABLE Z4 T1000 (GAMA HIGH PC - TIPO SENCILLO) | G47: 52258775/7178862 | H47: HP | I47: HP /DELL / SUPERMICRO | J47: 1 | K47: 5500
A48: COMPUTADORES | B48: 3120201290701 | F48: Rack Rittal - VX IT 5311116 | H48: RITTAL | J48: 1 | K48: 5289.19
F49: UTILES DE VERIFICACIÓN BPS PANELES | H49: XUQUER | I49: XUQUER | J49: 1 | K49: 5000
A50: CABINA | B50: 1279901170900 | F50: COMPASS | G50: 10-7133 CFG 01 | H50: SIMTEK | I50: SIMTEK | J50: 1 | K50: 4800
A51: DISPLAY | B51: 3166092900000 | F51: Lic sw simulador scalable disp manager | G51: SCALABLE DISP MANAGER/GA/SU/202207-070VB | H51: ST ENGINEERING | I51: ST ENGINEERING | J51: 3 | K51: 3800
A52: DISPLAY | B52: 1390701501305 | F52: Cerramiento inferior | G52: 0918686403700 | H52: XUQUER | I52: XUQUER | J52: 1 | K52: 3639
A53: DISPLAY | B53: 0973585290500 | C53: A0305 | F53: CERRAMIENTO INFERIOR | H53: XUQUER | I53: XUQUER | J53: 1 | K53: 3639
A54: ASIENTO IOS | F54: ASIENTO MOD. PEDESTAL ELECTRICO. BAJO | I54: TALLERES XUQUER, SL | J54: 1 | K54: 3546
A55: RTIO Y AVICOM | B55: 1351201490500 | F55: MOD MEZZANINE IPM MULTI 8TX-8RX PARAMETR | G55: MAX-IP-200142 | H55: MAX TECHNOLOGIES INC | I55: ARIES ING. Y SISTEMAS S.A. | J55: 8 | K55: 3374.28
A56: RTIO Y AVICOM | B56: 1351201490500 | F56: MOD MEZZANINE IPM MULTI 8TX-8RX PARAMETR | G56: MAX-IP-200142 | H56: MAX TECHNOLOGIES INC | I56: ARIES ING. Y SISTEMAS S.A. | J56: 7 | K56: 3374.28
A57: BASEFRAME Y AFTCABIN | F57: TRANSPORTE BASE FRAME,AFTER, COCKPIT | H57: TALLERES XUQUER, SL | I57: TALLERES XUQUER, SL | J57: 1 | K57: 3350.88
A58: SONIDOS Y COMUNICACIONES | B58: 1250200510200 | F58: Interfaz MADI de 12 micrófonos | G58: 12MIC | H58: RME AUDIO | J58: 2 | K58: 3200
A59: DISPLAY | B59: 1279990680000 | F59: Luminacimetro mod. LS-150 | G59: LS-150 | H59: KONICA MINOLTA | J59: 1 | K59: 3190
A60: COCKPIT | F60: DISEÑO ESTRUCTURA CUADERNAS | H60: TALLERES XUQUER, SL | I60: TALLERES XUQUER, SL | J60: 1 | K60: 3016
A61: COMPUTADORES | B61: 3060399700200 / TBD | F61: NAS – QNAP TS-H1277XU-RP-3700X-32G | G61: TS-H1277XU-RP / TBD | H61: QNAP / TBD | I61: TEMPEL / TBD | J61: 2 | K61: 3000
A62: DISPLAY | B62: 1390705449000 | F62: Servicio soporte/mantenimiento 1 año obligatorio | G62: 1YR SUPPORT AND MAIN/GA/SU/202207-070VB | H62: ST ENGINEERING | I62: ST ENGINEERING | J62: 1 | K62: 3000
A63: SONIDOS Y COMUNICACIONES | B63: 1312704910100 | F63: MOD CONV D/A 32CH 192KHZ I/O MADI/ADAT | G63: M-32 DA | H63: RME AUDIO | J63: 1 | K63: 3000
A64: RTIO Y AVICOM | B64: 1351201460000 | F64: T. PXI 3U INTELLIGENT CARRIER 2X MOD SIT | G64: MAX-SBC-400105 | H64: MAX TECHNOLOGIES INC | I64: ARIES ING. Y SISTEMAS S.A. | J64: 4 | K64: 2951.16
A65: RTIO Y AVICOM | B65: 1351201460000 | F65: T. PXI 3U INTELLIGENT CARRIER 2X MOD SIT | G65: MAX-SBC-400105 | H65: MAX TECHNOLOGIES INC | I65: ARIES ING. Y SISTEMAS S.A. | J65: 4 | K65: 2951.16
A66: RTIO Y AVICOM | B66: 3200501301700 | F66: RTIO COMPUTER PC IND Q370 I7-8700 256GB-SSD SATA3 S/OF | G66: EMB-PC-X86E/MIC-770Q-00A2/231000387 | I66: TEMPEL | J66: 1 | K66: 2800
A67: RTIO Y AVICOM | B67: 3200501561700 | F67: RTIO COMPUTER | G67: EMB-PC-X86E/ARK-352 0P-U8A1E/221100370 | H67: DELL | I67: TEMPEL | J67: 0 | K67: 2800
A68: ASIENTO IOS | B68: 1390704692600 | F68: PANEL FFIOS 170X85X58.25MM | G68: GR-SEQ40402 /TBD | H68: GRABYSUR | I68: GRABYSUR | J68: 6 | K68: 2500
A69: RTIO Y AVICOM | B69: 1351001440100 | F69: 1-slot (4HP) 3U CompactPCI Xeon E-2276ML 16GB DDR4-2666 DVI, 2x GbE, 1x USB 3.0 128GB SSD | G69: cPCI-3520/2776/M16/S128 | H69: ADLINK TECHNOLOGY | I69: NOVATRONIC SISTEMAS, S.L. | J69: 1 | K69: 2500
A70: SISTEMAS AUXILIARES | B70: 1243602470000 | F70: Aire respirable | G70: COMPRESOR EKOM DK50 2V/50S/M C/ACC S/OF | H70: Hidrohenares | I70: Hidrohenares | J70: 1 | K70: 2500
A71: SONIDOS Y COMUNICACIONES | B71: 1312702890000 | F71: UNIDAD ECUALIZADORA 12ENT/8SAL SOUNDWEB LONDON | G71: BLU-100 | H71: BSS | J71: 1 | K71: 2300
A72: ASIENTO IOS | F72: FAB. Y SUMINISTRO CONSOLA INSTUCTOR | I72: TALLERES XUQUER, SL | J72: 1 | K72: 2288
A73: SONIDOS Y COMUNICACIONES | B73: 1351709000800 | F73: MOD INTERFAZ AUDIO 192KHZ 188-CH USB3.0 | G73: FIREFACE UFX III | H73: RME AUDIO | J73: 1 | K73: 2200
A74: BASEFRAME Y AFTCABIN | F74: PORTE CARENADOS, BPS Y RESTO SIMULADOR | H74: TALLERES XUQUER, SL | I74: TALLERES XUQUER, SL | J74: 1 | K74: 2106
A75: SISTEMA DE CONTROL DE FUERZAS | F75: MONTAJE CLS | H75: TALLERES XUQUER, SL | I75: TALLERES XUQUER, SL | J75: 1 | K75: 2000
A76: ANTIINCENDIOS | B76: 1351705469000 | F76: FIRE CONTROLLER UNIT | G76: ID3004-2-001 | H76: HONEYWELL | J76: 1 | K76: 2000
A77: RTIO Y AVICOM | B77: 1701001920000 | F77: CHASIS BACKPLANE 3U P/COMPACTPCI | G77: CPCIS-2632 | H77: ADLINK TECHNOLOGY | J77: 1 | K77: 2000
A78: BASEFRAME Y AFTCABIN | F78: ARMARIO DOCUMENTACIÓN | H78: TALLERES XUQUER, SL | I78: TALLERES XUQUER, SL | J78: 1 | K78: 1946.88
A79: COMPUTADORES | B79: 3170101514700 | F79: SWITCH 28 PORT 10-GB PRO 4 SFP+ - IG STRG | G79: XS728T-100NES | H79: NETGEAR | J79: 1 | K79: 1871.67
A80: MECANICA | B80: 0973528190300 | F80: DISTRIBUTION PANEL ASSY | G80: 0973528190300 | I80: TALLER MECANICO | J80: 5 | K80: 1800
A81: ASIENTO IOS | B81: 1390705801295 | F81: AUDIO AND SEAT PANEL A320 | G81: GR-SEQ40410 | H81: GRABYSUR | I81: GRABYSUR | J81: 1 | K81: 1680.8
A82: DISPLAY | B82: 7279902590000 | F82: Teodolito digital 30X PREC 2" Laser 100m | G82: DE2A-L | H82: TSINGTAO | J82: 1 | K82: 1595
A83: DISPLAY | B83: 1390705440000 | F83: Camara calibra GIGE fisheye 165x165 FOV | G83: GIGE CALIBRATION CAM/GA/SU/202207-070VB | H83: ST ENGINEERING | I83: ST ENGINEERING | J83: 2 | K83: 1585
A84: CABLEADOS E INTERCONEXIONES | B84: 1229598230401 | F84: CBL EQ HDMI 1.4-M/M HD PRO P/150 L=45.7M | G84: 26-726-150 | H84: EXTRON | J84: 8 | K84: 1500
A85: CABLEADOS E INTERCONEXIONES | B85: 1229598230401 | F85: CBL EQ HDMI 1.4-M/M HD PRO P/150 L=45.7M | G85: 26-726-150 | H85: EXTRON | J85: 2 | K85: 1500
A86: RTIO Y AVICOM | B86: 1351710950100 | F86: USB AI ACQ MODULE USB-6218 | G86: 779678-01 | H86: National Instruments | I86: National Instruments | J86: 1 | K86: 1500
A87: MECANICA | B87: 1390700725500 | F87: GEAR BOX REDUCTION | G87: D3231007000100 | I87: AIRBUS / DEALER | J87: 1 | K87: 1470
A88: COMPUTADORES | B88: 3170102910900 | F88: SWITCH 24 PORT 10X100X1000BASE-T SFP+ | G88: GSM4328S-100NES | H88: NETGEAR | J88: 3 | K88: 1272
A89: CABLEADOS E INTERCONEXIONES | B89: 1229590910009 | F89: Fibra DP Pro P/100 | G89: 26-727-100 | H89: EXTRON | J89: 6 | K89: 1200
A90: COMPUTADORES | B90: 3170106020100 | F90: SWITCH 52P 176GBPS 10/1000GBASE US/EU | G90: GSM4352S-100NES | H90: NETGEAR | J90: 1 | K90: 1001.67
A91: ASIENTO IOS | B91: 1390704692700 | F91: PANEL SEAT 71X85MM ALUM 6061T6 | G91: GR-SEQ40403 /TBD | H91: GRABYSUR | I91: GRABYSUR | J91: 2 | K91: 1000
A92: COMPUTADORES | B92: 3170108870000 | F92: MOD SWITCH KVM ANALOG 16-PORT S/OFERTA | G92: DAV2216-G01 | H92: DELL | J92: 1 | K92: 1000
A93: COMPUTADORES | B93: 3170108880000 | F93: CONSOLA KVM-USB-18,5" 1U | G93: A7485910 | H93: DELL | J93: 1 | K93: 1000
A94: ASIENTO IOS | B94: 1390705801195 | F94: USB PANEL A320 | G94: GR-SEQ40409 | H94: GRABYSUR | I94: GRABYSUR | J94: 1 | K94: 982.26
A95: ASIENTO IOS | B95: 1390705801095 | F95: IOS AUDIO CONNECTION PANEL A320 | G95: GR-SEQ40408 | H95: GRABYSUR | I95: GRABYSUR | J95: 1 | K95: 927.18
A96: DISPLAY | B96: 1229598250100 | F96: Cable DP 1.4-M/M 8K DP PRO P/150 L45.7M | G96: 26-727-150 | H96: Extron | J96: 3 | K96: 916.5
A97: COMPUTADORES | B97: 3120500340100 | F97: APC Switched Rack PDU 2G Zero U - 24 SALIDAS | G97: A7067529 | H97: APC | I97: DELL | J97: 4 | K97: 859
A98: DISPLAY | B98: 3010200471700 | F98: Mod serv lan 8P RS232/422/485 | G98: NPORT 6650-8 | H98: Moxa | J98: 1 | K98: 850
A99: ASIENTO IOS | B99: 1390704692800 | F99: PANEL CONEXION AUDIO IOS 50X85MM ALUM | G99: GR-SEQ40404 /TBD | H99: GRABYSUR | I99: GRABYSUR | J99: 4 | K99: 800
A100: DBS | B100: 3190701010000 | F100: MONITOR UHD 4K 24" 3840X2160 1000:1 | G100: P2415Q | H100: DELL COMPUTER | J100: 2 | K100: 800
...

Sheet EDTs
A1: PROYECTO | B1: A320 FFS GT6 | C1: S24B05
A3: Materiales
A4: S1071 | B4: DISPLAY
A5: S1072 | B5: COCKPIT
A6: S1073 | B6: BASEFRAME-AFTERCABIN
A7: S1074 | B7: ALIMENTACIONES-INTERCONEXIONES
A8: S1075 | B8: EQUIPOS AUXILIARES
A9: S1076 | B9: EQUIPOS CABINA
A10: S1077 | B10: DACS
A11: S1078 | B11: HOST
A12: S1079 | B12: RTIO-AVICOM
A13: S107A | B13: DBS
A14: S107B | B14: IOS-INSE
A15: S107C | B15: MOTION
... A19: S107G | B19: TOOLS
B88: 1501216016001 | G88: DIN 7985 M6x16-A2-70
B89: 1540116000001 | G89: DIN 125 6.4-A2-70
B90: 1540216000101 | G90: DIN 127 B6-A2-70
B91: 1531215000001 | G91: DIN 985 M5-A2-70
B92: 1540115000001 | G92: DIN 125 5.3-A2-70
B796: 1208000320301 | F796: CNC RED 3P/M AER IEC320 10A 250VAC NYLON | G796: PX0686 | J796: 2 | N796: 1 | Q796: 45737 | T796: 2 | X796: 111 | Z796: adalvarezm | AB796: 2

Sheet obsoleta
A1: CHECK | B1: CHECK | C1: EDT | D1: CODIGO INDRA | E1: Alternativo | F1: DESCRIPCIÓN MATERIAL | G1: P/N FABRICANTE | H1: FABRICANTE | I1: PROVEEDOR | J1: QTY | K1: P.U. | L1: IMPORTE | M1: MON | N1: CAMBIO | O1: IMPORTE | P1: 2. CONGELADO (TODO OK) 1. CERRADO PARA LOI (PUEDE HABER PEQUEÑOS CAMBIOS) 3. ABIERTO | Q1: FREEZING DATE | R1: Acopiado SI/NO | S1: NOTAS | T1: PRIORIDAD | U1: LLTI | V1: NOTAS2 | W1: EDT | X1: Contraseña GPI | Y1: SOLICTUD LOTE | Z1: SOLICITANTE | AA1: CHECK | AB1: QTY PEDIDO
A2: SICA | B2: QTY | L2: DIVISA | O2: EUR
C3: S24B05
D4: CABINA
D5: EQUIPOS
A6: =IF(EXACT('BOM A320 FFS'!B6,obsoleta!D6),"OK","ERROR") -> OK | C6: CABINA | F6: DCDU | G6: 401MFD4-3 | H6: GE AVIATION / SYSTEMS LTD | I6: GE AVIATION / SYSTEMS LTD | J6: 2 | K6: 44400 | L6: 88800 | M6: USD | N6: 0.85 | O6: 75480 | P6: N/A | Q6: N/A | R6: N/A | S6: OPCIÓN NO ATSU - NO SE COMPRAN | T6: 1 | W6: S1076 | AA6: ok
A7: =IF(EXACT('BOM A320 FFS'!B7,obsoleta!D7),"OK","ERROR") -> ERROR | C7: DATA PACKAGE, SW PACKAGE, LICENCIAS | D7: 1390700590500 | F7: EGPWC A320 STD 2.0 - Simulado | G7: 69000942-151 | H7: HONEYWELL | I7: HONEYWELL | J7: 1 | K7: 82800 | L7: 82800 | M7: USD | N7: 0.85 | O7: 70380 | P7: CONGELADO | Q7: 45453 | R7: NO | S7: SUBCONTRATO | T7: 3 | W7: S104 | AA7: ok
A8: =IF(EXACT('BOM A320 FFS'!B8,obsoleta!D8),"OK","ERROR") -> ERROR | C8: CABINA | D8: 1279901170900 | F8: COMPASS | G8: 10-7133 CFG 01 | H8: SIMTEK | I8: SIMTEK | J8: 1 | K8: 4800 | L8: 4800 | M8: USD | N8: 0.85 | O8: 4080 | P8: CONGELADO | Q8: 45453 | R8: NO | T8: 1 | U8: SI | W8: S1076 | X8: JA2587/1001 | Y8: 1 | Z8: rochoa | AA8: ok | AB8: 1
A9: =IF(EXACT('BOM A320 FFS'!B10,obsoleta!D9),"OK","ERROR") -> ERROR | C9: CABINA | F9: DU | G9: TBD | H9: GRABYSUR | I9: GRABYSUR | J9: 6 | K9: 16800 | L9: 100800 | M9: USD | N9: 0.85 | O9: 85680 | P9: CERRADO | Q9: 45442 | R9: NO | S9: GRABYSUR - NREC Es hablar con ellos | T9: 1 | U9: SI | W9: S1076 | AA9: ok
A10: =IF(EXACT('BOM A320 FFS'!B11,obsoleta!D10),"OK","ERROR") -> ERROR | C10: CABINA | F10: DU NO REC | H10: GRABYSUR | I10: GRABYSUR | J10: 1 | K10: 18000 | L10: 18000 | M10: USD | N10: 0.85 | O10: 15300 | P10: CERRADO | Q10: 45442 | R10: NO | S10: GRABYSUR - NREC Es hablar con ellos | T10: 1 | U10: SI | W10: S1076 | AA10: ok
A11: =IF(EXACT('BOM A320 FFS'!B12,obsoleta!D11),"OK","ERROR") -> ERROR | C11: CABINA | D11: 1390701500700 | F11: MCDU | G11: GR-SEQ27901 | H11: GRABYSUR | I11: GRABYSUR | J11: 2 | K11: 19200 | L11: 38400 | M11: USD | N11: 0.85 | O11: 32640 | P11: CONGELADO | Q11: 45453 | R11: NO | S11: GRABYSUR | T11: 1 | U11: SI | W11: S1076 | X11: JA2587/1001 | Y11: 1 | Z11: rochoa | AA11: ok | AB11: 2
A12: =IF(EXACT('BOM A320 FFS'!B17,obsoleta!D12),"OK","ERROR") -> OK | AA12: ok
A13: =IF(EXACT('BOM A320 FFS'!B20,obsoleta!D13),"OK","ERROR") -> ERROR | D13: AIRBUS | F13: PARTE INCLUIDO EN EL SIM PACK | AA13: ok
A14: =IF(EXACT('BOM A320 FFS'!B21,obsoleta!D14),"OK","ERROR") -> ERROR | C14: DATA PACKAGE, SW PACKAGE, LICENCIAS | F14: A320 neo std 2.1.0 Simpack | H14: AIRBUS | I14: AIRBUS GO5 | J14: 1 | K14: 2578500 | L14: 2578500 | M14: EUR | N14: 1 | O14: 2578500 | P14: CONGELADO | R14: SI | S14: SUBCONTRATO | T14: 1 | W14: S103 | AA14: ok
A15: =IF(EXACT('BOM A320 FFS'!B22,obsoleta!D15),"OK","ERROR") -> OK | F15: A320 Std 2.1.0 HW Update Kit HAL Option | H15: AIRBUS | I15: AIRBUS GO5 | J15: 1 | K15: 35000 | L15: 35000 | M15: USD | N15: 0.85 | O15: 29750 | P15: ABIERTO | R15: NO | W15: S103 | AA15: ok
A16: =IF(EXACT('BOM A320 FFS'!B23,obsoleta!D16),"OK","ERROR") -> ERROR | C16: CABINA | F16: Hardware Package | H16: AIRBUS | I16: AIRBUS GO5 | J16: 1 | K16: 1140000 | L16: 1140000 | M16: USD | N16: 0.85 | O16: 969000 | P16: CONGELADO | R16: SI | S16: SUBCONTRATO | T16: 1 | U16: SI | W16: S1076 | AA16: ok
A17: =IF(EXACT('BOM A320 FFS'!B24,obsoleta!D17),"OK","ERROR") -> ERROR | AA17: =IF(AC17>AB17,"falta","ok") -> ok
A18: =IF(EXACT('BOM A320 FFS'!B25,obsoleta!D18),"OK","ERROR") -> ERROR | D18: THALES SE1 | AA18: ok
A19: =IF(EXACT('BOM A320 FFS'!B26,obsoleta!D19),"OK","ERROR") -> ERROR | C19: CABINA | F19: EQUIP SE1 FCU/3XRPM/ATC/BPI/DDRMI/ISIS | H19: THALES | I19: THALES | J19: 1 | K19: 223899.6 | L19: 223899.6 | M19: EUR | N19: 1 | O19: 223899.6 | P19: CONGELADO | R19: SI | S19: SUBCONTRATO | T19: 1 | W19: S1076 | AA19: ok
A20: =IF(EXACT('BOM A320 FFS'!B27,obsoleta!D20),"OK","ERROR") -> ERROR | C20: DATA PACKAGE, SW PACKAGE, LICENCIAS | F20: FG FUNCTION - Royalty per simulator | H20: THALES | I20: THALES | J20: 1 | K20: 92911.2 | L20: 92911.2 | M20: EUR | N20: 1 | O20: 92911.2 | P20: CONGELADO | Q20: 45453 | R20: NO | S20: SUBCONTRATO | T20: 2 | W20: S104 | AA20: ok
A21: =IF(EXACT('BOM A320 FFS'!B28,obsoleta!D21),"OK","ERROR") -> ERROR | C21: DATA PACKAGE, SW PACKAGE, LICENCIAS | F21: FG FUNCTION - Version Royalty per simulator | H21: THALES | I21: THALES | J21: 1 | K21: 52840.8 | L21: 52840.8 | M21: EUR | N21: 1 | O21: 52840.8 | P21: CONGELADO | Q21: 45453 | R21: NO | S21: SUBCONTRATO | T21: 2 | W21: S104 | AA21: ok
A22: =IF(EXACT('BOM A320 FFS'!B29,obsoleta!D22),"OK","ERROR") -> ERROR | AA22: ok
A23: =IF(EXACT('BOM A320 FFS'!B33,obsoleta!D23),"OK","ERROR") -> ERROR | D23: CABINA MEC | AA23: ok
A24: =IF(EXACT('BOM A320 FFS'!B34,obsoleta!D24),"OK","ERROR") -> ERROR | C24: COCKPIT | F24: DISEÑO ESTRUCTURA CUADERNAS | H24: TALLERES XUQUER, SL | I24: TALLERES XUQUER, SL | J24: 1 | K24: 3016 | L24: 3619.2 | M24: EUR | N24: 1 | O24: 3619.2 | P24: CONGELADO | R24: SI | S24: SUBCONTRATO | T24: 1 | U24: SI | W24: S1072 | AA24: ok
A25: =IF(EXACT('BOM A320 FFS'!B35,obsoleta!D25),"OK","ERROR") -> ERROR | C25: COCKPIT | F25: FABRICACION CABINA COMPLETA | H25: TALLERES XUQUER, SL | I25: TALLERES XUQUER, SL | J25: 1 | K25: 29390.4 | L25: 35268.48 | M25: EUR | N25: 1 | O25: 35268.48 | P25: CONGELADO | R25: SI | S25: SUBCONTRATO | T25: 1 | U25: SI | W25: S1072 | AA25: ok
A26: =IF(EXACT('BOM A320 FFS'!B36,obsoleta!D26),"OK","ERROR") -> ERROR | C26: COCKPIT | F26: FABRICACION CIRCUIT BREAKER PANEL | H26: TALLERES XUQUER, SL | I26: TALLERES XUQUER, SL | J26: 1 | K26: 6240 | L26: 7488 | M26: EUR | N26: 1 | O26: 7488 | P26: CONGELADO | R26: SI | S26: SUBCONTRATO | T26: 1 | U26: SI | W26: S1072 | AA26: ok
A27: =IF(EXACT('BOM A320 FFS'!B37,obsoleta!D27),"OK","ERROR") -> ERROR | C27: COCKPIT | F27: VENTANAS COCKPIT SIM A320 SN04 | H27: TALLERES XUQUER, SL | I27: TALLERES XUQUER, SL | J27: 1 | K27: 312 | L27: 374.4 | M27: EUR | N27: 1 | O27: 374.4 | P27: CONGELADO | R27: SI | S27: SUBCONTRATO | T27: 1 | U27: SI | W27: S1072 | AA27: ok
A28: =IF(EXACT('BOM A320 FFS'!B39,obsoleta!D28),"OK","ERROR") -> ERROR | AA28: ok
A29: =IF(EXACT('BOM A320 FFS'!B40,obsoleta!D29),"OK","ERROR") -> ERROR | D29: Breakers | AA29: ok
A30: =IF(EXACT('BOM A320 FFS'!B41,obsoleta!D30),"OK","ERROR") -> ERROR | C30: CABINA | D30: 1124510125000 | F30: SWITCH MAGNETICO SPDT 28VDC 200MA C/FUS | G30: 9510-G111-P1F1-Z0R2B2 | H30: E.T.A. | I30: ELPO ELECTRIC, S.A. | J30: 290 | K30: 25.5 | L30: 30.6 | M30: EUR | N30: 1 | O30: 30.6 | P30: CONGELADO | Q30: 45453 | R30: NO | T30: 2 | W30: S1076 | X30: JA2587/1001 | Y30: 1 | Z30: rochoa | AA30: ok | AB30: 290
A31: =IF(EXACT('BOM A320 FFS'!B43,obsoleta!D31),"OK","ERROR") -> ERROR | C31: CABINA | D31: 1128990390300 | F31: ANILLO BLOQUEO OFF ROJO | G31: Y 307 005 01 | H31: E.T.A. | I31: ELPO ELECTRIC, S.A. | J31: 25 | K31: 4.58 | L31: 5.5 | M31: EUR | N31: 1 | O31: 5.5 | P31: CONGELADO | Q31: 45453 | R31: NO | T31: 2 | W31: S1076 | X31: JA2587/1001 | Y31: 1 | Z31: rochoa | AA31: ok | AB31: 25
A32: =IF(EXACT('BOM A320 FFS'!B44,obsoleta!D32),"OK","ERROR") -> ERROR | C32: CABINA | D32: 1124510126100 | F32: SWITCH MAGNETICO SPDT 28VDC 3A 200MA C/D | G32: 9510-G111-P1F1-Z0R2A2-3A | H32: E.T.A. | I32: ELPO ELECTRIC, S.A. | J32: 113 | K32: 25.5 | L32: 30.6 | M32: EUR | N32: 1 | O32: 30.6 | P32: CONGELADO | Q32: 45453 | R32: NO | T32: 2 | W32: S1076 | X32: JA2587/1001 | Y32: 1 | Z32: rochoa | AA32: ok | AB32: 113
A33: =IF(EXACT('BOM A320 FFS'!B46,obsoleta!D33),"OK","ERROR") -> ERROR | C33: CABINA | D33: 1124510125200 | F33: SWITCH MAGNETICO SPDT 28VDC 5A VERDE C/D | G33: 9510-G111-P1F1-Z0R2A2-5A | H33: E.T.A. | I33: ELPO ELECTRIC, S.A. | J33: 24 | K33: 25.5 | L33: 30.6 | M33: EUR | N33: 1 | O33: 30.6 | P33: CONGELADO | Q33: 45453 | R33: NO | T33: 2 | W33: S1076 | X33: JA2587/1001 | Y33: 1 | Z33: rochoa | AA33: ok | AB33: 24
A34: =IF(EXACT('BOM A320 FFS'!B47,obsoleta!D34),"OK","ERROR") -> ERROR | C34: CABINA | D34: 1124510125300 | F34: SWITCH MAGNETICO SPDT 28VDC 7A 200MA C/D | G34: 9510-G111-P1F1-Z0R2A2-7A | H34: E.T.A. | I34: ELPO ELECTRIC, S.A. | J34: 1 | K34: 25.5 | L34: 30.6 | M34: EUR | N34: 1 | O34: 30.6 | P34: CONGELADO | Q34: 45453 | R34: NO | T34: 2 | W34: S1076 | X34: JA2587/1001 | Y34: 1 | Z34: rochoa | AA34: ok | AB34: 5
A35: =IF(EXACT('BOM A320 FFS'!B48,obsoleta!D35),"OK","ERROR") -> ERROR | C35: CABINA | D35: 1124510125400 | F35: SWITCH MAGNETICO SPDT 28VDC 7.5A 200MA C | G35: 9510-G111-P1F1-Z0R2A2-7.5A | H35: E.T.A. | I35: ELPO ELECTRIC, S.A. | J35: 27 | K35: 25.5 | L35: 30.6 | M35: EUR | N35: 1 | O35: 30.6 | P35: CONGELADO | Q35: 45453 | R35: NO | T35: 2 | W35: S1076 | X35: JA2587/1001 | Y35: 1 | Z35: rochoa | AA35: ok | AB35: 27
A36: =IF(EXACT('BOM A320 FFS'!B50,obsoleta!D36),"OK","ERROR") -> ERROR | C36: CABINA | D36: 1124510125500 | F36: SWITCH MAGNETICO SPDT 28VDC 10A 200MA C/ | G36: 9510-G111-P1F1-Z0R2A2-10A | H36: E.T.A. | I36: ELPO ELECTRIC, S.A. | J36: 4 | K36: 25.5 | L36: 30.6 | M36: EUR | N36: 1 | O36: 30.6 | P36: CONGELADO | Q36: 45453 | R36: NO | T36: 2 | W36: S1076 | X36: JA2587/1001 | Y36: 1 | Z36: rochoa | AA36: ok | AB36: 5
A37: =IF(EXACT('BOM A320 FFS'!B51,obsoleta!D37),"OK","ERROR") -> ERROR | C37: CABINA | D37: 1124510125600 | F37: SWITCH MAGNETICO SPDT 28VDC 15A 200MA C/ | G37: 9510-G111-P1F1-Z0R2A2-15A | H37: E.T.A. | I37: ELPO ELECTRIC, S.A. | J37: 6 | K37: 25.5 | L37: 30.6 | M37: EUR | N37: 1 | O37: 30.6 | P37: CONGELADO | Q37: 45453 | R37: NO | T37: 2 | W37: S1076 | X37: JA2587/1001 | Y37: 1 | Z37: rochoa | AA37: ok | AB37: 6
A38: =IF(EXACT('BOM A320 FFS'!B52,obsoleta!D38),"OK","ERROR") -> ERROR | C38: CABINA | D38: 1124510125900 | F38: SWITCH MAGNETICO SPDT 28VDC 35A 200MA C/ | G38: 9510-G111-P1F1-Z0R2A2-35A | H38: E.T.A. | I38: ELPO ELECTRIC, S.A. | J38: 2 | K38: 25.5 | L38: 30.6 | M38: EUR | N38: 1 | O38: 30.6 | P38: CONGELADO | Q38: 45453 | R38: NO | T38: 2 | W38: S1076 | X38: JA2587/1001 | Y38: 1 | Z38: rochoa | AA38: ok | AB38: 5
A39: =IF(EXACT('BOM A320 FFS'!B53,obsoleta!D39),"OK","ERROR") -> ERROR | C39: CABINA | D39: 1124510126000 | F39: SWITCH MAGNETICO SPDT 28VDC 50A 200MA C/ | G39: 9510-G111-P1F1-Z0R2A2-50A | H39: E.T.A. | I39: ELPO ELECTRIC, S.A. | J39: 2 | K39: 25.5 | L39: 30.6 | M39: EUR | N39: 1 | O39: 30.6 | P39: CONGELADO | Q39: 45453 | R39: NO | T39: 2 | W39: S1076 | X39: JA2587/1001 | Y39: 1 | Z39: rochoa | AA39: ok | AB39: 5
A40: =IF(EXACT('BOM A320 FFS'!B54,obsoleta!D40),"OK","ERROR") -> ERROR | C40: CABINA | D40: 1124510125700 | F40: SWITCH MAGNETICO SPDT 28VDC 20A 200MA C/ | G40: 9510-G111-P1F1-Z0R2A2-20A | H40: E.T.A. | I40: ELPO ELECTRIC, S.A. | J40: 4 | K40: 25.5 | L40: 30.6 | M40: EUR | N40: 1 | O40: 30.6 | P40: CONGELADO | Q40: 45453 | R40: NO | T40: 2 | W40: S1076 | X40: JA2587/1001 | Y40: 1 | Z40: rochoa | AA40: ok | AB40: 5
A41: =IF(EXACT('BOM A320 FFS'!B56,obsoleta!D41),"OK","ERROR") -> ERROR | C41: CABINA | D41: 1128990400800 | F41: current label 3 A | G41: X 222 175 07 | H41: E.T.A. | I41: ELPO ELECTRIC, S.A. | J41: 178 | K41: 1.51 | L41: 1.81 | M41: EUR | N41: 1 | O41: 1.81 | P41: CONGELADO | Q41: 45453 | R41: NO | T41: 2 | W41: S1076 | X41: JA2587/1001 | Y41: 1 | Z41: rochoa | AA41: ok | AB41: 178
A42: =IF(EXACT('BOM A320 FFS'!B58,obsoleta!D42),"OK","ERROR") -> ERROR | C42: CABINA | D42: 1128990400900 | F42: current label 5 A | G42: X 222 175 08 | H42: E.T.A. | I42: ELPO ELECTRIC, S.A. | J42: 31 | K42: 1.51 | L42: 1.81 | M42: EUR | N42: 1 | O42: 1.81 | P42: CONGELADO | Q42: 45453 | R42: NO | T42: 2 | W42: S1076 | X42: JA2587/1001 | Y42: 1 | Z42: rochoa | AA42: ok | AB42: 31
A43: =IF(EXACT('BOM A320 FFS'!B60,obsoleta!D43),"OK","ERROR") -> ERROR | C43: CABINA | D43: 1128990401500 | F43: current label 7,5 A | G43: X 222 175 09 | H43: E.T.A. | I43: ELPO ELECTRIC, S.A. | J43: 33 | K43: 1.51 | L43: 1.81 | M43: EUR | N43: 1 | O43: 1.81 | P43: CONGELADO | Q43: 45453 | R43: NO | T43: 2 | W43: S1076 | X43: JA2587/1001 | Y43: 1 | Z43: rochoa | AA43: ok | AB43: 33
A44: =IF(EXACT('BOM A320 FFS'!B61,obsoleta!D44),"OK","ERROR") -> ERROR | C44: CABINA | D44: 1128990400400 | F44: current label 10 A | G44: X 222 175 11 | H44: E.T.A. | I44: ELPO ELECTRIC, S.A. | J44: 30 | K44: 1.51 | L44: 1.81 | M44: EUR | N44: 1 | O44: 1.81 | P44: CONGELADO | Q44: 45453 | R44: NO | T44: 2 | W44: S1076 | X44: JA2587/1001 | Y44: 1 | Z44: rochoa | AA44: ok | AB44: 30
A45: =IF(EXACT('BOM A320 FFS'!B62,obsoleta!D45),"OK","ERROR") -> ERROR | C45: CABINA | D45: 1128990400200 | F45: current label 15 A | G45: X 222 175 12 | H45: E.T.A. | I45: ELPO ELECTRIC, S.A. | J45: 4 | K45: 1.51 | L45: 1.81 | M45: EUR | N45: 1 | O45: 1.81 | P45: CONGELADO | Q45: 45453 | R45: NO | T45: 2 | W45: S1076 | X45: JA2587/1001 | Y45: 1 | Z45: rochoa | AA45: ok | AB45: 4
A46: =IF(EXACT('BOM A320 FFS'!B63,obsoleta!D46),"OK","ERROR") -> ERROR | C46: CABINA | D46: 1128990400300 | F46: current label 20 A | G46: X 222 175 13 | H46: E.T.A. | I46: ELPO ELECTRIC, S.A. | J46: 6 | K46: 1.51 | L46: 1.81 | M46: EUR | N46: 1 | O46: 1.81 | P46: CONGELADO | Q46: 45453 | R46: NO | T46: 2 | W46: S1076 | X46: JA2587/1001 | Y46: 1 | Z46: rochoa | AA46: ok | AB46: 6
A47: =IF(EXACT('BOM A320 FFS'!B65,obsoleta!D47),"OK","ERROR") -> ERROR | C47: CABINA | D47: 1128990401100 | F47: current label 25 A | G47: X 222 175 14 | H47: E.T.A. | I47: ELPO ELECTRIC, S.A. | J47: 4 | K47: 1.51 | L47: 1.81 | M47: EUR | N47: 1 | O47: 1.81 | P47: CONGELADO | Q47: 45453 | R47: NO | T47: 2 | W47: S1076 | X47: JA2587/1001 | Y47: 1 | Z47: rochoa | AA47: ok | AB47: 4
A48: =IF(EXACT('BOM A320 FFS'!B66,obsoleta!D48),"OK","ERROR") -> ERROR | C48: CABINA | D48: 1128990400100 | F48: current label 50 A | G48: X 222 175 19 | H48: E.T.A. | I48: ELPO ELECTRIC, S.A. | J48: 24 | K48: 1.51 | L48: 1.81 | M48: EUR | N48: 1 | O48: 1.81 | P48: CONGELADO | Q48: 45453 | R48: NO | T48: 2 | W48: S1076 | X48: JA2587/1001 | Y48: 1 | Z48: rochoa | AA48: ok | AB48: 24
A49: =IF(EXACT('BOM A320 FFS'!B67,obsoleta!D49),"OK","ERROR") -> ERROR | AA49: ok
A50: =IF(EXACT('BOM A320 FFS'!B68,obsoleta!D50),"OK","ERROR") -> ERROR | D50: BASEFRAME AND AFTCABIN | AA50: ok
A51: =IF(EXACT('BOM A320 FFS'!B69,obsoleta!D51),"OK","ERROR") -> ERROR | D51: BASEFRAME AND AFTCABIN MEC | AA51: ok
A52: =IF(EXACT('BOM A320 FFS'!B70,obsoleta!D52),"OK","ERROR") -> ERROR | C52: BASEFRAME Y AFTCABIN | F52: FABRICACION BASE FRAME Y AFTER CABIN | H52: TALLERES XUQUER, SL | I52: TALLERES XUQUER, SL | J52: 1 | K52: 180000 | L52: 180000 | M52: EUR | N52: 1 | O52: 180000 | P52: CONGELADO | R52: SI | S52: SUBCONTRATO | T52: 1 | U52: SI | W52: S1073 | AA52: ok
A53: =IF(EXACT('BOM A320 FFS'!B71,obsoleta!D53),"OK","ERROR") -> ERROR | C53: BASEFRAME Y AFTCABIN | F53: ARMARIO DOCUMENTACIÓN | H53: TALLERES XUQUER, SL | I53: TALLERES XUQUER, SL | J53: 1 | K53: 1946.88 | L53: 1946.88 | M53: EUR | N53: 1 | O53: 1946.88 | P53: CONGELADO | R53: SI | T53: 1 | U53: SI | W53: S1073 | AA53: ok
A54: =IF(EXACT('BOM A320 FFS'!B72,obsoleta!D54),"OK","ERROR") -> OK | C54: BASEFRAME Y AFTCABIN | F54: TRANSPORTE BASE FRAME,AFTER, COCKPIT | H54: TALLERES XUQUER, SL | I54: TALLERES XUQUER, SL | J54: 1 | K54: 3350.88 | L54: 3350.88 | M54: EUR | N54: 1 | O54: 3350.88 | P54: CONGELADO | R54: SI | T54: 1 | U54: SI | W54: S1073 | AA54: ok
A55: =IF(EXACT('BOM A320 FFS'!B73,obsoleta!D55),"OK","ERROR") -> ERROR | C55: BASEFRAME Y AFTCABIN | F55: PORTE CARENADOS, BPS Y RESTO SIMULADOR | H55: TALLERES XUQUER, SL | I55: TALLERES XUQUER, SL | J55: 1 | K55: 2106 | L55: 2106 | M55: EUR | N55: 1 | O55: 2106 | P55: CONGELADO | R55: SI | T55: 1 | U55: SI | W55: S1073 | AA55: ok
A56: =IF(EXACT('BOM A320 FFS'!B74,obsoleta!D56),"OK","ERROR") -> OK | C56: BASEFRAME Y AFTCABIN | F56: TOMAS DE CORRIENTE Y RED EN AFTERCABIN | H56: TALLERES XUQUER, SL | I56: TALLERES XUQUER, SL | J56: 1 | K56: 0 | L56: 0 | M56: EUR | N56: 1 | O56: 0 | P56: CONGELADO | R56: SI | T56: 1 | U56: SI | W56: S1073 | AA56: ok
A57: =IF(EXACT('BOM A320 FFS'!B76,obsoleta!D57),"OK","ERROR") -> ERROR | AA57: ok
A58: =IF(EXACT('BOM A320 FFS'!B77,obsoleta!D58),"OK","ERROR") -> ERROR | D58: DRAWBRIDGE | AA58: ok
A59: =IF(EXACT('BOM A320 FFS'!B78,obsoleta!D59),"OK","ERROR") -> ERROR | C59: SISTEMA DE MOVIMIENTO | D59: 1390701501200 | F59: PASARELA | G59: 712100000001 | H59: TALLERES XUQUER, SL | I59: TALLERES XUQUER, SL | J59: 1 | K59: 10108.8 | L59: 10108.8 | M59: EUR | N59: 1 | O59: 10108.8 | P59: CONGELADO | Q59: 45453 | R59: NO | T59: 1 | U59: SI | W59: S107C | X59: JA2612/1001 | Y59: 1 | Z59: rochoa | AA59: ok | AB59: 1
A60: =IF(EXACT('BOM A320 FFS'!B79,obsoleta!D60),"OK","ERROR") -> ERROR | AA60: ok
A61: =IF(EXACT('BOM A320 FFS'!B80,obsoleta!D61),"OK","ERROR") -> ERROR | D61: MOTION | AA61: ok
A62: =IF(EXACT('BOM A320 FFS'!B81,obsoleta!D62),"OK","ERROR") -> ERROR | C62: SISTEMA DE MOVIMIENTO | D62: 1390705229900 | F62: MOTION KIT,3RD GEN,MB-E-6DOF-60.0-14000KG | G62: CC91958-000A-075-0 | H62: MOOG | I62: MOOG | J62: 1 | K62: 480000 | L62: 480000 | M62: USD | N62: 0.85 | O62: 408000 | S62: SUBCONTRATO SEGÚN FRAME AGREEMENT | T62: 1 | U62: SI | W62: S107C | X62: JA2612/1001 | Y62: 1 | AA62: ok
A63: =IF(EXACT('BOM A320 FFS'!B82,obsoleta!D63),"OK","ERROR") -> ERROR | AA63: ok
A64: =IF(EXACT('BOM A320 FFS'!B83,obsoleta!D64),"OK","ERROR") -> ERROR | D64: CLS | AA64: ok
A65: =IF(EXACT('BOM A320 FFS'!B84,obsoleta!D65),"OK","ERROR") -> ERROR | C65: SISTEMA DE CONTROL DE FUERZAS | D65: TBD | F65: CLS A320 | G65: CA55977-049 | H65: MOOG | I65: MOOG | J65: 1 | K65: 82432 | L65: 82432 | M65: USD | N65: 0.85 | O65: 70067.2 | P65: CONGELADO | R65: SI | S65: SUBCONTRATO SEGÚN FRAME AGREEMENT | T65: 1 | U65: SI | W65: S107D | AA65: ok
A66: =IF(EXACT('BOM A320 FFS'!B85,obsoleta!D66),"OK","ERROR") -> ERROR | C66: SISTEMA DE CONTROL DE FUERZAS | F66: CONJUNTO CLS COMPLETO | H66: TALLERES XUQUER, SL | I66: TALLERES XUQUER, SL | J66: 1 | K66: 6000 | L66: 6000 | M66: EUR | N66: 1 | O66: 6000 | P66: CONGELADO | R66: SI | S66: SUBCONTRATO | T66: 1 | U66: SI | W66: S1072 | AA66: ok
A67: =IF(EXACT('BOM A320 FFS'!B86,obsoleta!D67),"OK","ERROR") -> ERROR | C67: SISTEMA DE CONTROL DE FUERZAS | F67: MONTAJE CLS | H67: TALLERES XUQUER, SL | I67: TALLERES XUQUER, SL | J67: 1 | K67: 2000 | L67: 2000 | M67: EUR | N67: 1 | O67: 2000 | P67: CONGELADO | R67: SI | S67: SUBCONTRATO | T67: 1 | U67: SI | W67: S1072 | AA67: ok
A68: =IF(EXACT('BOM A320 FFS'!B87,obsoleta!D68),"OK","ERROR") -> ERROR | AA68: ok
A69: =IF(EXACT('BOM A320 FFS'!B94,obsoleta!D69),"OK","ERROR") -> ERROR | D69: SISTEMAS AUXILIARES | AA69: ok
A70: =IF(EXACT('BOM A320 FFS'!B95,obsoleta!D70),"OK","ERROR") -> ERROR | AA70: ok
A71: =IF(EXACT('BOM A320 FFS'!B96,obsoleta!D71),"OK","ERROR") -> ERROR | C71: SISTEMAS AUXILIARES | D71: Aire respirable | F71: Aire respirable | H71: Hidrohenares | I71: Hidrohenares | J71: 1 | K71: 2500 | L71: 2500 | M71: EUR | N71: 1 | O71: 2500 | P71: CONGELADO | Q71: 45453 | R71: NO | S71: PO de referencia 1101610194 | T71: 2 | W71: S1075 | AA71: ok
A72: =IF(EXACT('BOM A320 FFS'!B97,obsoleta!D72),"OK","ERROR") -> ERROR | C72: SISTEMAS AUXILIARES | D72: AIRE ACONDICIONADO | F72: AIRE ACONDICIONADO | H72: Yntegra | I72: Yntegra | J72: 1 | K72: 20000 | L72: 20000 | M72: EUR | N72: 1 | O72: 20000 | P72: CONGELADO | Q72: 45453 | R72: NO | S72: SUBCONTRATO PO de referencia 1101592008 | T72: 2 | W72: S1075 | AA72: ok
A73: =IF(EXACT('BOM A320 FFS'!B105,obsoleta!D73),"OK","ERROR") -> ERROR | C73: SISTEMAS AUXILIARES | D73: 0972825430000.00 / TBD | F73: POWER RACK | G73: 0972825430000.00 / TBD | H73: ISC / INDRA | I73: ISC /AEMSYS | J73: 1 | K73: 19000 | L73: 19000 | M73: EUR | N73: 1 | O73: 19000 | P73: CERRADO | Q73: 45453 | R73: NO | S73: PO de referencia 1101586223 | T73: 1 | W73: S1075 | AA73: ok
A74: =IF(EXACT('BOM A320 FFS'!B106,obsoleta!D74),"OK","ERROR") -> ERROR | C74: SISTEMAS AUXILIARES | D74: 1264611110000 | F74: Convertidor 115Vac 400Hz | G74: LF3-400 | H74: MAGNUS POWER | I74: ENELEC | J74: 1 | K74: 7000 | L74: 7000 | M74: EUR | N74: 1 | O74: 7000 | P74: CONGELADO | Q74: 45453 | R74: NO | T74: 1 | U74: SI | W74: S1075 | X74: JA2582/1001 | Y74: 1 | Z74: rochoa | AA74: ok | AB74: 1
A75: =IF(EXACT('BOM A320 FFS'!B107,obsoleta!D75),"OK","ERROR") -> ERROR | C75: SISTEMAS AUXILIARES | D75: 1138022400100 | E75: 1138022410200 | F75: CONTROLADOR ILC 170 ETH 2T | G75: 2916532 | H75: PHOENIX CONTACT | J75: 1 | K75: 450 | L75: 450 | M75: EUR | N75: 1 | O75: 450 | P75: CONGELADO | Q75: 45453 | R75: NO | T75: 1 | U75: SI | W75: S1075 | X75: JA2582/1001 | Y75: 1 | Z75: rochoa | AA75: ok | AB75: 1
A76: =IF(EXACT('BOM A320 FFS'!B108,obsoleta!D76),"OK","ERROR") -> ERROR | C76: SISTEMAS AUXILIARES | D76: 1351202410300 | F76: MODULO E/S DIGITAL IB IL 24 DI 16-PAC | G76: 2861250 | H76: PHOENIX CONTACT | J76: 3 | K76: 200 | L76: 600 | M76: EUR | N76: 1 | O76: 600 | P76: CONGELADO | Q76: 45453 | R76: NO | T76: 1 | U76: SI | W76: S1075 | X76: JA2582/1001 | Y76: 1 | Z76: rochoa | AA76: ok | AB76: 3
A77: =IF(EXACT('BOM A320 FFS'!B109,obsoleta!D77),"OK","ERROR") -> ERROR | C77: SISTEMAS AUXILIARES | D77: 1351202410200 | F77: MODULO E/S DIGITAL IB IL 24 DO 16-PAC | G77: 2861292 | H77: PHOENIX CONTACT | J77: 2 | K77: 200 | L77: 400 | M77: EUR | N77: 1 | O77: 400 | P77: CONGELADO | Q77: 45453 | R77: NO | T77: 1 | U77: SI | W77: S1075 | X77: JA2582/1001 | Y77: 1 | Z77: rochoa | AA77: ok | AB77: 2
A78: =IF(EXACT('BOM A320 FFS'!B110,obsoleta!D78),"OK","ERROR") -> ERROR | C78: SISTEMAS AUXILIARES | D78: 1351800390000 | F78: SD Flash 512MB Memory | J78: 1 | K78: 100 | L78: 100 | M78: EUR | N78: 1 | O78: 100 | P78: CONGELADO | Q78: 45453 | R78: NO | T78: 1 | U78: SI | W78: S1075 | X78: JA2582/1001 | Y78: 1 | Z78: rochoa | AA78: ok | AB78: 1
A79: =IF(EXACT('BOM A320 FFS'!B115,obsoleta!D79),"OK","ERROR") -> ERROR | AA79: ok
A80: =IF(EXACT('BOM A320 FFS'!B116,obsoleta!D80),"OK","ERROR") -> ERROR | C80: SISTEMAS AUXILIARES | D80: UPS | F80: UPS | H80: Schneider Electric | I80: SCHNEIDER ELECTRIC | J80: 1 | K80: 25000 | L80: 25000 | M80: EUR | N80: 1 | O80: 25000 | P80: ABIERTO | R80: NO | T80: 2 | W80: S1075 | AA80: ok
A81: =IF(EXACT('BOM A320 FFS'!B117,obsoleta!D81),"OK","ERROR") -> ERROR | C81: SISTEMAS AUXILIARES | D81: 1264011783100 | F81: SAI 80KW 3F 400V PUESTA-5X8 GALAXY-VS | G81: GVSUPS80KHS | H81: SCHNEIDER ELECTRIC | J81: 1 | L81: 0 | M81: EUR | N81: 1 | O81: 0 | P81: ABIERTO | R81: NO | T81: 2 | W81: S1075 | AA81: ok
A82: =IF(EXACT('BOM A320 FFS'!B118,obsoleta!D82),"OK","ERROR") -> ERROR | C82: SISTEMAS AUXILIARES | D82: 1351303410000 | F82: T. RED GEST LCES2 C/MODBUS/ETH/SENS-AUX | G82: AP9644 | H82: SCHNEIDER ELECTRIC | J82: 1 | L82: 0 | M82: EUR | N82: 1 | O82: 0 | P82: ABIERTO | R82: NO | T82: 2 | W82: S1075 | AA82: ok
A83: =IF(EXACT('BOM A320 FFS'!B119,obsoleta!D83),"OK","ERROR") -> ERROR | C83: SISTEMAS AUXILIARES | D83: 1700103180000 | F83: ARMARIO BATERIA VACIO VRLA 197X110X85CM | G83: GVEBC11 | H83: SCHNEIDER ELECTRIC | J83: 1 | L83: 0 | M83: EUR | N83: 1 | O83: 0 | P83: ABIERTO | R83: NO | T83: 2 | W83: S1075 | AA83: ok
A84: =IF(EXACT('BOM A320 FFS'!B120,obsoleta!D84),"OK","ERROR") -> ERROR | C84: SISTEMAS AUXILIARES | D84: 1135234080300 | F84: KIT DISYUNTOR 20-80KW 400V VRLA GALAXYVS | G84: GVSBBK20K80H | H84: SCHNEIDER ELECTRIC | J84: 1 | L84: 0 | M84: EUR | N84: 1 | O84: 0 | P84: ABIERTO | R84: NO | T84: 2 | W84: S1075 | AA84: ok
A85: =IF(EXACT('BOM A320 FFS'!B123,obsoleta!D85),"OK","ERROR") -> ERROR | C85: SISTEMAS AUXILIARES | D85: 1261121200605 | F85: BATERIA VRLA 12V 92.8AH 2350W SPRINTER | G85: XP12V3000 | H85: SCHNEIDER ELECTRIC | J85: 0 | L85: 0 | M85: EUR | N85: 1 | O85: 0 | P85: ABIERTO | R85: NO | T85: 2 | W85: S1075 | AA85: ok
A86: =IF(EXACT('BOM A320 FFS'!B124,obsoleta!D86),"OK","ERROR") -> ERROR | AA86: ok
A87: =IF(EXACT('BOM A320 FFS'!B125,obsoleta!D87),"OK","ERROR") -> ERROR | D87: AUDIO / COMMS | AA87: ok
A88: =IF(EXACT('BOM A320 FFS'!B126,obsoleta!D88),"OK","ERROR") -> ERROR | C88: SONIDOS Y COMUNICACIONES | D88: 1000242711000 | F88: RST PELMET 2K71 1% 1/4W 100PPM | G88: CCF552K71FKE36 | H88: VISHAY | J88: 10 | K88: 1 | L88: 10 | M88: EUR | N88: 1 | O88: 10 | P88: CONGELADO | Q88: 45453 | R88: NO | T88: 2 | W88: S1077 | Z88: mmvicente | AA88: ok | AB88: 10
A89: =IF(EXACT('BOM A320 FFS'!B127,obsoleta!D89),"OK","ERROR") -> ERROR | C89: SONIDOS Y COMUNICACIONES | D89: 1229591920606 | F89: CBL EQ USB(A/B) 3M AZ | G89: 182-8838 | H89: RS PRO | J89: 1 | L89: 0 | M89: EUR | N89: 1 | O89: 0 | P89: CONGELADO | Q89: 45453 | R89: NO | T89: 2 | W89: S1077 | Z89: mmvicente | AA89: ok | AB89: 1
A90: =IF(EXACT('BOM A320 FFS'!B128,obsoleta!D90),"OK","ERROR") -> ERROR | C90: SONIDOS Y COMUNICACIONES | D90: 1206500320300 | F90: CNC AUDIO 3M AEREO S/CBL | G90: NC3MX | H90: NEUTRIX | J90: 25 | L90: 0 | M90: GBP | N90: 1.374 | O90: 0 | P90: CONGELADO | Q90: 45453 | R90: NO | T90: 2 | W90: S1077 | Z90: mmvicente | AA90: ok | AB90: 25
A91: =IF(EXACT('BOM A320 FFS'!B131,obsoleta!D91),"OK","ERROR") -> ERROR | C91: SONIDOS Y COMUNICACIONES | D91: 1206500321500 | F91: CNC AUDIO XLR 3M 16A PLUG ACOD SOLD RX | G91: NC3MRX | H91: NEUTRIX | J91: 20 | L91: 0 | M91: EUR | N91: 1 | O91: 0 | P91: CONGELADO | Q91: 45453 | R91: NO | T91: 2 | W91: S1077 | Z91: mmvicente | AA91: ok | AB91: 20
A92: =IF(EXACT('BOM A320 FFS'!B132,obsoleta!D92),"OK","ERROR") -> ERROR | C92: SONIDOS Y COMUNICACIONES | D92: 1587080101200 | F92: ETIQUETA ADH TRANSF TERM 50,8X38,1MM TLS | G92: PTL-107-427 | H92: MARKABLE SOLUTIONS, S.L. | J92: 1 | K92: 55.04 | L92: 55.04 | M92: EUR | N92: 1 | O92: 55.04 | P92: CONGELADO | Q92: 45453 | R92: NO | T92: 2 | W92: S1077 | Z92: mmvicente | AA92: ok | AB92: 1
A93: =IF(EXACT('BOM A320 FFS'!B133,obsoleta!D93),"OK","ERROR") -> ERROR | C93: SONIDOS Y COMUNICACIONES | D93: 1216500320300 | F93: CNC AUDIO 3H AEREO S/CBL | G93: NC3FX | H93: NEUTRIX | J93: 10 | L93: 0 | M93: EUR | N93: 1 | O93: 0 | P93: CONGELADO | Q93: 45453 | R93: NO | T93: 2 | W93: S1077 | Z93: mmvicente | AA93: ok | AB93: 10
A94: =IF(EXACT('BOM A320 FFS'!B134,obsoleta!D94),"OK","ERROR") -> ERROR | C94: SONIDOS Y COMUNICACIONES | D94: 1239024369000 | F94: MANG AUTOSOLD DI=3.68MM L=18.25MM PVDF ROSH | G94: SO96-2-00 | H94: RAYCHEM | J94: 300 | K94: 2.4 | L94: 720 | M94: EUR | N94: 1 | O94: 720 | P94: CONGELADO | Q94: 45453 | R94: NO | T94: 2 | W94: S1077 | Z94: mmvicente | AA94: ok | AB94: 300
A95: =IF(EXACT('BOM A320 FFS'!B135,obsoleta!D95),"OK","ERROR") -> ERROR | C95: SONIDOS Y COMUNICACIONES | D95: 1206500321400 | F95: CNC AUDIO 1/4” 3M PLUG RECT S/CBL PX | G95: NP3X | H95: NEUTRIX | J95: 35 | L95: 0 | M95: EUR | N95: 1 | O95: 0 | P95: CONGELADO | Q95: 45453 | R95: NO | T95: 2 | W95: S1077 | Z95: mmvicente | AA95: ok | AB95: 35
A96: =IF(EXACT('BOM A320 FFS'!B136,obsoleta!D96),"OK","ERROR") -> ERROR | C96: SONIDOS Y COMUNICACIONES | D96: 1580160080000 | F96: SEPARADOR DE LATON ROSCADO Y TORNILLO PR | G96: 221-162 | H96: RS AMIDATA, S.A. | J96: 50 | K96: 0.43 | L96: 21.55 | M96: EUR | N96: 1 | O96: 21.55 | P96: CONGELADO | Q96: 45453 | R96: NO | T96: 2 | W96: S1077 | Z96: mmvicente | AA96: ok | AB96: 50
A97: =IF(EXACT('BOM A320 FFS'!B137,obsoleta!D97),"OK","ERROR") -> ERROR | C97: SONIDOS Y COMUNICACIONES | D97: 1580160050100 | F97: SEPARADOR EX E/C 5 M/H M3X30MM LATON/NI | G97: 221-178 | H97: RS AMIDATA, S.A. | J97: 50 | K97: 0.6 | L97: 30.16 | M97: EUR | N97: 1 | O97: 30.16 | P97: CONGELADO | Q97: 45453 | R97: NO | T97: 2 | W97: S1077 | Z97: mmvicente | AA97: falta | AB97: 50
A98: =IF(EXACT('BOM A320 FFS'!B138,obsoleta!D98),"OK","ERROR") -> ERROR | C98: SONIDOS Y COMUNICACIONES | D98: 1206500320701 | F98: CNC JACK SOCKET 3P/M 6.35MM SOLD N-PL ACODADO | G98: NP3RX | H98: NEUTRIX | J98: 5 | L98: 0 | M98: EUR | N98: 1 | O98: 0 | P98: CONGELADO | Q98: 45453 | R98: NO | T98: 2 | W98: S1077 | Z98: mmvicente | AA98: ok | AB98: 5
A99: =IF(EXACT('BOM A320 FFS'!B139,obsoleta!D99),"OK","ERROR") -> ERROR | C99: SONIDOS Y COMUNICACIONES | D99: 1232025195900 | F99: MANG IDENTIF TERMO 3/4" 3:1 POLIOLE BLAN | G99: TMS-SCE-3/4-2.0-9 | H99: RAYCHEM | J99: 100 | K99: 0.68 | L99: 68 | M99: EUR | N99: 1 | O99: 68 | P99: CONGELADO | Q99: 45453 | R99: NO | T99: 2 | W99: S1077 | Z99: mmvicente | AA99: ok | AB99: 100
A100: =IF(EXACT('BOM A320 FFS'!B141,obsoleta!D100),"OK","ERROR") -> ERROR | C100: SONIDOS Y COMUNICACIONES | D100: 1232024645900 | F100: MANG IDENTIF TERMO 1/4" BLANCO | G100: TMS-SCE-1/4"-9 | H100: RAYCHEM | J100: 100 | K100: 0.53 | L100: 53 | M100: EUR | N100: 1 | O100: 53 | P100: CONGELADO | Q100: 45453 | R100: NO | T100: 2 | W100: S1077 | Z100: mmvicente | AA100: ok | AB100: 100
...

Sheet SAP Equipos Compras
A1: Material | B1: Descripción material | C1: Fecha Sol. | D1: Nº Cesta / Sol | E1: Posición sol. | F1: Estado de la Firma | G1: Nº pedido | H1: Posición ped. | I1: Fecha Ped. | J1: Fe. Entrega | K1: Entrega final | L1: Ind.Borr/Bloq Ped | M1: Estado | N1: Ctd. Solicitada | O1: Ctd. pedido | P1: Ctd. Recepcionada | Q1: Ctd. por recepcionar | R1: Ctd. por inspeccionar | S1: Imp. unitario Ped. | T1: Imp.total pos Ped | U1: Moneda Ped. | V1: P/N fab. Ped | W1: Desc.Proveedor | X1: Elemento PEP | Y1: Almacen | Z1: Bloqueo Compras | AA1: Cant Base Ped. | AB1: Cant.base SP | AC1: Cantidad solicitada | AD1: Carácter longitud 1 | AE1: Centro | AF1: Cl. Pedido | AG1: Clase de operación | AH1: Clase de pedido | AI1: Clave de horizonte | AJ1: Creado por | AK1: CREADOR SP | AL1: Ctd. Aceptada | AM1: Ctd. Aceptada | AN1: Ctd. facturada | AO1: Ctd. por facturar | AP1: Ctd. por recepcionar | AQ1: Ctd. Rechazada | AR1: Desc. Fabricante en ped. | AS1: Desc. Mercado Organizativo (SolPed) | AT1: Descripción de la operación | AU1: Descripción fabricante en sp. | AV1: Dirección de Entrega | AW1: Documentacion | AX1: Entregas (de/a) | AY1: Fabricante en ped. | AZ1: Fabricante en sp | BA1: Fecha de documento | BB1: Fecha de entrada en compras | BC1: Fecha de entrega | BD1: Fecha de fin extrema | BE1: Fecha inicio extrema | BF1: Fecha Liberación | BG1: Fecha-apert. planif. | BH1: Grupo de artículos | BI1: Grupo de artículos Operación | BJ1: Imp.total pos SP | BK1: Imp.unit.SP | BL1: Ind.Borr/Bloq Sol | BM1: Indicador de borrado | BN1: Indicador liberación | BO1: Mercado Organizativo (SolPed) | BP1: Moneda | BQ1: Moneda | BR1: Moneda Ped | BS1: Moneda SP | BT1: Nombre completo | BU1: Número de material Padre | BV1: OP/Grafo | BW1: Orden previsional | BX1: P/N fab. sp. | BY1: Pedido Inmediato | BZ1: Plazo entrega prev. | CA1: Por calcular (cantidad) | CB1: Por calcular (valor) | CC1: Por facturar cantidad. | CD1: Proveedor | CE1: Status | CF1: Texto breve de material | CG1: Texto de cabecera | CH1: Tiempo espera normal | CI1: Tipo cambio | CJ1: Tipo Compra | CK1: Tipo de imputación | CL1: Tmpo.tratamiento EM | CM1: Total EM valor | CN1: Total entrada de mercancía(ctd) | CO1: Total facturas ctd. | CP1: Unid.tmp.nor.espera | CQ1: Unidad | CR1: Unidad | CS1: Unidad de medida | CT1: Unidad de medida | CU1: Unidad medida base | CV1: Unidad medida base | CW1: UnMedidaPrecioPedido | CX1: Valor aceptado | CY1: Valor ctd. aceptada | CZ1: Valor facturado | DA1: Valor por entregar | DB1: Valor por facturar | DC1: Valor por inspeccionar | DD1: Valor por recepcionar | DE1: Valor recepcionado | DF1: Solic. | DG1: Comprador
B2: HW OTP TOKEN 1 YEAR (WITH PROOFING) | C2: 44796 | D2: 1101528754 | E2: 1 | H2: 0 | N2: 1 | O2: 0 | P2: 0 | Q2: 0 | R2: 0 | S2: 0 | T2: 0 | X2: 7218|S22B04_GPR05 | AA2: 0 | AB2: 1 | AE2: 6000 | AJ2: SRM2ERP | AK2: SRM2ERP | AL2: 0 | AN2: 0 | AO2: 0 | AQ2: 0 | AS2: Simulacion | AV2: Calle Mar Egeo,428830San Fernando de Henares | AW2: '@FM@ | AX2: 44796 | BB2: 44796 | BF2: 44796 | BH2: 432411 | BJ2: 105 | BK2: 105 | BO2: 20 | BS2: USD | BT2: María Isabel Recio Gutiérrez | BZ2: 0 | CA2: 0 | CB2: 0 | CH2: 0 | CK2: P | CL2: 0 | CM2: 0.00 | CX2: 0 | CZ2: 0 | DA2: 0.00 | DB2: 0 | DC2: 0 | DD2: 0 | DE2: 0 | DF2: MRECIO | DG2: Sanchez Graciano, Antonio
A3: 1390701500800 | B3: MCDU B737-800 FANS S/OF | C3: 44796 | D3: 1101528790 | E3: 1 | G3: 4600003331 | H3: 10 | I3: 44802 | J3: 45044 | M3: Liberado | N3: 2 | O3: 2 | P3: 0 | Q3: 2 | R3: 0 | S3: 17575 | T3: 35150 | U3: USD | V3: 631-922425-001 | W3: SYMBOLIC DISPLAYS, INC | X3: 7218|S22B04_S1041 | Y3: 8990 | AA3: 1 | AB3: 1 | AE3: 8000 | AF3: Ped. antici. hitos | AH3: ZANT | AJ3: 152028 | AK3: SRM2ERP | AL3: 0 | AN3: 0 | AO3: 2 | AQ3: 0 | AR3: SDI | AS3: Simulacion | AV3: Avenida de la Veguilla,419171Cabanillas del Campo | AW3: '@FM@ | AX3: 44865 | AY3: 9002524 | BB3: 44802 | BC3: 45044 | BF3: 44802 | BH3: 322020 | BJ3: 35150 | BK3: 17575 | BN3: 3 | BO3: 20 | BP3: USD | BR3: USD | BS3: USD | BT3: Arsenio Jiménez Pérez | BZ3: 40 | CA3: 2 | CB3: 35150 | CD3: 1051015 | CH3: 0 | CI3: 0,98795 | CK3: Q | CL3: 8 | CM3: 0.00 | CQ3: UN | CR3: UN | CS3: UN | CT3: UN | CU3: UN | CV3: UN | CW3: UN | CX3: 0 | CZ3: 0 | DA3: 35150.00 | DB3: 35150 | DC3: 0 | DD3: 35150 | DE3: 0 | DF3: AJIMENEZP | DG3: Fernández Carrascal, José Abel
A4: 9999000322010 | B4: N.R. PANELES SIMULADORES | C4: 44796 | D4: 1101528790 | E4: 3 | G4: 4600003331 | H4: 20 | I4: 44802 | J4: 45044 | M4: Liberado | N4: 1 | O4: 1 | P4: 0 | Q4: 1 | R4: 0 | S4: 2700 | T4: 2700 | U4: USD | W4: SYMBOLIC DISPLAYS, INC | X4: 7218|S22B04_S1041 | AA4: 1 | AB4: 1 | AE4: 8000 | AF4: Ped. antici. hitos | AH4: ZANT | AJ4: 152028 | AK4: SRM2ERP | AL4: 0 | AN4: 0 | AO4: 1 | AQ4: 0 | AS4: Simulacion | AV4: Calle Mar Egeo,428830San Fernando de Henares | AW4: '@FM@ | AX4: 44865 | BB4: 44802 | BC4: 45044 | BF4: 44802 | BH4: 322010 | BJ4: 2700 | BK4: 2700 | BN4: 3 | BO4: 20 | BP4: USD | BR4: USD | BS4: USD | BT4: Arsenio Jiménez Pérez | BZ4: 195 | CA4: 1 | CB4: 2700 | CD4: 1051015 | CH4: 0 | CI4: 0,98795 | CK4: P | CL4: 8 | CM4: 0.00 | CQ4: UN | CR4: UN | CS4: UN | CT4: UN | CU4: UN | CV4: UN | CW4: UN | CX4: 0 | CZ4: 0 | DA4: 2700.00 | DB4: 2700 | DC4: 0 | DD4: 2700 | DE4: 0 | DF4: AJIMENEZP | DG4: Fernández Carrascal, José Abel
A5: 1390701500100 | B5: B737-800 DISPLAY UNIT 631-909698-901 | C5: 44796 | D5: 1101528790 | E5: 4 | G5: 4600003331 | H5: 30 | I5: 44802 | J5: 44969 | M5: Liberado | N5: 5 | O5: 5 | P5: 0 | Q5: 5 | R5: 0 | S5: 13310 | T5: 66550 | U5: USD | V5: 631-909698-901 | W5: SYMBOLIC DISPLAYS, INC | X5: 7218|S22B04_S1041 | Y5: 8990 | AA5: 1 | AB5: 1 | AE5: 8000 | AF5: Ped. antici. hitos | AH5: ZANT | AJ5: 152028 | AK5: SRM2ERP | AL5: 0 | AN5: 0 | AO5: 5 | AQ5: 0 | AR5: SDI | AS5: Simulacion | AV5: Avenida de la Veguilla,419171Cabanillas del Campo | AW5: '@FM@ | AX5: 44865 | AY5: 9002524 | BB5: 44802 | BC5: 44969 | BF5: 44827 | BH5: 322020 | BJ5: 66550 | BK5: 13310 | BN5: 3 | BO5: 20 | BP5: USD | BR5: USD | BS5: USD | BT5: Arsenio Jiménez Pérez | BZ5: 4 | CA5: 5 | CB5: 66550 | CD5: 1051015 | CH5: 0 | CI5: 0,98795 | CK5: Q | CL5: 8 | CM5: 0.00 | CQ5: UN | CR5: UN | CS5: UN | CT5: UN | CU5: UN | CV5: UN | CW5: UN | CX5: 0 | CZ5: 0 | DA5: 66550.00 | DB5: 66550 | DC5: 0 | DD5: 66550 | DE5: 0 | DF5: AJIMENEZP | DG5: Fernández Carrascal, José Abel
A6: 1309000611900 | B6: CTL PANEL WEATHER RADAR | C6: 44754 | D6: 1101517813 | E6: 1 | G6: 4200484030 | H6: 10 | I6: 44761 | J6: 44819 | M6: Liberado | N6: 1 | O6: 1 | P6: 1 | Q6: 0 | R6: 1 | S6: 15329.57 | T6: 15329.57 | U6: EUR | V6: 622-5129-802 | W6: AEROFALCON S.L. | X6: 7218|S22B04_S1076 | Y6: 8990 | AA6: 1 | AB6: 1 | AE6: 8000 | AF6: Pedido de materiales | AH6: ZNB | AJ6: 947726 | AK6: SRM2ERP | AL6: 0 | AN6: 0 | AO6: 1 | AQ6: 0 | AR6: ROCKWELL-COLLINS | AS6: Simulacion | AV6: El Rayo (Polig Indust La Quinta,719171Cabanillas del Campo | AW6: '@FM@ | AX6: 44826 | AY6: 9000328 | BB6: 44754 | BC6: 44819 | BF6: 44777 | BH6: 425027 | BJ6: 15329.57 | BK6: 15329.57 | BN6: 3 | BO6: 20 | BP6: EUR | BR6: EUR | BS6: EUR | BT6: María Ángeles Coello Roma | BZ6: 15 | CA6: 1 | CB6: 15329.57 | CD6: 1205312 | CH6: 0 | CI6: 1,00000 | CK6: Q | CL6: 8 | CM6: 15329.57 | CQ6: UN | CR6: UN | CS6: UN | CT6: UN | CU6: UN | CV6: UN | CW6: UN | CX6: 0 | CZ6: 0 | DA6: 0.00 | DB6: 15329.57 | DC6: 15329.57 | DD6: 0 | DE6: 15329.57 | DF6: ACOELLO | DG6: Ortiz Diaz, Carolina
A7: 1390703220100 | B7: CABIN PRESS PANEL SIM REPLI 814392-2-002 | C7: 44753 | D7: 1101517234 | E7: 1 | G7: 4200483039 | H7: 10 | I7: 44755 | J7: 44959 | M7: Liberado | N7: 1 | O7: 1 | P7: 0 | Q7: 1 | R7: 0 | S7: 21270 | T7: 21270 | U7: USD | V7: 10-7829 | W7: SIMTEK, INC | X7: 7218|S22B04_S1076 | Y7: 8990 | AA7: 1 | AB7: 1 | AE7: 8000 | AF7: Pedido de materiales | AH7: ZNB | AJ7: 152028 | AK7: SRM2ERP | AL7: 0 | AN7: 0 | AO7: 1 | AQ7: 0 | AR7: SIMTEK | AS7: Simulacion | AV7: El Rayo (Polig Indust La Quinta,719171Cabanillas del Campo | AW7: '@FM@ | AX7: 44826 | AY7: 9008133 | BC7: 44959 | BH7: 322010 | BJ7: 41300 | BK7: 41300 | BN7: 3 | BO7: 20 | BP7: USD | BR7: USD | BS7: USD | BT7: María Ángeles Coello Roma | BZ7: 142 | CA7: 1 | CB7: 21270 | CD7: 1047453 | CH7: 0 | CI7: 0,96274 | CK7: Q | CL7: 8 | CM7: 0.00 | CQ7: UN | CR7: UN | CS7: UN | CT7: UN | CU7: UN | CV7: UN | CW7: UN | CX7: 0 | CZ7: 0 | DA7: 21270.00 | DB7: 21270 | DC7: 0 | DD7: 21270 | DE7: 0 | DF7: ACOELLO | DG7: Ramos Torreadrado, Carolina
A8: 1390703021100 | B8: RUDDER TRIM POS IND SIM PN: 10166N01N00 | C8: 44753 | D8: 1101517234 | E8: 2 | G8: 4200483039 | H8: 20 | I8: 44755 | J8: 44959 | M8: Liberado | N8: 1 | O8: 1 | P8: 0 | Q8: 1 | R8: 0 | S8: 5330 | T8: 5330 | U8: USD | V8: 10-7774 | W8: SIMTEK, INC | X8: 7218|S22B04_S1076 | Y8: 8990 | AA8: 1 | AB8: 1 | AE8: 8000 | AF8: Pedido de materiales | AH8: ZNB | AJ8: 152028 | AK8: SRM2ERP | AL8: 0 | AN8: 0 | AO8: 1 | AQ8: 0 | AR8: SIMTEK | AS8: Simulacion | AV8: El Rayo (Polig Indust La Quinta,719171Cabanillas del Campo | AW8: '@FM@ | AX8: 44826 | AY8: 9008133 | BB8: 44753 | BC8: 44959 | BF8: 44777 | BH8: 322010 | BJ8: 9980 | BK8: 9980 | BN8: 3 | BO8: 20 | BP8: USD | BR8: USD | BS8: USD | BT8: María Ángeles Coello Roma | BZ8: 15 | CA8: 1 | CB8: 5330 | CD8: 1047453 | CH8: 0 | CI8: 0,96274 | CK8: Q | CL8: 8 | CM8: 0.00 | CQ8: UN | CR8: UN | CS8: UN | CT8: UN | CU8: UN | CV8: UN | CW8: UN | CX8: 0 | CZ8: 0 | DA8: 5330.00 | DB8: 5330 | DC8: 0 | DD8: 5330 | DE8: 0 | DF8: ACOELLO | DG8: Ramos Torreadrado, Carolina
A9: 1390703021000 | B9: ANNUNCIATOR PANEL SIM PN: D434-56-001 | C9: 44753 | D9: 1101517234 | E9: 3 | G9: 4200483039 | H9: 30 | I9: 44755 | J9: 44959 | M9: Liberado | N9: 2 | O9: 2 | P9: 0 | Q9: 2 | R9: 0 | S9: 3780 | T9: 7560 | U9: USD | V9: 10-7773 | W9: SIMTEK, INC | X9: 7218|S22B04_S1076 | Y9: 8990 | AA9: 1 | AB9: 1 | AE9: 8000 | AF9: Pedido de materiales | AH9: ZNB | AJ9: 152028 | AK9: SRM2ERP | AL9: 0 | AN9: 0 | AO9: 2 | AQ9: 0 | AR9: SIMTEK | AS9: Simulacion | AV9: El Rayo (Polig Indust La Quinta,719171Cabanillas del Campo | AW9: '@FM@ | AX9: 44826 | AY9: 9008133 | BC9: 44959 | BH9: 322010 | BJ9: 20430 | BK9: 10215 | BN9: 3 | BO9: 20 | BP9: USD | BR9: USD | BS9: USD | BT9: María Ángeles Coello Roma | BZ9: 15 | CA9: 2 | CB9: 7560 | CD9: 1047453 | CH9: 0 | CI9: 0,96274 | CK9: Q | CL9: 8 | CM9: 0.00 | CQ9: UN | CR9: UN | CS9: UN | CT9: UN | CU9: UN | CV9: UN | CW9: UN | CX9: 0 | CZ9: 0 | DA9: 7560.00 | DB9: 7560 | DC9: 0 | DD9: 7560 | DE9: 0 | DF9: ACOELLO | DG9: Ramos Torreadrado, Carolina
A10: 1390703020900 | B10: COMPASS SIM REPLICA PN: C5L | C10: 44753 | D10: 1101517234 | E10: 4 | G10: 4200483039 | H10: 40 | I10: 44755 | J10: 44959 | M10: Liberado | N10: 1 | O10: 1 | P10: 0 | Q10: 1 | R10: 0 | S10: 3695 | T10: 3695 | U10: USD | V10: 10-7772 | W10: SIMTEK, INC | X10: 7218|S22B04_S1076 | Y10: 8990 | AA10: 1 | AB10: 1 | AE10: 8000 | AF10: Pedido de materiales | AH10: ZNB | AJ10: SRM2ERP | AK10: SRM2ERP | AL10: 0 | AN10: 0 | AO10: 1 | AQ10: 0 | AR10: SIMTEK | AS10: Simulacion | AV10: El Rayo (Polig Indust La Quinta,719171Cabanillas del Campo | AW10: '@FM@ | AX10: 44826 | AY10: 9008133 | BB10: 44753 | BC10: 44959 | BF10: 44777 | BH10: 322010 | BJ10: 7180 | BK10: 7180 | BN10: 3 | BO10: 20 | BP10: USD | BR10: USD | BS10: USD | BT10: María Ángeles Coello Roma | BZ10: 15 | CA10: 1 | CB10: 3695 | CD10: 1047453 | CH10: 0 | CI10: 0,96274 | CK10: Q | CL10: 8 | CM10: 0.00 | CQ10: UN | CR10: UN | CS10: UN | CT10: UN | CU10: UN | CV10: UN | CW10: UN | CX10: 0 | CZ10: 0 | DA10: 3695.00 | DB10: 3695 | DC10: 0 | DD10: 3695 | DE10: 0 | DF10: ACOELLO | DG10: Ramos Torreadrado, Carolina
A11: 1390703020800 | B11: BRAKE PRESSURE IND SIM REPL PN: 163LCP80 | C11: 44753 | D11: 1101517234 | E11: 5 | G11: 4200483039 | H11: 50 | I11: 44755 | J11: 44959 | M11: Liberado | N11: 1 | O11: 1 | P11: 0 | Q11: 1 | R11: 0 | S11: 2755 | T11: 2755 | U11: USD | V11: 10-7771 | W11: SIMTEK, INC | X11: 7218|S22B04_S1076 | Y11: 8990 | AA11: 1 | AB11: 1 | AE11: 8000 | AF11: Pedido de materiales | AH11: ZNB | AJ11: 152028 | AK11: SRM2ERP | AL11: 0 | AN11: 0 | AO11: 1 | AQ11: 0 | AR11: SIMTEK | AS11: Simulacion | AV11: El Rayo (Polig Indust La Quinta,719171Cabanillas del Campo | AW11: '@FM@ | AX11: 44826 | AY11: 9008133 | BB11: 44753 | BC11: 44959 | BF11: 44777 | BH11: 322010 | BJ11: 5350 | BK11: 5350 | BN11: 3 | BO11: 20 | BP11: USD | BR11: USD | BS11: USD | BT11: María Ángeles Coello Roma | BZ11: 15 | CA11: 1 | CB11: 2755 | CD11: 1047453 | CH11: 0 | CI11: 0,96274 | CK11: Q | CL11: 8 | CM11: 0.00 | CQ11: UN | CR11: UN | CS11: UN | CT11: UN | CU11: UN | CV11: UN | CW11: UN | CX11: 0 | CZ11: 0 | DA11: 2755.00 | DB11: 2755 | DC11: 0 | DD11: 2755 | DE11: 0 | DF11: ACOELLO | DG11: Ramos Torreadrado, Carolina
A12: 1390703020700 | B12: FLAP POSITION IND SIM REPL PN: 2061-15-1 | C12: 44753 | D12: 1101517234 | E12: 6 | G12: 4200483039 | H12: 60 | I12: 44755 | J12: 44959 | M12: Liberado | N12: 1 | O12: 1 | P12: 0 | Q12: 1 | R12: 0 | S12: 4175 | T12: 4175 | U12: USD | V12: 10-7770 | W12: SIMTEK, INC | X12: 7218|S22B04_S1076 | Y12: 8990 | AA12: 1 | AB12: 1 | AE12: 8000 | AF12: Pedido de materiales | AH12: ZNB | AJ12: 152028 | AK12: SRM2ERP | AL12: 0 | AN12: 0 | AO12: 1 | AQ12: 0 | AR12: SIMTEK | AS12: Simulacion | AV12: El Rayo (Polig Indust La Quinta,719171Cabanillas del Campo | AW12: '@FM@ | AX12: 44826 | AY12: 9008133 | BB12: 44753 | BC12: 44959 | BF12: 44777 | BH12: 322010 | BJ12: 8110 | BK12: 8110 | BN12: 3 | BO12: 20 | BP12: USD | BR12: USD | BS12: USD | BT12: María Ángeles Coello Roma | BZ12: 15 | CA12: 1 | CB12: 4175 | CD12: 1047453 | CH12: 0 | CI12: 0,96274 | CK12: Q | CL12: 8 | CM12: 0.00 | CQ12: UN | CR12: UN | CS12: UN | CT12: UN | CU12: UN | CV12: UN | CW12: UN | CX12: 0 | CZ12: 0 | DA12: 4175.00 | DB12: 4175 | DC12: 0 | DD12: 4175 | DE12: 0 | DF12: ACOELLO | DG12: Ramos Torreadrado, Carolina
A13: 1390703020600 | B13: OXYGEN PRESSURE IND SIM REPLI PN: 182936 | C13: 44753 | D13: 1101517234 | E13: 7 | G13: 4200483039 | H13: 70 | I13: 44755 | J13: 44959 | M13: Liberado | N13: 1 | O13: 1 | P13: 0 | Q13: 1 | R13: 0 | S13: 2490 | T13: 2490 | U13: USD | V13: 10-7769 | W13: SIMTEK, INC | X13: 7218|S22B04_S1076 | Y13: 8990 | AA13: 1 | AB13: 1 | AE13: 8000 | AF13: Pedido de materiales | AH13: ZNB | AJ13: SRM2ERP | AK13: SRM2ERP | AL13: 0 | AN13: 0 | AO13: 1 | AQ13: 0 | AR13: SIMTEK | AS13: Simulacion | AV13: El Rayo (Polig Indust La Quinta,719171Cabanillas del Campo | AW13: '@FM@ | AX13: 44826 | AY13: 9008133 | BB13: 44753 | BC13: 44959 | BF13: 44777 | BH13: 322010 | BJ13: 3830 | BK13: 3830 | BN13: 3 | BO13: 20 | BP13: USD | BR13: USD | BS13: USD | BT13: María Ángeles Coello Roma | BZ13: 15 | CA13: 1 | CB13: 2490 | CD13: 1047453 | CH13: 0 | CI13: 0,96274 | CK13: Q | CL13: 8 | CM13: 0.00 | CQ13: UN | CR13: UN | CS13: UN | CT13: UN | CU13: UN | CV13: UN | CW13: UN | CX13: 0 | CZ13: 0 | DA13: 2490.00 | DB13: 2490 | DC13: 0 | DD13: 2490 | DE13: 0 | DF13: ACOELLO | DG13: Ramos Torreadrado, Carolina
A14: 1390703020500 | B14: DUCT PRESSURE IND SIM REPLI PN: SEDLOC9C | C14: 44753 | D14: 1101517234 | E14: 8 | G14: 4200483039 | H14: 80 | I14: 44755 | J14: 44959 | M14: Liberado | N14: 1 | O14: 1 | P14: 0 | Q14: 1 | R14: 0 | S14: 4175 | T14: 4175 | U14: USD | V14: 10-7768 | W14: SIMTEK, INC | X14: 7218|S22B04_S1076 | Y14: 8990 | AA14: 1 | AB14: 1 | AE14: 8000 | AF14: Pedido de materiales | AH14: ZNB | AJ14: SRM2ERP | AK14: SRM2ERP | AL14: 0 | AN14: 0 | AO14: 1 | AQ14: 0 | AR14: SIMTEK | AS14: Simulacion | AV14: El Rayo (Polig Indust La Quinta,719171Cabanillas del Campo | AW14: '@FM@ | AX14: 44826 | AY14: 9008133 | BB14: 44753 | BC14: 44959 | BF14: 44777 | BH14: 322010 | BJ14: 8110 | BK14: 8110 | BN14: 3 | BO14: 20 | BP14: USD | BR14: USD | BS14: USD | BT14: María Ángeles Coello Roma | BZ14: 15 | CA14: 1 | CB14: 4175 | CD14: 1047453 | CH14: 0 | CI14: 0,96274 | CK14: Q | CL14: 8 | CM14: 0.00 | CQ14: UN | CR14: UN | CS14: UN | CT14: UN | CU14: UN | CV14: UN | CW14: UN | CX14: 0 | CZ14: 0 | DA14: 4175.00 | DB14: 4175 | DC14: 0 | DD14: 4175 | DE14: 0 | DF14: ACOELLO | DG14: Ramos Torreadrado, Carolina
A15: 1390703020400 | B15: CABIN TEMP IND SIM REPLICA PN: 162BL903 | C15: 44753 | D15: 1101517234 | E15: 9 | G15: 4200483039 | H15: 90 | I15: 44755 | J15: 44959 | M15: Liberado | N15: 1 | O15: 1 | P15: 0 | Q15: 1 | R15: 0 | S15: 2565 | T15: 2565 | U15: USD | V15: 10-7767 | W15: SIMTEK, INC | X15: 7218|S22B04_S1076 | Y15: 8990 | AA15: 1 | AB15: 1 | AE15: 8000 | AF15: Pedido de materiales | AH15: ZNB | AK15: SRM2ERP | AL15: 0 | AN15: 0 | AO15: 1 | AQ15: 0 | AR15: SIMTEK | AS15: Simulacion | AV15: El Rayo (Polig Indust La Quinta,719171Cabanillas del Campo | AW15: '@FM@ | AX15: 44826 | AY15: 9008133 | BC15: 44959 | BH15: 322010 | BJ15: 3830 | BK15: 3830 | BN15: 3 | BO15: 20 | BP15: USD | BR15: USD | BS15: USD | BT15: María Ángeles Coello Roma | BZ15: 15 | CA15: 1 | CB15: 2565 | CD15: 1047453 | CH15: 0 | CI15: 0,96274 | CK15: Q | CL15: 8 | CM15: 0.00 | CQ15: UN | CR15: UN | CS15: UN | CT15: UN | CU15: UN | CV15: UN | CW15: UN | CX15: 0 | CZ15: 0 | DA15: 2565.00 | DB15: 2565 | DC15: 0 | DD15: 2565 | DE15: 0 | DF15: ACOELLO | DG15: Ramos Torreadrado, Carolina
A16: 1390703020300 | B16: CABIN VERTICA SPEED IND SIM PN: WL501RC1 | C16: 44753 | D16: 1101517234 | E16: 10 | G16: 4200483039 | H16: 100 | I16: 44755 | J16: 44959 | M16: Liberado | N16: 1 | O16: 1 | P16: 0 | Q16: 1 | R16: 0 | S16: 2585 | T16: 2585 | U16: USD | V16: 10-7766 | W16: SIMTEK, INC | X16: 7218|S22B04_S1076 | Y16: 8990 | AA16: 1 | AB16: 1 | AE16: 8000 | AF16: Pedido de materiales | AH16: ZNB | AJ16: 152028 | AK16: SRM2ERP | AL16: 0 | AN16: 0 | AO16: 1 | AQ16: 0 | AR16: SIMTEK | AS16: Simulacion | AV16: El Rayo (Polig Indust La Quinta,719171Cabanillas del Campo | AW16: '@FM@ | AX16: 44826 | AY16: 9008133 | BB16: 44753 | BC16: 44959 | BF16: 44777 | BH16: 322010 | BJ16: 5020 | BK16: 5020 | BN16: 3 | BO16: 20 | BP16: USD | BR16: USD | BS16: USD | BT16: María Ángeles Coello Roma | BZ16: 15 | CA16: 1 | CB16: 2585 | CD16: 1047453 | CH16: 0 | CI16: 0,96274 | CK16: Q | CL16: 8 | CM16: 0.00 | CQ16: UN | CR16: UN | CS16: UN | CT16: UN | CU16: UN | CV16: UN | CW16: UN | CX16: 0 | CZ16: 0 | DA16: 2585.00 | DB16: 2585 | DC16: 0 | DD16: 2585 | DE16: 0 | DF16: ACOELLO | DG16: Ramos Torreadrado, Carolina
A17: 1390703020200 | B17: CAB ALT/DIFF PRES IND SIM PN: AW2835AB06 | C17: 44753 | D17: 1101517234 | E17: 11 | G17: 4200483039 | H17: 110 | I17: 44755 | J17: 44959 | M17: Liberado | N17: 1 | O17: 1 | P17: 0 | Q17: 1 | R17: 0 | S17: 4175 | T17: 4175 | U17: USD | V17: 10-7765 | W17: SIMTEK, INC | X17: 7218|S22B04_S1076 | Y17: 8990 | AA17: 1 | AB17: 1 | AE17: 8000 | AF17: Pedido de materiales | AH17: ZNB | AJ17: SRM2ERP | AK17: SRM2ERP | AL17: 0 | AN17: 0 | AO17: 1 | AQ17: 0 | AR17: SIMTEK | AS17: Simulacion | AV17: El Rayo (Polig Indust La Quinta,719171Cabanillas del Campo | AW17: '@FM@ | AX17: 44826 | AY17: 9008133 | BB17: 44753 | BC17: 44959 | BF17: 44777 | BH17: 322010 | BJ17: 8110 | BK17: 8110 | BN17: 3 | BO17: 20 | BP17: USD | BR17: USD | BS17: USD | BT17: María Ángeles Coello Roma | BZ17: 15 | CA17: 1 | CB17: 4175 | CD17: 1047453 | CH17: 0 | CI17: 0,96274 | CK17: Q | CL17: 8 | CM17: 0.00 | CQ17: UN | CR17: UN | CS17: UN | CT17: UN | CU17: UN | CV17: UN | CW17: UN | CX17: 0 | CZ17: 0 | DA17: 4175.00 | DB17: 4175 | DC17: 0 | DD17: 4175 | DE17: 0 | DF17: ACOELLO | DG17: Ramos Torreadrado, Carolina
A18: 1390703020100 | B18: EGT APU SIM REPLICA PN: 152LMA23 | C18: 44753 | D18: 1101517234 | E18: 12 | G18: 4200483039 | H18: 120 | I18: 44755 | J18: 44959 | M18: Liberado | N18: 1 | O18: 1 | P18: 0 | Q18: 1 | R18: 0 | S18: 2565 | T18: 2565 | U18: USD | V18: 10-7764 | W18: SIMTEK, INC | X18: 7218|S22B04_S1076 | Y18: 8990 | AA18: 1 | AB18: 1 | AE18: 8000 | AF18: Pedido de materiales | AH18: ZNB | AJ18: SRM2ERP | AK18: SRM2ERP | AL18: 0 | AN18: 0 | AO18: 1 | AQ18: 0 | AR18: SIMTEK | AS18: Simulacion | AV18: El Rayo (Polig Indust La Quinta,719171Cabanillas del Campo | AW18: '@FM@ | AX18: 44826 | AY18: 9008133 | BB18: 44753 | BC18: 44959 | BF18: 44777 | BH18: 322020 | BJ18: 3980 | BK18: 3980 | BN18: 3 | BO18: 20 | BP18: USD | BR18: USD | BS18: USD | BT18: María Ángeles Coello Roma | BZ18: 15 | CA18: 1 | CB18: 2565 | CD18: 1047453 | CH18: 0 | CI18: 0,96274 | CK18: Q | CL18: 8 | CM18: 0.00 | CQ18: UN | CR18: UN | CS18: UN | CT18: UN | CU18: UN | CV18: UN | CW18: UN | CX18: 0 | CZ18: 0 | DA18: 2565.00 | DB18: 2565 | DC18: 0 | DD18: 2565 | DE18: 0 | DF18: ACOELLO | DG18: Ramos Torreadrado, Carolina
A19: 1390703020000 | B19: FUEL TEMP IND SIM REPLICA PN:162BL801 | C19: 44753 | D19: 1101517234 | E19: 13 | G19: 4200483039 | H19: 130 | I19: 44755 | J19: 44959 | M19: Liberado | N19: 1 | O19: 1 | P19: 0 | Q19: 1 | R19: 0 | S19: 2565 | T19: 2565 | U19: USD | V19: 10-7763 | W19: SIMTEK, INC | X19: 7218|S22B04_S1076 | Y19: 8990 | AA19: 1 | AB19: 1 | AE19: 8000 | AF19: Pedido de materiales | AH19: ZNB | AJ19: 152028 | AK19: SRM2ERP | AL19: 0 | AN19: 0 | AO19: 1 | AQ19: 0 | AR19: SIMTEK | AS19: Simulacion | AV19: El Rayo (Polig Indust La Quinta,719171Cabanillas del Campo | AW19: '@FM@ | AX19: 44826 | AY19: 9008133 | BC19: 44959 | BH19: 322010 | BJ19: 3980 | BK19: 3980 | BN19: 3 | BO19: 20 | BP19: USD | BR19: USD | BS19: USD | BT19: María Ángeles Coello Roma | BZ19: 15 | CA19: 1 | CB19: 2565 | CD19: 1047453 | CH19: 0 | CI19: 0,96274 | CK19: Q | CL19: 8 | CM19: 0.00 | CQ19: UN | CR19: UN | CS19: UN | CT19: UN | CU19: UN | CV19: UN | CW19: UN | CX19: 0 | CZ19: 0 | DA19: 2565.00 | DB19: 2565 | DC19: 0 | DD19: 2565 | DE19: 0 | DF19: ACOELLO | DG19: Ramos Torreadrado, Carolina
A20: 1390703021300 | B20: AIR VALVE POSITION | C20: 44753 | D20: 1101517234 | E20: 14 | G20: 4200483039 | H20: 140 | I20: 44755 | J20: 44959 | M20: Liberado | N20: 2 | O20: 2 | P20: 0 | Q20: 2 | R20: 0 | S20: 1875 | T20: 3750 | U20: USD | V20: 51-0230-01 | W20: SIMTEK, INC | X20: 7218|S22B04_S1076 | Y20: 8990 | AA20: 1 | AB20: 1 | AE20: 8000 | AF20: Pedido de materiales | AH20: ZNB | AJ20: 152028 | AK20: SRM2ERP | AL20: 0 | AN20: 0 | AO20: 2 | AQ20: 0 | AR20: SIMTEK | AS20: Simulacion | AV20: El Rayo (Polig Indust La Quinta,719171Cabanillas del Campo | AW20: '@FM@ | AX20: 44826 | AY20: 9008133 | BC20: 44959 | BH20: 322020 | BJ20: 2510 | BK20: 1255 | BN20: 3 | BO20: 20 | BP20: USD | BR20: USD | BS20: USD | BT20: María Ángeles Coello Roma | BZ20: 204 | CA20: 2 | CB20: 3750 | CD20: 1047453 | CH20: 0 | CI20: 0,96274 | CK20: Q | CL20: 8 | CM20: 0.00 | CQ20: UN | CR20: UN | CS20: UN | CT20: UN | CU20: UN | CV20: UN | CW20: UN | CX20: 0 | CZ20: 0 | DA20: 3750.00 | DB20: 3750 | DC20: 0 | DD20: 3750 | DE20: 0 | DF20: ACOELLO | DG20: Ramos Torreadrado, Carolina
A21: 1390702740000 | B21: CLOCK | C21: 44750 | D21: 1101516960 | E21: 1 | G21: 4200482994 | H21: 10 | I21: 44755 | J21: 44772 | M21: Generado documento | N21: 2 | O21: 2 | P21: 0 | Q21: 2 | R21: 0 | S21: 8659 | T21: 17318 | U21: USD | V21: 9010-1-3 | W21: THE BOEING COMPANY | X21: 7218|S22B04_S1076 | Y21: 8990 | AA21: 1 | AB21: 1 | AE21: 8000 | AF21: Pedido de materiales | AH21: ZNB | AJ21: SRM2ERP | AK21: SRM2ERP | AL21: 0 | AN21: 0 | AO21: 2 | AQ21: 0 | AR21: AVTECH CORPORATION | AS21: Simulacion | AV21: El Rayo (Polig Indust La Quinta,719171Cabanillas del Campo | AW21: '@FM@ | AX21: 44820 | AY21: 9010466 | BB21: 44753 | BC21: 44772 | BF21: 44760 | BH21: 322010 | BJ21: 17318 | BK21: 8659 | BN21: X | BO21: 20 | BP21: USD | BR21: USD | BS21: USD | BT21: María Ángeles Coello Roma | BZ21: 28 | CA21: 2 | CB21: 17318 | CD21: 1046021 | CH21: 0 | CI21: 0,96274 | CK21: Q | CL21: 8 | CM21: 0.00 | CQ21: UN | CR21: UN | CS21: UN | CT21: UN | CU21: UN | CV21: UN | CW21: UN | CX21: 0 | CZ21: 0 | DA21: 17318.00 | DB21: 17318 | DC21: 0 | DD21: 17318 | DE21: 0 | DF21: ACOELLO | DG21: Ramos Torreadrado, Carolina
A22: 1390702720000 | B22: REMOTE LIGHT SENSOR | C22: 44750 | D22: 1101516960 | E22: 2 | G22: 4200482994 | H22: 20 | I22: 44755 | J22: 45019 | M22: Generado documento | N22: 2 | O22: 2 | P22: 0 | Q22: 2 | R22: 0 | S22: 10970 | T22: 21940 | U22: USD | V22: 4082740-901 | W22: THE BOEING COMPANY | X22: 7218|S22B04_S1076 | Y22: 8990 | AA22: 1 | AB22: 1 | AE22: 8000 | AF22: Pedido de materiales | AH22: ZNB | AK22: SRM2ERP | AL22: 0 | AN22: 0 | AO22: 2 | AQ22: 0 | AR22: HONEYWELL INC | AS22: Simulacion | AV22: El Rayo (Polig Indust La Quinta,719171Cabanillas del Campo | AW22: '@FM@ | AX22: 44820 | AY22: 9003555 | BC22: 45019 | BH22: 322020 | BJ22: 21940 | BK22: 10970 | BN22: X | BO22: 20 | BP22: USD | BR22: USD | BS22: USD | BT22: María Ángeles Coello Roma | BZ22: 25 | CA22: 2 | CB22: 21940 | CD22: 1046021 | CH22: 0 | CI22: 0,96274 | CK22: Q | CL22: 8 | CM22: 0.00 | CQ22: UN | CR22: UN | CS22: UN | CT22: UN | CU22: UN | CV22: UN | CW22: UN | CX22: 0 | CZ22: 0 | DA22: 21940.00 | DB22: 21940 | DC22: 0 | DD22: 21940 | DE22: 0 | DF22: ACOELLO | DG22: Ramos Torreadrado, Carolina
A23: 1390705171100 | B23: PANEL ASSY-MAP/CHART LT CONT P23-1 | C23: 44750 | D23: 1101516960 | E23: 3 | G23: 4200482994 | H23: 30 | I23: 44755 | J23: 44772 | M23: Generado documento | N23: 1 | O23: 1 | P23: 0 | Q23: 1 | R23: 0 | S23: 13147 | T23: 13147 | U23: USD | V23: 233A7202-3 | W23: THE BOEING COMPANY | X23: 7218|S22B04_S1076 | Y23: 8990 | AA23: 1 | AB23: 1 | AE23: 8000 | AF23: Pedido de materiales | AH23: ZNB | AK23: SRM2ERP | AL23: 0 | AN23: 0 | AO23: 1 | AQ23: 0 | AR23: BAE SYSTEMS | AS23: Simulacion | AV23: El Rayo (Polig Indust La Quinta,719171Cabanillas del Campo | AW23: '@FM@ | AX23: 44820 | AY23: 9008109 | BC23: 44772 | BH23: 322020 | BJ23: 13147 | BK23: 13147 | BN23: X | BO23: 20 | BP23: USD | BR23: USD | BS23: USD | BT23: María Ángeles Coello Roma | BZ23: 40 | CA23: 1 | CB23: 13147 | CD23: 1046021 | CH23: 0 | CI23: 0,96274 | CK23: Q | CL23: 8 | CM23: 0.00 | CQ23: UN | CR23: UN | CS23: UN | CT23: UN | CU23: UN | CV23: UN | CW23: UN | CX23: 0 | CZ23: 0 | DA23: 13147.00 | DB23: 13147 | DC23: 0 | DD23: 13147 | DE23: 0 | DF23: ACOELLO | DG23: Ramos Torreadrado, Carolina
A24: 1390705170700 | B24: MOD ASSY-ENG/APU FIRE CONTROL P8-01 | C24: 44750 | D24: 1101516960 | E24: 4 | G24: 4200482994 | H24: 40 | I24: 44755 | J24: 44790 | M24: Generado documento | N24: 1 | O24: 1 | P24: 0 | Q24: 1 | R24: 0 | S24: 69459 | T24: 69459 | U24: USD | V24: 69-37307-300 | W24: THE BOEING COMPANY | X24: 7218|S22B04_S1076 | Y24: 8990 | AA24: 1 | AB24: 1 | AE24: 8000 | AF24: Pedido de materiales | AH24: ZNB | AJ24: 491051 | AK24: SRM2ERP | AL24: 0 | AN24: 0 | AO24: 1 | AQ24: 0 | AR24: BAE SYSTEMS | AS24: Simulacion | AV24: El Rayo (Polig Indust La Quinta,719171Cabanillas del Campo | AW24: '@FM@ | AX24: 44820 | AY24: 9008109 | BC24: 44790 | BH24: 322020 | BJ24: 69459 | BK24: 69459 | BN24: X | BO24: 20 | BP24: USD | BR24: USD | BS24: USD | BT24: María Ángeles Coello Roma | BZ24: 40 | CA24: 1 | CB24: 69459 | CD24: 1046021 | CH24: 0 | CI24: 0,96274 | CK24: Q | CL24: 8 | CM24: 0.00 | CQ24: UN | CR24: UN | CS24: UN | CT24: UN | CU24: UN | CV24: UN | CW24: UN | CX24: 0 | CZ24: 0 | DA24: 69459.00 | DB24: 69459 | DC24: 0 | DD24: 69459 | DE24: 0 | DF24: ACOELLO | DG24: Ramos Torreadrado, Carolina
A25: 1390705170800 | B25: MOD ASSY-RUD TRIM P8-43 | C25: 44750 | D25: 1101516960 | E25: 5 | G25: 4200482994 | H25: 50 | I25: 44755 | J25: 44772 | M25: Generado documento | N25: 1 | O25: 1 | P25: 0 | Q25: 1 | R25: 0 | S25: 17005 | T25: 17005 | U25: USD | V25: 69-73703-313 | W25: THE BOEING COMPANY | X25: 7218|S22B04_S1076 | Y25: 8990 | AA25: 1 | AB25: 1 | AE25: 8000 | AF25: Pedido de materiales | AH25: ZNB | AJ25: 491051 | AK25: SRM2ERP | AL25: 0 | AN25: 0 | AO25: 1 | AQ25: 0 | AR25: BAE SYSTEMS | AS25: Simulacion | AV25: El Rayo (Polig Indust La Quinta,719171Cabanillas del Campo | AW25: '@FM@ | AX25: 44820 | AY25: 9008109 | BB25: 44753 | BC25: 44772 | BF25: 44753 | BH25: 322020 | BJ25: 17005 | BK25: 17005 | BN25: X | BO25: 20 | BP25: USD | BR25: USD | BS25: USD | BT25: María Ángeles Coello Roma | BZ25: 40 | CA25: 1 | CB25: 17005 | CD25: 1046021 | CH25: 0 | CI25: 0,96274 | CK25: Q | CL25: 8 | CM25: 0.00 | CQ25: UN | CR25: UN | CS25: UN | CT25: UN | CU25: UN | CV25: UN | CW25: UN | CX25: 0 | CZ25: 0 | DA25: 17005.00 | DB25: 17005 | DC25: 0 | DD25: 17005 | DE25: 0 | DF25: ACOELLO | DG25: Ramos Torreadrado, Carolina
A26: 1390705170900 | B26: MOD ASSY-FLOOD AND PNL LIGHTING P8-50 | C26: 44750 | D26: 1101516960 | E26: 6 | G26: 4200482994 | H26: 60 | I26: 44755 | J26: 44772 | M26: Generado documento | N26: 1 | O26: 1 | P26: 0 | Q26: 1 | R26: 0 | S26: 10111 | T26: 10111 | U26: USD | V26: 69-76435-305 | W26: THE BOEING COMPANY | X26: 7218|S22B04_S1076 | Y26: 8990 | AA26: 1 | AB26: 1 | AE26: 8000 | AF26: Pedido de materiales | AH26: ZNB | AJ26: 491051 | AK26: SRM2ERP | AL26: 0 | AN26: 0 | AO26: 1 | AQ26: 0 | AR26: BAE SYSTEMS | AS26: Simulacion | AV26: El Rayo (Polig Indust La Quinta,719171Cabanillas del Campo | AW26: '@FM@ | AX26: 44820 | AY26: 9008109 | BB26: 44753 | BC26: 44772 | BF26: 44753 | BH26: 322020 | BJ26: 10111 | BK26: 10111 | BN26: X | BO26: 20 | BP26: USD | BR26: USD | BS26: USD | BT26: María Ángeles Coello Roma | BZ26: 40 | CA26: 1 | CB26: 10111 | CD26: 1046021 | CH26: 0 | CI26: 0,96274 | CK26: Q | CL26: 8 | CM26: 0.00 | CQ26: UN | CR26: UN | CS26: UN | CT26: UN | CU26: UN | CV26: UN | CW26: UN | CX26: 0 | CZ26: 0 | DA26: 10111.00 | DB26: 10111 | DC26: 0 | DD26: 10111 | DE26: 0 | DF26: ACOELLO | DG26: Ramos Torreadrado, Carolina
A27: 1390705171200 | B27: MOD ASSY ENGINE AND WING ANTI-ICE P5-11 | C27: 44750 | D27: 1101516960 | E27: 7 | G27: 4200482994 | H27: 70 | I27: 44755 | J27: 44972 | M27: Generado documento | N27: 1 | O27: 1 | P27: 0 | Q27: 1 | R27: 0 | S27: 47060 | T27: 47060 | U27: USD | V27: 69-37320-3114 | W27: THE BOEING COMPANY | X27: 7218|S22B04_S1076 | Y27: 8990 | AA27: 1 | AB27: 1 | AE27: 8000 | AF27: Pedido de materiales | AH27: ZNB | AJ27: 491051 | AK27: SRM2ERP | AL27: 0 | AN27: 0 | AO27: 1 | AQ27: 0 | AR27: BAE SYSTEMS | AS27: Simulacion | AV27: El Rayo (Polig Indust La Quinta,719171Cabanillas del Campo | AW27: '@FM@ | AX27: 44820 | AY27: 9008109 | BB27: 44753 | BC27: 44972 | BF27: 44753 | BH27: 322020 | BJ27: 47060 | BK27: 47060 | BN27: X | BO27: 20 | BP27: USD | BR27: USD | BS27: USD | BT27: María Ángeles Coello Roma | BZ27: 40 | CA27: 1 | CB27: 47060 | CD27: 1046021 | CH27: 0 | CI27: 0,96274 | CK27: Q | CL27: 8 | CM27: 0.00 | CQ27: UN | CR27: UN | CS27: UN | CT27: UN | CU27: UN | CV27: UN | CW27: UN | CX27: 0 | CZ27: 0 | DA27: 47060.00 | DB27: 47060 | DC27: 0 | DD27: 47060 | DE27: 0 | DF27: ACOELLO | DG27: Ramos Torreadrado, Carolina
A28: 1390702790100 | B28: COCKPIT SPEAKER ASSY | C28: 44750 | D28: 1101517004 | E28: 1 | G28: 4200482968 | H28: 10 | I28: 44755 | J28: 44827 | M28: Liberado | N28: 2 | O28: 2 | P28: 0 | Q28: 2 | R28: 0 | S28: 3612.12 | T28: 7224.24 | U28: EUR | V28: 10-62090-30 | W28: EUROPAVIA ESPAÑA S.A. | X28: 7218|S22B04_S1076 | Y28: 8990 | AA28: 1 | AB28: 1 | AE28: 8000 | AF28: Pedido de materiales | AH28: ZNB | AJ28: 420046 | AK28: SRM2ERP | AL28: 0 | AN28: 0 | AO28: 2 | AQ28: 0 | AR28: AVTECH CORPORATION | AS28: Simulacion | AV28: El Rayo (Polig Indust La Quinta,719171Cabanillas del Campo | AW28: '@FM@ | AX28: 44820 | AY28: 9010466 | BC28: 44827 | BH28: 322010 | BJ28: 7224.24 | BK28: 3612.12 | BN28: 3 | BO28: 20 | BP28: EUR | BR28: EUR | BS28: EUR | BT28: María Ángeles Coello Roma | BZ28: 17 | CA28: 2 | CB28: 7224.24 | CD28: 1009691 | CH28: 0 | CI28: 1,00000 | CK28: Q | CL28: 8 | CM28: 0.00 | CQ28: UN | CR28: UN | CS28: UN | CT28: UN | CU28: UN | CV28: UN | CW28: UN | CX28: 0 | CZ28: 0 | DA28: 7224.24 | DB28: 7224.24 | DC28: 0 | DD28: 7224.24 | DE28: 0 | DF28: ACOELLO | DG28: Aguado Blanco, Ana María
B29: INSTALLATION ASISTANCE | C29: 44749 | D29: 1101516535 | E29: 1 | G29: 4300285652 | H29: 10 | I29: 44750 | J29: 45026 | M29: Liberado | N29: 1 | O29: 1 | P29: 0 | Q29: 0 | R29: 0 | S29: 5200 | T29: 5200 | U29: EUR | W29: MOOG, B.V. | X29: 7218|S22B04_S107E | AA29: 1 | AB29: 1 | AE29: 8000 | AF29: Ped. cerrado servic. | AH29: ZSE1 | AJ29: 491051 | AK29: SRM2ERP | AL29: 0 | AN29: 0 | AO29: 1 | AQ29: 0 | AS29: Simulacion | AV29: Calle Mar Egeo,428830San Fernando de Henares | AW29: '@FM@ | AX29: 44834 | BC29: 45026 | BH29: 721519 | BJ29: 5200 | BK29: 5200 | BN29: 3 | BO29: 20 | BP29: EUR | BR29: EUR | BS29: EUR | BT29: María Ángeles Coello Roma | BZ29: 0 | CA29: 1 | CB29: 5200 | CD29: 1052878 | CH29: 0 | CI29: 1,00000 | CJ29: PO | CK29: P | CL29: 0 | CM29: 0.00 | CQ29: UA | CR29: UA | CS29: N/A | CT29: N/A | CV29: UA | CW29: UA | CX29: 0 | CZ29: 0 | DA29: 5200.00 | DB29: 5200 | DC29: 0 | DD29: 5200 | DE29: 0 | DF29: ACOELLO | DG29: Ramos Torreadrado, Carolina
B30: TUNING | C30: 44749 | D30: 1101516535 | E30: 2 | G30: 4300285652 | H30: 20 | I30: 44750 | J30: 45107 | M30: Liberado | N30: 1 | O30: 1 | P30: 0 | Q30: 0 | R30: 0 | S30: 6560 | T30: 6560 | U30: EUR | W30: MOOG, B.V. | X30: 7218|S22B04_S107E | AA30: 1 | AB30: 1 | AE30: 8000 | AF30: Ped. cerrado servic. | AH30: ZSE1 | AJ30: SRM2ERP | AK30: SRM2ERP | AL30: 0 | AN30: 0 | AO30: 1 | AQ30: 0 | AS30: Simulacion | AV30: Calle Mar Egeo,428830San Fernando de Henares | AW30: '@FM@ | AX30: 44834 | BB30: 44749 | BC30: 45107 | BF30: 44749 | BH30: 721519 | BJ30: 6560 | BK30: 6560 | BN30: 3 | BO30: 20 | BP30: EUR | BR30: EUR | BS30: EUR | BT30: María Ángeles Coello Roma | BZ30: 0 | CA30: 1 | CB30: 6560 | CD30: 1052878 | CH30: 0 | CI30: 1,00000 | CJ30: PO | CK30: P | CL30: 0 | CM30: 0.00 | CQ30: UA | CR30: UA | CS30: N/A | CT30: N/A | CV30: UA | CW30: UA | CX30: 0 | CZ30: 0 | DA30: 6560.00 | DB30: 6560 | DC30: 0 | DD30: 6560 | DE30: 0 | DF30: ACOELLO | DG30: Ramos Torreadrado, Carolina
A31: 1390705333000 | B31: DISPOSITIVO SIMULACION VISUAL IG + WXR | C31: 44747 | D31: 1101515529 | E31: 1 | G31: 4200482135 | H31: 10 | I31: 44748 | J31: 44810 | K31: X | M31: Liberado | N31: 1 | O31: 1 | P31: 0 | Q31: 1 | R31: 0 | S31: 663598 | T31: 663598 | U31: GBP | V31: 946-00C6-100_REVD EP-8100 | W31: ROCKWELL COLLINS UK LTD | X31: 7218|S22B04_P1023311 | Y31: 8990 | AA31: 1 | AB31: 1 | AE31: 8000 | AF31: Pedido de materiales | AH31: ZNB | AK31: SRM2ERP | AL31: 0 | AN31: 0 | AO31: 1 | AQ31: 0 | AR31: ROCKWELL-COLLINS | AS31: Simulacion | AV31: El Rayo (Polig Indust La Quinta,719171Cabanillas del Campo | AW31: '@FM@ | AX31: 44810 | AY31: 9000328 | BC31: 44810 | BH31: 322020 | BJ31: 663598 | BK31: 663598 | BN31: 3 | BO31: 20 | BP31: GBP | BR31: GBP | BS31: GBP | BT31: María Ángeles Coello Roma | BZ31: 40 | CA31: 1 | CB31: 663598 | CD31: 1051399 | CH31: 0 | CI31: 1,16523 | CJ31: PO | CK31: Q | CL31: 8 | CM31: 0.00 | CQ31: UN | CR31: UN | CS31: UN | CT31: UN | CU31: UN | CV31: UN | CW31: UN | CX31: 0 | CZ31: 0 | DA31: 663598.00 | DB31: 663598 | DC31: 0 | DD31: 663598 | DE31: 0 | DF31: ACOELLO | DG31: Ramos Torreadrado, Carolina
A32: 1390705330000 | B32: HUD COMPUTER B737 | C32: 44740 | D32: 1101513085 | E32: 1 | G32: 4200482123 | H32: 10 | I32: 44748 | J32: 45075 | M32: Liberado | N32: 1 | O32: 1 | P32: 0 | Q32: 1 | R32: 0 | S32: 169524 | T32: 169524 | U32: USD | V32: 1500-2460-004 | W32: ROCKWELL COLLINS UK LTD | X32: 7218|S22B04_S1076 | Y32: 6990 | AA32: 1 | AB32: 1 | AE32: 6000 | AF32: Pedido de materiales | AH32: ZNB | AJ32: 491051 | AK32: SRM2ERP | AL32: 0 | AN32: 0 | AO32: 1 | AQ32: 0 | AR32: ROCKWELL-COLLINS | AS32: Simulacion | AV32: El Rayo (Polig Indust La Quinta,719171Cabanillas del Campo | AW32: '@FM@ | AX32: 45075 | AY32: 9000328 | BC32: 45075 | BH32: 322010 | BJ32: 169524 | BK32: 169524 | BN32: 3 | BO32: 20 | BP32: USD | BR32: USD | BS32: USD | BT32: María Isabel Recio Gutiérrez | BZ32: 40 | CA32: 1 | CB32: 169524 | CD32: 1051399 | CH32: 0 | CI32: 0,96274 | CJ32: PO | CK32: Q | CL32: 8 | CM32: 0.00 | CQ32: UN | CR32: UN | CS32: UN | CT32: UN | CU32: UN | CV32: UN | CW32: UN | CX32: 0 | CZ32: 0 | DA32: 169524.00 | DB32: 169524 | DC32: 0 | DD32: 169524 | DE32: 0 | DF32: MRECIO | DG32: Ramos Torreadrado, Carolina
A33: 1390705320000 | B33: HUD OVERHEAD UNIT | C33: 44740 | D33: 1101513085 | E33: 2 | G33: 4200482123 | H33: 20 | I33: 44748 | J33: 45075 | M33: Liberado | N33: 1 | O33: 1 | P33: 0 | Q33: 1 | R33: 0 | S33: 296068 | T33: 296068 | U33: USD | V33: 1500-2360-001 | W33: ROCKWELL COLLINS UK LTD | X33: 7218|S22B04_S1076 | Y33: 6990 | AA33: 1 | AB33: 1 | AE33: 6000 | AF33: Pedido de materiales | AH33: ZNB | AJ33: 491051 | AK33: SRM2ERP | AL33: 0 | AN33: 0 | AO33: 1 | AQ33: 0 | AR33: ROCKWELL-COLLINS | AS33: Simulacion | AV33: El Rayo (Polig Indust La Quinta,719171Cabanillas del Campo | AX33: 45075 | AY33: 9000328 | BC33: 45075 | BH33: 322010 | BJ33: 296068 | BK33: 296068 | BN33: 3 | BO33: 20 | BP33: USD | BR33: USD | BS33: USD | BT33: María Isabel Recio Gutiérrez | BZ33: 40 | CA33: 1 | CB33: 296068 | CD33: 1051399 | CH33: 0 | CI33: 0,96274 | CJ33: PO | CK33: Q | CL33: 8 | CM33: 0.00 | CQ33: UN | CR33: UN | CS33: UN | CT33: UN | CU33: UN | CV33: UN | CW33: UN | CX33: 0 | CZ33: 0 | DA33: 296068.00 | DB33: 296068 | DC33: 0 | DD33: 296068 | DE33: 0 | DF33: MRECIO | DG33: Ramos Torreadrado, Carolina
A34: 1390704460200 | B34: SIMULADOR PANEL CTR SIMMMR 737 PLUG&PLAY | C34: 44735 | D34: 1101511711 | E34: 1 | G34: 4200482272 | H34: 10 | I34: 44749 | J34: 44798 | M34: Generado documento | N34: 2 | O34: 2 | P34: 0 | Q34: 2 | R34: 0 | S34: 23000 | T34: 46000 | U34: USD | V34: C01-2200-321 | W34: THE BOEING COMPANY | X34: 7218|S22B04_S1076 | Y34: 6990 | AA34: 1 | AB34: 1 | AE34: 6000 | AF34: Pedido de materiales | AH34: ZNB | AJ34: 491051 | AK34: SRM2ERP | AL34: 0 | AN34: 0 | AO34: 2 | AQ34: 0 | AR34: BOEING | AS34: Simulacion | AV34: El Rayo (Polig Indust La Quinta,719171Cabanillas del Campo | AW34: '@FM@ | AX34: 44798 | AY34: 9000332 | BB34: 44739 | BC34: 44798 | BF34: 44739 | BH34: 322010 | BJ34: 31800 | BK34: 15900 | BN34: X | BO34: 20 | BP34: USD | BR34: USD | BS34: USD | BT34: María Isabel Recio Gutiérrez | BZ34: 40 | CA34: 2 | CB34: 46000 | CD34: 1046021 | CH34: 0 | CI34: 0,96274 | CJ34: PO | CK34: Q | CL34: 8 | CM34: 0.00 | CQ34: UN | CR34: UN | CS34: UN | CT34: UN | CU34: UN | CV34: UN | CW34: UN | CX34: 0 | CZ34: 0 | DA34: 46000.00 | DB34: 46000 | DC34: 0 | DD34: 46000 | DE34: 0 | DF34: MRECIO | DG34: Ramos Torreadrado, Carolina
A35: 1390705340000 | B35: PANEL SINTONIZACION RADIO SIMULA 737 | C35: 44735 | D35: 1101511711 | E35: 2 | G35: 4200482272 | H35: 20 | I35: 44749 | J35: 44798 | M35: Generado documento | N35: 2 | O35: 2 | P35: 0 | Q35: 2 | R35: 0 | S35: 15600 | T35: 31200 | U35: USD | V35: C01-1600-321 | W35: THE BOEING COMPANY | X35: 7218|S22B04_S1076 | Y35: 6990 | AA35: 1 | AB35: 1 | AE35: 6000 | AF35: Pedido de materiales | AH35: ZNB | AJ35: 491051 | AK35: SRM2ERP | AL35: 0 | AN35: 0 | AO35: 2 | AQ35: 0 | AR35: BOEING | AS35: Simulacion | AV35: El Rayo (Polig Indust La Quinta,719171Cabanillas del Campo | AW35: '@FM@ | AX35: 44848 | AY35: 9000332 | BB35: 44739 | BC35: 44798 | BF35: 44774 | BH35: 322010 | BJ35: 31200 | BK35: 15600 | BN35: X | BO35: 20 | BP35: USD | BR35: USD | BS35: USD | BT35: María Isabel Recio Gutiérrez | BZ35: 40 | CA35: 2 | CB35: 31200 | CD35: 1046021 | CH35: 0 | CI35: 0,96274 | CJ35: PO | CK35: Q | CL35: 8 | CM35: 0.00 | CQ35: UN | CR35: UN | CS35: UN | CT35: UN | CU35: UN | CV35: UN | CW35: UN | CX35: 0 | CZ35: 0 | DA35: 31200.00 | DB35: 31200 | DC35: 0 | DD35: 31200 | DE35: 0 | DF35: MRECIO | DG35: Ramos Torreadrado, Carolina
A36: 1390704460300 | B36: SIMULADOR 737NG SIMEFIS PLUG-AND-PLAY | C36: 44735 | D36: 1101511711 | E36: 3 | G36: 4200482272 | H36: 30 | I36: 44749 | J36: 45152 | M36: Generado documento | N36: 2 | O36: 2 | P36: 0 | Q36: 2 | R36: 0 | S36: 23300 | T36: 46600 | U36: USD | V36: C01-1300-322 | W36: THE BOEING COMPANY | X36: 7218|S22B04_S1076 | Y36: 6990 | AA36: 1 | AB36: 1 | AE36: 6000 | AF36: Pedido de materiales | AH36: ZNB | AJ36: 491051 | AK36: SRM2ERP | AL36: 0 | AN36: 0 | AO36: 2 | AQ36: 0 | AR36: BOEING | AS36: Simulacion | AV36: El Rayo (Polig Indust La Quinta,719171Cabanillas del Campo | AW36: '@FM@ | AX36: 45134 | AY36: 9000332 | BB36: 44739 | BC36: 45152 | BF36: 45062 | BH36: 322010 | BJ36: 46600 | BK36: 23300 | BN36: X | BO36: 20 | BP36: USD | BR36: USD | BS36: USD | BT36: María Isabel Recio Gutiérrez | BZ36: 40 | CA36: 2 | CB36: 46600 | CD36: 1046021 | CH36: 0 | CI36: 0,96274 | CJ36: PO | CK36: Q | CL36: 8 | CM36: 0.00 | CQ36: UN | CR36: UN | CS36: UN | CT36: UN | CU36: UN | CV36: UN | CW36: UN | CX36: 0 | CZ36: 0 | DA36: 46600.00 | DB36: 46600 | DC36: 0 | DD36: 46600 | DE36: 0 | DF36: MRECIO | DG36: Ramos Torreadrado, Carolina
B37: SOLICITUD NORMA IEC 62443-4-2 | C37: 44734 | D37: 1101511444 | E37: 1 | G37: 4300285002 | H37: 10 | I37: 44740 | J37: 44834 | M37: Liberado | N37: 1 | O37: 1 | P37: 0 | Q37: 0 | R37: 0 | S37: 1000 | T37: 1000 | U37: USD | W37: IHS MARKIT GLOBAL SARL | X37: 7218|S22B04_GPR05 | AA37: 1 | AB37: 1 | AE37: 6000 | AF37: Ped. cerrado servic. | AH37: ZSE1 | AJ37: 152074 | AK37: SRM2ERP | AL37: 0 | AN37: 0 | AO37: 1 | AQ37: 0 | AS37: Simulacion | AV37: Calle Mar Egeo,428830San Fernando de Henares | AW37: '@FM@ | AX37: 44741 | BB37: 44736 | BC37: 44834 | BF37: 44736 | BH37: 651015 | BJ37: 1000 | BK37: 1000 | BN37: 3 | BO37: 20 | BP37: USD | BR37: USD | BS37: USD | BT37: María Isabel Recio Gutiérrez | BZ37: 0 | CA37: 1 | CB37: 1000 | CD37: 1222355 | CH37: 0 | CI37: 0,93345 | CJ37: PO | CK37: P | CL37: 0 | CM37: 1000.00 | CQ37: UA | CR37: UA | CS37: N/A | CT37: N/A | CV37: UA | CW37: UA | CX37: 0 | CZ37: 0 | DA37: 0.00 | DB37: 1000 | DC37: 0 | DD37: 0 | DE37: 1000 | DF37: MRECIO | DG37: Fernández Fernández, María
A38: 3166099900092 | B38: MANTENIMIENTO Y GARANTIA DE SOFTWARE | C38: 44728 | D38: 1101509442 | E38: 1 | G38: 4200481467 | H38: 10 | I38: 44743 | J38: 44748 | M38: Liberado | N38: 1 | O38: 1 | P38: 0 | Q38: 1 | R38: 0 | S38: 5000 | T38: 5000 | U38: USD | V38: 3166099900092 | W38: GE AVIATION SYSTEMS LLC | X38: 7218|S22B04_S1041 | AA38: 1 | AB38: 1 | AE38: 6000 | AF38: Pedido de materiales | AH38: ZNB | AJ38: 945547 | AK38: SRM2ERP | AL38: 0 | AN38: 0 | AO38: 1 | AQ38: 0 | AR38: OTROS FABRICANTES | AS38: Simulacion | AV38: Calle Mar Egeo,428830San Fernando de Henares | AW38: '@FM@ | AX38: 44748 | AY38: 9003222 | BB38: 44728 | BC38: 44748 | BF38: 44728 | BH38: 432411 | BJ38: 5000 | BK38: 5000 | BN38: 3 | BO38: 20 | BP38: USD | BR38: USD | BS38: USD | BT38: María Isabel Recio Gutiérrez | BZ38: 85 | CA38: 1 | CB38: 5000 | CD38: 1165101 | CH38: 0 | CI38: 0,93345 | CJ38: PO | CK38: P | CL38: 8 | CM38: 0.00 | CQ38: UN | CR38: UN | CS38: UN | CT38: UN | CU38: UN | CV38: UN | CW38: UN | CX38: 0 | CZ38: 0 | DA38: 5000.00 | DB38: 5000 | DC38: 0 | DD38: 5000 | DE38: 0 | DF38: MRECIO | DG38: Garcia Prieto, Pablo
A39: 1124510125000 | B39: SWITCH MAGNETICO SPDT 28VDC 200MA C/FUS | C39: 44727 | D39: 1101508963 | E39: 1 | G39: 4200480501 | H39: 10 | I39: 44736 | J39: 44838 | M39: Liberado | N39: 455 | O39: 455 | P39: 0 | Q39: 455 | R39: 0 | S39: 33.82 | T39: 15388.1 | U39: EUR | V39: 9510-G111-P1F1-Z0R2B2 | W39: E-T-A APARELLAJE ELECTRICO S.L.U. | X39: 7218|S22B04_S1076 | Y39: 6990 | AA39: 1 | AB39: 1 | AE39: 6000 | AF39: Pedido de materiales | AH39: ZNB | AJ39: SRM2ERP | AK39: SRM2ERP | AL39: 0 | AN39: 0 | AO39: 455 | AQ39: 0 | AR39: E.T.A. | AS39: Simulacion | AV39: El Rayo (Polig Indust La Quinta,719171Cabanillas del Campo | AX39: 44838 | AY39: 9006271 | BB39: 44728 | BC39: 44838 | BF39: 44754 | BH39: 381814 | BJ39: 14182.35 | BK39: 31.17 | BN39: 3 | BO39: 20 | BP39: EUR | BR39: EUR | BS39: EUR | BT39: María Isabel Recio Gutiérrez | BZ39: 50 | CA39: 455 | CB39: 15388.1 | CD39: 1208010 | CH39: 0 | CI39: 1,00000 | CK39: Q | CL39: 8 | CM39: 0.00 | CQ39: UN | CR39: UN | CS39: UN | CT39: UN | CU39: UN | CV39: UN | CW39: UN | CX39: 0 | CZ39: 0 | DA39: 15388.10 | DB39: 15388.1 | DC39: 0 | DD39: 15388.1 | DE39: 0 | DF39: MRECIO | DG39: Gomez Cornejo, Luis
A40: 1128990400600 | B40: INSERTO MARCAJE NEGRO 1A PULS CONFIG A/B | C40: 44727 | D40: 1101508963 | E40: 2 | G40: 4200480501 | H40: 20 | I40: 44736 | J40: 44837 | M40: Liberado | N40: 10 | O40: 10 | P40: 0 | Q40: 10 | R40: 0 | S40: 2.05 | T40: 20.5 | U40: EUR | V40: X 222 175 03 | W40: E-T-A APARELLAJE ELECTRICO S.L.U. | X40: 7218|S22B04_S1076 | Y40: 6990 | AA40: 1 | AB40: 1 | AE40: 6000 | AF40: Pedido de materiales | AH40: ZNB | AJ40: SRM2ERP | AK40: SRM2ERP | AL40: 0 | AN40: 0 | AO40: 10 | AQ40: 0 | AR40: E.T.A. | AS40: Simulacion | AV40: El Rayo (Polig Indust La Quinta,719171Cabanillas del Campo | AX40: 44837 | AY40: 9006271 | BB40: 44728 | BC40: 44837 | BF40: 44728 | BH40: 381816 | BJ40: 18 | BK40: 1.8 | BN40: 3 | BO40: 20 | BP40: EUR | BR40: EUR | BS40: EUR | BT40: María Isabel Recio Gutiérrez | BZ40: 85 | CA40: 10 | CB40: 20.5 | CD40: 1208010 | CH40: 0 | CI40: 1,00000 | CK40: Q | CL40: 8 | CM40: 0.00 | CQ40: UN | CR40: UN | CS40: UN | CT40: UN | CU40: UN | CV40: UN | CW40: UN | CX40: 0 | CZ40: 0 | DA40: 20.50 | DB40: 20.5 | DC40: 0 | DD40: 20.5 | DE40: 0 | DF40: MRECIO | DG40: Gomez Cornejo, Luis
A41: 1128990401600 | B41: INSERTO MARCAJE NEGRO 2.5A PULS CONF A/B | C41: 44727 | D41: 1101508963 | E41: 3 | G41: 4200480501 | H41: 30 | I41: 44736 | J41: 44837 | M41: Liberado | N41: 170 | O41: 170 | P41: 0 | Q41: 170 | R41: 0 | S41: 2.05 | T41: 348.5 | U41: EUR | V41: X 222 175 30 | W41: E-T-A APARELLAJE ELECTRICO S.L.U. | X41: 7218|S22B04_S1076 | Y41: 6990 | AA41: 1 | AB41: 1 | AE41: 6000 | AF41: Pedido de materiales | AH41: ZNB | AJ41: SRM2ERP | AK41: SRM2ERP | AL41: 0 | AN41: 0 | AO41: 170 | AQ41: 0 | AR41: E.T.A. | AS41: Simulacion | AV41: El Rayo (Polig Indust La Quinta,719171Cabanillas del Campo | AX41: 44837 | AY41: 9006271 | BB41: 44728 | BC41: 44837 | BF41: 44728 | BH41: 381816 | BJ41: 272 | BK41: 1.6 | BN41: 3 | BO41: 20 | BP41: EUR | BR41: EUR | BS41: EUR | BT41: María Isabel Recio Gutiérrez | BZ41: 76 | CA41: 170 | CB41: 348.5 | CD41: 1208010 | CH41: 0 | CI41: 1,00000 | CK41: Q | CL41: 8 | CM41: 0.00 | CQ41: UN | CR41: UN | CS41: UN | CT41: UN | CU41: UN | CV41: UN | CW41: UN | CX41: 0 | CZ41: 0 | DA41: 348.50 | DB41: 348.5 | DC41: 0 | DD41: 348.5 | DE41: 0 | DF41: MRECIO | DG41: Gomez Cornejo, Luis
A42: 1128990400800 | B42: INSERTO MARCAJE NEGRO 3A PULS CONFIG A/B | C42: 44727 | D42: 1101508963 | E42: 4 | G42: 4200480501 | H42: 40 | I42: 44736 | J42: 44837 | M42: Liberado | N42: 75 | O42: 75 | P42: 0 | Q42: 75 | R42: 0 | S42: 2.05 | T42: 153.75 | U42: EUR | V42: X 222 175 07 | W42: E-T-A APARELLAJE ELECTRICO S.L.U. | X42: 7218|S22B04_S1076 | Y42: 6990 | AA42: 1 | AB42: 1 | AE42: 6000 | AF42: Pedido de materiales | AH42: ZNB | AJ42: SRM2ERP | AK42: SRM2ERP | AL42: 0 | AN42: 0 | AO42: 75 | AQ42: 0 | AR42: E.T.A. | AS42: Simulacion | AV42: El Rayo (Polig Indust La Quinta,719171Cabanillas del Campo | AX42: 44837 | AY42: 9006271 | BB42: 44728 | BC42: 44837 | BF42: 44728 | BH42: 381816 | BJ42: 136.5 | BK42: 1.82 | BN42: 3 | BO42: 20 | BP42: EUR | BR42: EUR | BS42: EUR | BT42: María Isabel Recio Gutiérrez | BZ42: 85 | CA42: 75 | CB42: 153.75 | CD42: 1208010 | CH42: 0 | CI42: 1,00000 | CK42: Q | CL42: 8 | CM42: 0.00 | CQ42: UN | CR42: UN | CS42: UN | CT42: UN | CU42: UN | CV42: UN | CW42: UN | CX42: 0 | CZ42: 0 | DA42: 153.75 | DB42: 153.75 | DC42: 0 | DD42: 153.75 | DE42: 0 | DF42: MRECIO | DG42: Gomez Cornejo, Luis
A43: 1128990401000 | B43: INSERTO MARCAJE NEGRO 7,5A PULS CONF A/B | C43: 44727 | D43: 1101508963 | E43: 5 | G43: 4200480501 | H43: 50 | I43: 44736 | J43: 44837 | M43: Liberado | N43: 60 | O43: 60 | P43: 0 | Q43: 60 | R43: 0 | S43: 2.05 | T43: 123 | U43: EUR | V43: X 222 175 10 | W43: E-T-A APARELLAJE ELECTRICO S.L.U. | X43: 7218|S22B04_S1076 | Y43: 6990 | AA43: 1 | AB43: 1 | AE43: 6000 | AF43: Pedido de materiales | AH43: ZNB | AJ43: 945509 | AK43: SRM2ERP | AL43: 0 | AN43: 0 | AO43: 60 | AQ43: 0 | AR43: E.T.A. | AS43: Simulacion | AV43: El Rayo (Polig Indust La Quinta,719171Cabanillas del Campo | AX43: 44837 | AY43: 9006271 | BB43: 44728 | BC43: 44837 | BF43: 44728 | BH43: 381816 | BJ43: 109.2 | BK43: 1.82 | BN43: 3 | BO43: 20 | BP43: EUR | BR43: EUR | BS43: EUR | BT43: María Isabel Recio Gutiérrez | BZ43: 85 | CA43: 60 | CB43: 123 | CD43: 1208010 | CH43: 0 | CI43: 1,00000 | CK43: Q | CL43: 8 | CM43: 0.00 | CQ43: UN | CR43: UN | CS43: UN | CT43: UN | CU43: UN | CV43: UN | CW43: UN | CX43: 0 | CZ43: 0 | DA43: 123.00 | DB43: 123 | DC43: 0 | DD43: 123 | DE43: 0 | DF43: MRECIO | DG43: Gomez Cornejo, Luis
A44: 1128990400400 | B44: INSERTO MARCAJE NEGRO 10A PULS CONFI A/B | C44: 44727 | D44: 1101508963 | E44: 6 | G44: 4200480501 | H44: 60 | I44: 44736 | J44: 44837 | M44: Liberado | N44: 20 | O44: 20 | P44: 0 | Q44: 20 | R44: 0 | S44: 2.05 | T44: 41 | U44: EUR | V44: X 222 175 11 | W44: E-T-A APARELLAJE ELECTRICO S.L.U. | X44: 7218|S22B04_S1076 | Y44: 6990 | AA44: 1 | AB44: 1 | AE44: 6000 | AF44: Pedido de materiales | AH44: ZNB | AJ44: 945509 | AK44: SRM2ERP | AL44: 0 | AN44: 0 | AO44: 20 | AQ44: 0 | AR44: E.T.A. | AS44: Simulacion | AV44: El Rayo (Polig Indust La Quinta,719171Cabanillas del Campo | AX44: 44837 | AY44: 9006271 | BC44: 44837 | BH44: 381816 | BJ44: 36.4 | BK44: 1.82 | BN44: 3 | BO44: 20 | BP44: EUR | BR44: EUR | BS44: EUR | BT44: María Isabel Recio Gutiérrez | BZ44: 85 | CA44: 20 | CB44: 41 | CD44: 1208010 | CH44: 0 | CI44: 1,00000 | CK44: Q | CL44: 8 | CM44: 0.00 | CQ44: UN | CR44: UN | CS44: UN | CT44: UN | CU44: UN | CV44: UN | CW44: UN | CX44: 0 | CZ44: 0 | DA44: 41.00 | DB44: 41 | DC44: 0 | DD44: 41 | DE44: 0 | DF44: MRECIO | DG44: Gomez Cornejo, Luis
A45: 1128990401100 | B45: INSERTO MARCAJE NEGRO 25A PULS CONFI A/B | C45: 44727 | D45: 1101508963 | E45: 7 | G45: 4200480501 | H45: 70 | I45: 44736 | J45: 44837 | M45: Liberado | N45: 10 | O45: 10 | P45: 0 | Q45: 10 | R45: 0 | S45: 2.05 | T45: 20.5 | U45: EUR | V45: X 222 175 14 | W45: E-T-A APARELLAJE ELECTRICO S.L.U. | X45: 7218|S22B04_S1076 | Y45: 6990 | AA45: 1 | AB45: 1 | AE45: 6000 | AF45: Pedido de materiales | AH45: ZNB | AJ45: 945509 | AK45: SRM2ERP | AL45: 0 | AN45: 0 | AO45: 10 | AQ45: 0 | AR45: E.T.A. | AS45: Simulacion | AV45: El Rayo (Polig Indust La Quinta,719171Cabanillas del Campo | AX45: 44837 | AY45: 9006271 | BC45: 44837 | BH45: 381816 | BJ45: 18.2 | BK45: 1.82 | BN45: 3 | BO45: 20 | BP45: EUR | BR45: EUR | BS45: EUR | BT45: María Isabel Recio Gutiérrez | BZ45: 85 | CA45: 10 | CB45: 20.5 | CD45: 1208010 | CH45: 0 | CI45: 1,00000 | CK45: Q | CL45: 8 | CM45: 0.00 | CQ45: UN | CR45: UN | CS45: UN | CT45: UN | CU45: UN | CV45: UN | CW45: UN | CX45: 0 | CZ45: 0 | DA45: 20.50 | DB45: 20.5 | DC45: 0 | DD45: 20.5 | DE45: 0 | DF45: MRECIO | DG45: Gomez Cornejo, Luis
A46: 1128990400900 | B46: INSERTO MARCAJE NEGRO 5A PULS CONFIG A/B | C46: 44727 | D46: 1101508963 | E46: 8 | G46: 4200480501 | H46: 80 | I46: 44736 | J46: 44837 | M46: Liberado | N46: 100 | O46: 100 | P46: 0 | Q46: 100 | R46: 0 | S46: 2.05 | T46: 205 | U46: EUR | V46: X 222 175 08 | W46: E-T-A APARELLAJE ELECTRICO S.L.U. | X46: 7218|S22B04_S1076 | Y46: 6990 | AA46: 1 | AB46: 1 | AE46: 6000 | AF46: Pedido de materiales | AH46: ZNB | AJ46: 945509 | AK46: SRM2ERP | AL46: 0 | AN46: 0 | AO46: 100 | AQ46: 0 | AR46: E.T.A. | AS46: Simulacion | AV46: El Rayo (Polig Indust La Quinta,719171Cabanillas del Campo | AX46: 44837 | AY46: 9006271 | BB46: 44728 | BC46: 44837 | BF46: 44728 | BH46: 381816 | BJ46: 182 | BK46: 1.82 | BN46: 3 | BO46: 20 | BP46: EUR | BR46: EUR | BS46: EUR | BT46: María Isabel Recio Gutiérrez | BZ46: 85 | CA46: 100 | CB46: 205 | CD46: 1208010 | CH46: 0 | CI46: 1,00000 | CK46: Q | CL46: 8 | CM46: 0.00 | CQ46: UN | CR46: UN | CS46: UN | CT46: UN | CU46: UN | CV46: UN | CW46: UN | CX46: 0 | CZ46: 0 | DA46: 205.00 | DB46: 205 | DC46: 0 | DD46: 205 | DE46: 0 | DF46: MRECIO | DG46: Gomez Cornejo, Luis
A47: 1128990400200 | B47: INSERTO MARCAJE NEGRO 15A PULS CONFI A/B | C47: 44727 | D47: 1101508963 | E47: 9 | G47: 4200480501 | H47: 90 | I47: 44736 | J47: 44837 | M47: Liberado | N47: 20 | O47: 20 | P47: 0 | Q47: 20 | R47: 0 | S47: 2.05 | T47: 41 | U47: EUR | V47: X 222 175 12 | W47: E-T-A APARELLAJE ELECTRICO S.L.U. | X47: 7218|S22B04_S1076 | Y47: 6990 | AA47: 1 | AB47: 1 | AE47: 6000 | AF47: Pedido de materiales | AH47: ZNB | AJ47: 945509 | AK47: SRM2ERP | AL47: 0 | AN47: 0 | AO47: 20 | AQ47: 0 | AR47: E.T.A. | AS47: Simulacion | AV47: El Rayo (Polig Indust La Quinta,719171Cabanillas del Campo | AX47: 44837 | AY47: 9006271 | BB47: 44728 | BC47: 44837 | BF47: 44728 | BH47: 381816 | BJ47: 36.4 | BK47: 1.82 | BN47: 3 | BO47: 20 | BP47: EUR | BR47: EUR | BS47: EUR | BT47: María Isabel Recio Gutiérrez | BZ47: 85 | CA47: 20 | CB47: 41 | CD47: 1208010 | CH47: 0 | CI47: 1,00000 | CK47: Q | CL47: 8 | CM47: 0.00 | CQ47: UN | CR47: UN | CS47: UN | CT47: UN | CU47: UN | CV47: UN | CW47: UN | CX47: 0 | CZ47: 0 | DA47: 41.00 | DB47: 41 | DC47: 0 | DD47: 41 | DE47: 0 | DF47: MRECIO | DG47: Gomez Cornejo, Luis
A48: 1390703010100 | B48: CAJA FMP BOING GE | C48: 44725 | D48: 1101507890 | E48: 1 | G48: 4200480634 | H48: 10 | I48: 44739 | J48: 45352 | M48: Envío a firma | N48: 2 | O48: 2 | P48: 0 | Q48: 2 | R48: 0 | S48: 22539 | T48: 45078 | U48: USD | V48: PLT6324-01-01 | W48: GE AVIATION SYSTEMS LLC | X48: 7218|S22B04_S1041 | Y48: 6990 | AA48: 1 | AB48: 1 | AE48: 6000 | AF48: Pedido de materiales | AH48: ZNB | AJ48: 460772 | AK48: SRM2ERP | AL48: 0 | AN48: 0 | AO48: 2 | AQ48: 0 | AR48: GE AVIATION SYSTEMS LLC | AS48: Simulacion | AV48: El Rayo (Polig Indust La Quinta,719171Cabanillas del Campo | AW48: '@FM@ | AX48: 44834 | AY48: 9013644 | BB48: 44729 | BC48: 45352 | BF48: 44729 | BH48: 432016 | BJ48: 45078 | BK48: 22539 | BN48: 1 | BO48: 20 | BP48: USD | BR48: USD | BS48: USD | BT48: María Isabel Recio Gutiérrez | BZ48: 40 | CA48: 2 | CB48: 45078 | CD48: 1165101 | CH48: 0 | CI48: 0,93345 | CJ48: PO | CK48: Q | CL48: 8 | CM48: 0.00 | CQ48: UN | CR48: UN | CS48: UN | CT48: UN | CU48: UN | CV48: UN | CW48: UN | CX48: 0 | CZ48: 0 | DA48: 45078.00 | DB48: 45078 | DC48: 0 | DD48: 45078 | DE48: 0 | DF48: MRECIO | DG48: Ramos Torreadrado, Carolina
A49: 1390700652300 | B49: SIST MOV SIMUL GEN3 E7 FULL 1.400KG | C49: 44722 | D49: 1101504793 | E49: 2 | G49: 4200483345 | H49: 10 | I49: 44756 | J49: 44834 | K49: X | M49: Liberado | N49: 1 | O49: 1 | P49: 0 | Q49: 1 | R49: 0 | S49: 433850 | T49: 433850 | U49: EUR | V49: MB-E-6DOF/60/14000KG | W49: MOOG CONTROLS LIMITED | X49: 7218|S22B04_S107E | Y49: 6990 | AA49: 1 | AB49: 1 | AE49: 6000 | AF49: Pedido de materiales | AH49: ZNB | AJ49: 491051 | AK49: SRM2ERP | AL49: 0 | AN49: 0 | AO49: 1 | AQ49: 0 | AR49: MOOG FCS BV | AS49: Simulacion | AV49: El Rayo (Polig Indust La Quinta,719171Cabanillas del Campo | AW49: '@FM@ | AX49: 44834 | AY49: 9000188 | BB49: 44734 | BC49: 44834 | BF49: 44760 | BH49: 322012 | BJ49: 425000 | BK49: 425000 | BM49: L | BN49: 3 | BO49: 20 | BP49: EUR | BR49: EUR | BS49: EUR | BT49: María Isabel Recio Gutiérrez | BZ49: 40 | CA49: 1 | CB49: 433850 | CD49: 1237272 | CH49: 0 | CI49: 1,00000 | CJ49: PO | CK49: Q | CL49: 8 | CM49: 0.00 | CQ49: UN | CR49: UN | CS49: UN | CT49: UN | CU49: UN | CV49: UN | CW49: UN | CX49: 0 | CZ49: 0 | DA49: 433850.00 | DB49: 433850 | DC49: 0 | DD49: 433850 | DE49: 0 | DF49: MRECIO | DG49: Ramos Torreadrado, Carolina
A50: 1390700652300 | B50: SIST MOV SIMUL GEN3 E7 FULL 1.400KG | C50: 44722 | D50: 1101504793 | E50: 2 | G50: 4200480633 | H50: 10 | I50: 44739 | J50: 44834 | K50: X | L50: BORR | M50: Generado documento | N50: 1 | O50: 1 | P50: 0 | Q50: 1 | R50: 0 | S50: 425000 | T50: 425000 | U50: EUR | V50: MB-E-6DOF/60/14000KG | W50: MOOG READING LIMITED | X50: 7218|S22B04_S107E | Y50: 6990 | AA50: 1 | AB50: 1 | AE50: 6000 | AF50: Pedido de materiales | AH50: ZNB | AJ50: SRM2ERP | AK50: SRM2ERP | AL50: 0 | AN50: 0 | AO50: 1 | AQ50: 0 | AR50: MOOG FCS BV | AS50: Simulacion | AV50: El Rayo (Polig Indust La Quinta,719171Cabanillas del Campo | AW50: '@FM@ | AX50: 44834 | AY50: 9000188 | BB50: 44734 | BC50: 44834 | BF50: 44760 | BH50: 322012 | BJ50: 425000 | BK50: 425000 | BM50: L | BN50: X | BO50: 20 | BP50: EUR | BR50: EUR | BS50: EUR | BT50: María Isabel Recio Gutiérrez | BZ50: 40 | CA50: 1 | CB50: 425000 | CD50: 1225760 | CH50: 0 | CI50: 1,00000 | CJ50: PO | CK50: Q | CL50: 8 | CM50: 0.00 | CQ50: UN | CR50: UN | CS50: UN | CT50: UN | CU50: UN | CV50: UN | CW50: UN | CX50: 0 | CZ50: 0 | DA50: 425000.00 | DB50: 425000 | DC50: 0 | DD50: 425000 | DE50: 0 | DF50: MRECIO | DG50: Ramos Torreadrado, Carolina
B51: INSTALLATION ASSISTANCE | C51: 44722 | D51: 1101507627 | E51: 1 | G51: 4300285548 | H51: 10 | I51: 44748 | J51: 44834 | K51: X | L51: BORR | M51: Generado documento | N51: 1 | O51: 1 | P51: 0 | Q51: 0 | R51: 0 | S51: 5200 | T51: 5200 | U51: EUR | W51: MOOG, B.V. | X51: 7218|S22B04_S107E | AA51: 1 | AB51: 1 | AE51: 6000 | AF51: Ped. cerrado servic. | AH51: ZSE1 | AJ51: SRM2ERP | AK51: SRM2ERP | AL51: 0 | AN51: 0 | AO51: 1 | AQ51: 0 | AS51: Simulacion | AV51: Calle Mar Egeo,428830San Fernando de Henares | AW51: '@FM@ | AX51: 44834 | BB51: 44729 | BC51: 44834 | BF51: 44729 | BH51: 721519 | BJ51: 5200 | BK51: 5200 | BL51: BORR | BM51: L | BN51: X | BO51: 20 | BP51: EUR | BR51: EUR | BS51: EUR | BT51: María Isabel Recio Gutiérrez | BZ51: 0 | CA51: 1 | CB51: 5200 | CD51: 1052878 | CH51: 0 | CI51: 1,00000 | CJ51: PO | CK51: P | CL51: 0 | CM51: 0.00 | CQ51: UA | CR51: UA | CS51: N/A | CT51: N/A | CV51: UA | CW51: UA | CX51: 0 | CZ51: 0 | DA51: 5200.00 | DB51: 5200 | DC51: 0 | DD51: 5200 | DE51: 0 | DF51: MRECIO | DG51: Ramos Torreadrado, Carolina
B52: INSTALLATION ASSISTANCE | C52: 44722 | D52: 1101507627 | E52: 1 | G52: 4300284897 | H52: 10 | I52: 44739 | J52: 44834 | K52: X | L52: BORR | M52: Generado documento | N52: 1 | O52: 1 | P52: 0 | Q52: 0 | R52: 0 | S52: 5200 | T52: 5200 | U52: EUR | W52: MOOG READING LIMITED | X52: 7218|S22B04_S107E | AA52: 1 | AB52: 1 | AE52: 6000 | AF52: Ped. cerrado servic. | AH52: ZSE1 | AJ52: SRM2ERP | AK52: SRM2ERP | AL52: 0 | AN52: 0 | AO52: 1 | AQ52: 0 | AS52: Simulacion | AV52: Calle Mar Egeo,428830San Fernando de Henares | AW52: '@FM@ | AX52: 44834 | BB52: 44729 | BC52: 44834 | BF52: 44729 | BH52: 721519 | BJ52: 5200 | BK52: 5200 | BL52: BORR | BM52: L | BN52: X | BO52: 20 | BP52: EUR | BR52: EUR | BS52: EUR | BT52: María Isabel Recio Gutiérrez | BZ52: 0 | CA52: 1 | CB52: 5200 | CD52: 1225760 | CH52: 0 | CI52: 1,00000 | CJ52: PO | CK52: P | CL52: 0 | CM52: 0.00 | CQ52: UA | CR52: UA | CS52: N/A | CT52: N/A | CV52: UA | CW52: UA | CX52: 0 | CZ52: 0 | DA52: 5200.00 | DB52: 5200 | DC52: 0 | DD52: 5200 | DE52: 0 | DF52: MRECIO | DG52: Ramos Torreadrado, Carolina
B53: TUNNING | C53: 44722 | D53: 1101507627 | E53: 2 | G53: 4300285548 | H53: 20 | I53: 44748 | J53: 44834 | K53: X | L53: BORR | M53: Generado documento | N53: 1 | O53: 1 | P53: 0 | Q53: 0 | R53: 0 | S53: 6560 | T53: 6560 | U53: EUR | W53: MOOG, B.V. | X53: 7218|S22B04_S107E | AA53: 1 | AB53: 1 | AE53: 6000 | AF53: Ped. cerrado servic. | AH53: ZSE1 | AJ53: SRM2ERP | AK53: SRM2ERP | AL53: 0 | AN53: 0 | AO53: 1 | AQ53: 0 | AS53: Simulacion | AV53: Calle Mar Egeo,428830San Fernando de Henares | AW53: '@FM@ | AX53: 44834 | BB53: 44729 | BC53: 44834 | BF53: 44729 | BH53: 721519 | BJ53: 6560 | BK53: 6560 | BL53: BORR | BM53: L | BN53: X | BO53: 20 | BP53: EUR | BR53: EUR | BS53: EUR | BT53: María Isabel Recio Gutiérrez | BZ53: 0 | CA53: 1 | CB53: 6560 | CD53: 1052878 | CH53: 0 | CI53: 1,00000 | CJ53: PO | CK53: P | CL53: 0 | CM53: 0.00 | CQ53: UA | CR53: UA | CS53: N/A | CT53: N/A | CV53: UA | CW53: UA | CX53: 0 | CZ53: 0 | DA53: 6560.00 | DB53: 6560 | DC53: 0 | DD53: 6560 | DE53: 0 | DF53: MRECIO | DG53: Ramos Torreadrado, Carolina
B54: TUNNING | C54: 44722 | D54: 1101507627 | E54: 2 | G54: 4300284897 | H54: 20 | I54: 44739 | J54: 44834 | K54: X | L54: BORR | M54: Generado documento | N54: 1 | O54: 1 | P54: 0 | Q54: 0 | R54: 0 | S54: 6560 | T54: 6560 | U54: EUR | W54: MOOG READING LIMITED | X54: 7218|S22B04_S107E | AA54: 1 | AB54: 1 | AE54: 6000 | AF54: Ped. cerrado servic. | AH54: ZSE1 | AJ54: SRM2ERP | AK54: SRM2ERP | AL54: 0 | AN54: 0 | AO54: 1 | AQ54: 0 | AS54: Simulacion | AV54: Calle Mar Egeo,428830San Fernando de Henares | AW54: '@FM@ | AX54: 44834 | BB54: 44729 | BC54: 44834 | BF54: 44729 | BH54: 721519 | BJ54: 6560 | BK54: 6560 | BL54: BORR | BM54: L | BN54: X | BO54: 20 | BP54: EUR | BR54: EUR | BS54: EUR | BT54: María Isabel Recio Gutiérrez | BZ54: 0 | CA54: 1 | CB54: 6560 | CD54: 1225760 | CH54: 0 | CI54: 1,00000 | CJ54: PO | CK54: P | CL54: 0 | CM54: 0.00 | CQ54: UA | CR54: UA | CS54: N/A | CT54: N/A | CV54: UA | CW54: UA | CX54: 0 | CZ54: 0 | DA54: 6560.00 | DB54: 6560 | DC54: 0 | DD54: 6560 | DE54: 0 | DF54: MRECIO | DG54: Ramos Torreadrado, Carolina
A55: 3210604771100 | B55: FILTRO PRIVACIDAD PORTATIL 13,3" | C55: 44721 | D55: 1101507222 | E55: 1 | G55: 4200480430 | H55: 10 | I55: 44736 | J55: 44791 | M55: Liberado | N55: 2 | O55: 2 | P55: 2 | Q55: 0 | R55: 2 | S55: 38.13 | T55: 76.26 | U55: EUR | V55: 98-0440-0655-3 | W55: TECH DATA ESPAÑA, S.L.U. | X55: 7218|S22B04_S01 | Y55: 6990 | AA55: 1 | AB55: 1 | AE55: 6000 | AF55: Pedido de materiales | AH55: ZNB | AJ55: 563504 | AK55: SRM2ERP | AL55: 0 | AN55: 0 | AO55: 2 | AQ55: 0 | AR55: 3M | AS55: Simulacion | AV55: El Rayo (Polig Indust La Quinta,719171Cabanillas del Campo | AW55: '@FM@ | AX55: 44749 | AY55: 9005337 | BB55: 44722 | BC55: 44791 | BF55: 44722 | BH55: 432116 | BJ55: 76.26 | BK55: 38.13 | BN55: 3 | BO55: 20 | BP55: EUR | BR55: EUR | BS55: EUR | BT55: María Isabel Recio Gutiérrez | BZ55: 4 | CA55: 2 | CB55: 76.26 | CD55: 1059688 | CH55: 0 | CI55: 1,00000 | CK55: Q | CL55: 8 | CM55: 76.26 | CQ55: UN | CR55: UN | CS55: UN | CT55: UN | CU55: UN | CV55: UN | CW55: UN | CX55: 0 | CZ55: 0 | DA55: 0.00 | DB55: 76.26 | DC55: 76.26 | DD55: 0 | DE55: 76.26 | DF55: MRECIO | DG55: Martin Jimenez, Marta
A56: 1390704470000 | B56: ELECT CTRL LOADING SYST EFORCE EF12 B737 | C56: 44711 | D56: 1101502989 | E56: 1 | G56: 4600003268 | H56: 10 | I56: 44714 | J56: 44999 | M56: Liberado | N56: 1 | O56: 1 | P56: 0 | Q56: 1 | R56: 0 | S56: 209313 | T56: 209313 | U56: EUR | V56: EF12 CLS B737/Q20180793 | W56: E2M Technologies B.V. | X56: 7218|S22B04_S107F | Y56: 6990 | AA56: 1 | AB56: 1 | AE56: 6000 | AF56: Ped. antici. hitos | AH56: ZANT | AJ56: SRM2ERP | AK56: SRM2ERP | AL56: 0 | AN56: 0 | AO56: 1 | AQ56: 0 | AR56: E2M TECHNOLOGIES | AS56: Simulacion | AV56: El Rayo (Polig Indust La Quinta,719171Cabanillas del Campo | AW56: '@FM@ | AX56: 44803 | AY56: 9011500 | BB56: 44713 | BC56: 44999 | BF56: 44732 | BH56: 322018 | BJ56: 209313 | BK56: 209313 | BN56: 3 | BO56: 20 | BP56: EUR | BR56: EUR | BS56: EUR | BT56: María Isabel Recio Gutiérrez | BZ56: 40 | CA56: 1 | CB56: 209313 | CD56: 1184414 | CH56: 0 | CI56: 1,00000 | CJ56: PO | CK56: Q | CL56: 8 | CM56: 0.00 | CQ56: UN | CR56: UN | CS56: UN | CT56: UN | CU56: UN | CV56: UN | CW56: UN | CX56: 0 | CZ56: 0 | DA56: 209313.00 | DB56: 209313 | DC56: 0 | DD56: 209313 | DE56: 0 | DF56: MRECIO | DG56: Fernández Carrascal, José Abel
A57: 3260200010000 | B57: MEMORIAS EXTERNAS-USB | C57: 44708 | D57: 1101502613 | E57: 1 | G57: 4200477121 | H57: 10 | I57: 44715 | J57: 44735 | K57: X | M57: Liberado | N57: 2 | O57: 2 | P57: 2 | Q57: 0 | R57: 0 | S57: 113.64 | T57: 227.28 | U57: EUR | V57: 3260200010000 | W57: ELECTRONIC EQUIPMENT TRADING SAU (E | X57: 7218|S22B04_GPR05 | AA57: 1 | AB57: 1 | AE57: 6000 | AF57: Pedido de materiales | AH57: ZNB | AJ57: SRM2ERP | AK57: SRM2ERP | AL57: 0 | AN57: 2 | AO57: 0 | AQ57: 0 | AR57: OTROS FABRICANTES | AS57: Simulacion | AV57: Calle Mar Egeo,428830San Fernando de Henares | AW57: '@FM@ | AX57: 44726 | AY57: 9003222 | BB57: 44711 | BC57: 44735 | BF57: 44711 | BH57: 432116 | BJ57: 241.68 | BK57: 120.84 | BN57: 3 | BO57: 20 | BP57: EUR | BR57: EUR | BS57: EUR | BT57: María Isabel Recio Gutiérrez | BZ57: 30 | CA57: 0 | CB57: 0 | CD57: 1058525 | CH57: 0 | CI57: 1,00000 | CK57: P | CL57: 8 | CM57: 227.28 | CQ57: UN | CR57: UN | CS57: UN | CT57: UN | CU57: UN | CV57: UN | CW57: UN | CX57: 0 | CZ57: 227.28 | DA57: 0.00 | DB57: 0 | DC57: 0 | DD57: 0 | DE57: 227.28 | DF57: MRECIO | DG57: Martin Jimenez, Marta
A58: 0970710000400 | B58: CABINA del B737 | C58: 44707 | D58: 1101501807 | E58: 1 | G58: 4200477075 | H58: 10 | I58: 44714 | J58: 44843 | M58: Liberado | N58: 1 | O58: 1 | P58: 0 | Q58: 1 | R58: 0 | S58: 54000 | T58: 54000 | U58: EUR | V58: 0970710000400 | W58: S3 SOLUTIONS | X58: 7218|S22B04_S1072 | Y58: 6990 | AA58: 1 | AB58: 1 | AE58: 6000 | AF58: Pedido de materiales | AH58: ZNB | AJ58: 152028 | AK58: SRM2ERP | AL58: 0 | AN58: 0 | AO58: 1 | AQ58: 0 | AR58: INDRA SISTEMAS S.A. | AS58: Simulacion | AV58: El Rayo (Polig Indust La Quinta,719171Cabanillas del Campo | AW58: '@FM@ | AX58: 44793 | AY58: 9006321 | BB58: 44707 | BC58: 44843 | BF58: 44722 | BH58: 322014 | BJ58: 55500 | BK58: 55500 | BN58: 3 | BO58: 20 | BP58: EUR | BR58: EUR | BS58: EUR | BT58: María Isabel Recio Gutiérrez | BZ58: 40 | CA58: 1 | CB58: 54000 | CD58: 1216864 | CH58: 0 | CI58: 1,00000 | CK58: Q | CL58: 15 | CM58: 0.00 | CQ58: UN | CR58: UN | CS58: UN | CT58: UN | CU58: UN | CV58: UN | CW58: UN | CX58: 0 | CZ58: 0 | DA58: 54000.00 | DB58: 54000 | DC58: 0 | DD58: 54000 | DE58: 0 | DF58: MRECIO | DG58: Fernández Carrascal, José Abel
A59: 1390705210000 | B59: KIT INTEGRACION SIMULADOR (SIK) P/B737 | C59: 44707 | D59: 1101501819 | E59: 1 | G59: 4600003332 | H59: 10 | I59: 44803 | J59: 45534 | M59: Liberado | N59: 1 | O59: 1 | P59: 0 | Q59: 1 | R59: 0 | S59: 6000000 | T59: 6000000 | U59: USD | V59: C1-P315-737-21-1487 | W59: THE BOEING COMPANY | X59: 7218|S22B04_S103 | Y59: 6990 | AA59: 1 | AB59: 1 | AE59: 6000 | AF59: Ped. antici. hitos | AH59: ZANT | AJ59: 491051 | AK59: SRM2ERP | AL59: 0 | AN59: 0 | AO59: 1 | AQ59: 0 | AR59: BOEING | AS59: Simulacion | AV59: El Rayo (Polig Indust La Quinta,719171Cabanillas del Campo | AW59: '@FM@ | AX59: 44771 | AY59: 9000332 | BB59: 44711 | BC59: 45534 | BF59: 44711 | BH59: 322024 | BJ59: 6000000 | BK59: 6000000 | BM59: L | BN59: 3 | BO59: 20 | BP59: USD | BR59: USD | BS59: USD | BT59: María Isabel Recio Gutiérrez | BZ59: 40 | CA59: 1 | CB59: 6000000 | CD59: 1046021 | CH59: 0 | CI59: 0,98795 | CJ59: PO | CK59: Q | CL59: 8 | CM59: 0.00 | CQ59: UN | CR59: UN | CS59: UN | CT59: UN | CU59: UN | CV59: UN | CW59: UN | CX59: 0 | CZ59: 0 | DA59: 6000000.00 | DB59: 6000000 | DC59: 0 | DD59: 6000000 | DE59: 0 | DF59: MRECIO | DG59: Ramos Torreadrado, Carolina
A60: 1390705210000 | B60: KIT INTEGRACION SIMULADOR (SIK) P/B737 | C60: 44707 | D60: 1101501819 | E60: 1 | G60: 4200482274 | H60: 10 | I60: 44749 | J60: 45136 | L60: BORR | N60: 1 | O60: 1 | P60: 0 | Q60: 1 | R60: 0 | S60: 6000000 | T60: 6000000 | U60: USD | V60: C1-P315-737-21-1487 | W60: THE BOEING COMPANY | X60: 7218|S22B04_S103 | Y60: 6990 | AA60: 1 | AB60: 1 | AE60: 6000 | AF60: Pedido de materiales | AH60: ZNB | AJ60: SRM2ERP | AK60: SRM2ERP | AL60: 0 | AN60: 0 | AO60: 1 | AQ60: 0 | AR60: BOEING | AS60: Simulacion | AV60: El Rayo (Polig Indust La Quinta,719171Cabanillas del Campo | AW60: '@FM@ | AX60: 44771 | AY60: 9000332 | BB60: 44711 | BC60: 45136 | BF60: 44711 | BH60: 322024 | BJ60: 6000000 | BK60: 6000000 | BM60: L | BO60: 20 | BP60: USD | BR60: USD | BS60: USD | BT60: María Isabel Recio Gutiérrez | BZ60: 40 | CA60: 1 | CB60: 6000000 | CD60: 1046021 | CH60: 0 | CI60: 0,96274 | CJ60: PO | CK60: Q | CL60: 8 | CM60: 0.00 | CQ60: UN | CR60: UN | CS60: UN | CT60: UN | CU60: UN | CV60: UN | CW60: UN | CX60: 0 | CZ60: 0 | DA60: 6000000.00 | DB60: 6000000 | DC60: 0 | DD60: 6000000 | DE60: 0 | DF60: MRECIO | DG60: Ramos Torreadrado, Carolina

Sheet CONTRASEÑAS
A1: Título de pedido | B1: Proyecto suministrador | C1: Fecha fin planificada | D1: Fecha inicio planificada | E1: Presupuesto planificado | F1: Divisa | G1: Unidad de negocio Suministradora | H1: Suministrador | I1: Centro prod. | J1: Código material | K1: Proy/Elem peticionario | L1: Proy/Elem suministrador
A2: DP and HW kit 1 x FFS A320 - España - España | B2: 7218|JA2576_1001 | C2: 45566 | D2: 45413 | E2: 4409383.5 | F2: EUR | G2: TSDSIM - PROD SIMULACIÓN CP6000 | H2: Mateos Ortega, Juan José | I2: 6000 | J2: AC610000001 | K2: S24B05/S103 | L2: 2GP240/1001
A3: Licenses 1 x FFS A320 - España - España | B3: 7218|JA2577_1001 | C3: 45566 | D3: 45413 | E3: 185630 | F3: EUR | G3: TSDSIM - PROD SIMULACIÓN CP6000 | H3: Mateos Ortega, Juan José | I3: 6000 | J3: AC610000002 | K3: S24B05/S104 | L3: 2GP240/1002
A4: Display 1 x FFS A320 - España - España | B4: 7218|JA2578_1001 | C4: 45566 | D4: 45413 | E4: 225352.25 | F4: EUR | G4: TSDSIM - PROD SIMULACIÓN CP6000 | H4: Mateos Ortega, Juan José | I4: 6000 | J4: AC610000003 | K4: S24B05/S1071 | L4: 2GP240/1003
A5: Cockpit 1 x FFS A320 - España - España | B5: 7218|JA2579_1001 | C5: 45566 | D5: 45413 | E5: 61923 | F5: EUR | G5: TSDSIM - PROD SIMULACIÓN CP6000 | H5: Mateos Ortega, Juan José | I5: 6000 | J5: AC610000004 | K5: S24B05/S1072 | L5: 2GP240/1004
A6: BaseFrame - Aftercabin1 x FFS A320 - España - España | B6: 7218|JA2580_1001 | C6: 45566 | D6: 45413 | E6: 187403.76 | F6: EUR | G6: TSDSIM - PROD SIMULACIÓN CP6000 | H6: Mateos Ortega, Juan José | I6: 6000 | J6: AC610000005 | K6: S24B05/S1073 | L6: 2GP240/1005
A7: Alimentaciones- Interconexiones 1 x FFS A320 - España - España | B7: 7218|JA2581_1001 | C7: 45566 | D7: 45413 | E7: 83327.46 | F7: EUR | G7: TSDSIM - PROD SIMULACIÓN CP6000 | H7: Mateos Ortega, Juan José | I7: 6000 | J7: AC610000006 | K7: S24B05/S1074 | L7: 2GP240/1006
A8: Equipos Auxiliares 1 x FFS A320 - España - España | B8: 7218|JA2582_1001 | C8: 45566 | D8: 45413 | E8: 80794.97 | F8: EUR | G8: TSDSIM - PROD SIMULACIÓN CP6000 | H8: Mateos Ortega, Juan José | I8: 6000 | J8: AC610000007 | K8: S24B05/S1075 | L8: 2GP240/1007
A9: Equipos cabina 1 x FFS A320 - España - España | B9: 7218|JA2583_1001 | C9: 45566 | D9: 45413 | E9: 442933.2 | F9: EUR | G9: TSDSIM - PROD SIMULACIÓN CP6000 | H9: Mateos Ortega, Juan José | I9: 6000 | J9: AC610000008 | K9: S24B05/S1076 | L9: 2GP240/1008
A10: DACS1 x FFS A320 - España - España | B10: 7218|JA2584_1001 | C10: 45566 | D10: 45413 | E10: 24043.6 | F10: EUR | G10: TSDSIM - PROD SIMULACIÓN CP6000 | H10: Mateos Ortega, Juan José | I10: 6000 | J10: AC610000009 | K10: S24B05/S1077 | L10: 2GP240/1009
A11: Host 1 x FFS A320 - España - España | B11: 7218|JA2585_1001 | C11: 45566 | D11: 45413 | E11: 145118.72 | F11: EUR | G11: TSDSIM - PROD SIMULACIÓN CP6000 | H11: Mateos Ortega, Juan José | I11: 6000 | J11: AC610000010 | K11: S24B05/S1078 | L11: 2GP240/1010
A12: Rtio - Avicom 1 x FFS A320 - España - España | B12: 7218|JA2586_1001 | C12: 45566 | D12: 45413 | E12: 65590.31 | F12: EUR | G12: TSDSIM - PROD SIMULACIÓN CP6000 | H12: Mateos Ortega, Juan José | I12: 6000 | J12: AC610000011 | K12: S24B05/S1079 | L12: 2GP240/1011
A13: DBS 1 x FFS A320 - España - España | B13: 7218|JA2587_1001 | C13: 45566 | D13: 45413 | E13: 35000 | F13: EUR | G13: TSDSIM - PROD SIMULACIÓN CP6000 | H13: Mateos Ortega, Juan José | I13: 6000 | J13: AC610000012 | K13: S24B05/S107A | L13: 2GP240/1012
A14: IOS - INSE 1 x FFS A320 - España - España | B14: 7218|JA2588_1001 | C14: 45566 | D14: 45413 | E14: 12817.63 | F14: EUR | G14: TSDSIM - PROD SIMULACIÓN CP6000 | H14: Mateos Ortega, Juan José | I14: 6000 | J14: AC610000013 | K14: S24B05/S107B | L14: 2GP240/1013
A15: Motion 1 x FFS A320 - España - España | B15: 7218|JA2612_1001 | E15: 0 | F15: EUR | G15: TSDSIM - PROD SIMULACIÓN CP6000 | H15: Mateos Ortega, Juan José | I15: 6000 | J15: AC610000014 | K15: S24B05/S107C | L15: 2GP240/1014
A16: CLS 1 x FFS A320 - España - España | B16: 7218|JA2589_1001 | C16: 45566 | D16: 45413 | E16: 90407.13 | F16: EUR | G16: TSDSIM - PROD SIMULACIÓN CP6000 | H16: Mateos Ortega, Juan José | I16: 6000 | J16: AC610000015 | K16: S24B05/S107D | L16: 2GP240/1015
A17: Prod. Display 1 x FFS A320 - España - España | B17: 7218|JA2590_1001 | C17: 45566 | D17: 45413 | E17: 25000 | F17: EUR | G17: TSDSIM - PROD SIMULACIÓN CP6000 | H17: Mateos Ortega, Juan José | I17: 6000 | J17: AC610000016 | K17: S24B05/S107E | L17: 2GP240/1016
A18: Spares 1 x FFS A320 - España - España | B18: 7218|JA2591_1001 | C18: 45566 | D18: 45413 | E18: 200000 | F18: EUR | G18: TSDSIM - PROD SIMULACIÓN CP6000 | H18: Mateos Ortega, Juan José | I18: 6000 | J18: AC610000017 | K18: S24B05/S107F | L18: 2GP240/1017
A19: Tools 1 x FFS A320 - España - España | B19: 7218|JA2592_1001 | C19: 45566 | D19: 45413 | E19: 20000 | F19: EUR | G19: TSDSIM - PROD SIMULACIÓN CP6000 | H19: Mateos Ortega, Juan José | I19: 6000 | J19: AC610000018 | K19: S24B05/S107G | L19: 2GP240/1018
A20: Prod. Cableados y Mazos (Lab 1 x FFS A320 - España - España | B20: 7218|JA2593_1001 | C20: 45566 | D20: 45413 | E20: 132000 | F20: EUR | G20: TSDSIM - PROD SIMULACIÓN CP6000 | H20: Mateos Ortega, Juan José | I20: 6000 | J20: AC610000019 | K20: S24B05/P10321 | L20: 2GP240/1019
A21: Instal. cableados y mec.1 x FFS A320 - España - España | B21: 7218|JA2594_1001 | C21: 45566 | D21: 45413 | E21: 165000 | F21: EUR | G21: TSDSIM - PROD SIMULACIÓN CP6000 | H21: Mateos Ortega, Juan José | I21: 6000 | J21: AC610000020 | K21: S24B05/P10322 | L21: 2GP240/1020
A23: A320 FFS SN06

Sheet BOM TESTBENCH A320 SN06
A1: Cod. Indra | B1: Recodificado | C1: DESCRIPTION | D1: SYSTEM/EQUIPMENT | E1: P/N MFR | F1: MFR | G1: P.U. | H1: QTY | I1: TOTAL | J1: RESPONSABLE | K1: PRIORIDAD | L1: Comentario | M1: DATE | N1: GPI I&T | O1: AC | P1: Contraseña | Q1: Nº Petición 1 | R1: OP SUB | S1: OP SUB | T1: N/S | U1: Pedido | V1: ESTADO | W1: Fecha Entrega | X1: Fecha Entrada en | Y1: Comentarios LVR | AA1: FACTURA | AB1: SOLICTUD LOTE
J2: I&T | K2: PO | L2: I&T | V2: (11/12/2023) | W2: Pedido | X2: Compras de la SP
A3: 3120201290701 | C3: RACK | D3: RACK | F3: RITTAL | H3: 1 | I3: =H3*G3 -> 0 | J3: JGP | K3: 1 | L3: COGIDO DEL 135 - INCLUYE NIVELADOR Y PIES | M3: 45561 | N3: - | Q3: 1101894009
A4: 3030700470000 | C4: QNAP PROCESADOR INTEL XEON D-1622 3.2GHZ 32GB | D4: RACK - QNAP | E4: TS-H1886XU-RP-R2-D1622-32G | F4: QNAP SYSTEMS | H4: 1 | I4: =H4*G4 -> 0 | J4: JGP | K4: 1 | L4: YA SE HA COMPRADO | M4: 45561 | N4: S24B05_S1078 | Q4: N/A | AB4: -
A5: 3060301930600 | C5: DISCO DURO SSD 2TB SATA3 2.5" 870QVO NEG | D5: RACK -QNAP | E5: MZ-77Q2T0BW | F5: SAMSUMG | H5: 12 | I5: =H5*G5 -> 0 | J5: JGP | K5: 1 | L5: YA SE HA COMPRADO | M5: 45561 | N5: S24B05_S1078 | Q5: N/A | AB5: -
A6: 1706700040700 | C6: KIT / GUIA MONTAJE P/RACK NAS INSTALACION | D6: RACK -TESTBENCH | E6: RAIL-B02 | F6: QNAP SYSTEMS | H6: 1 | I6: =H6*G6 -> 0 | J6: JGP | K6: 1 | L6: YA SE HA COMPRADO | M6: 45561 | N6: S24B05_S1078 | Q6: N/A | AB6: -
A7: 3010201822301 | C7: ORDENADOR ENRACABLE Z4 RTXA6000 (GAMA HIGH PC - TIPO IG) | D7: RACK -PCs | E7: 52258736 | F7: HP | H7: 1 | I7: =H7*G7 -> 0 | J7: JGP | K7: 1 | L7: YA SE HA COMPRADO | M7: 45561 | N7: S24B05_S1078 | Q7: N/A | AB7: -
A8: 3010201822302 | C8: ORDENADOR ENRACABLE Z4 T1000 (GAMA HIGH PC - TIPO SENCILLO) | D8: RACK -PCs | E8: 52258775 | F8: HP | H8: 7 | I8: =H8*G8 -> 0 | J8: JGP | K8: 1 | L8: YA SE HA COMPRADO | M8: 45561 | N8: S24B05_S1078 | Q8: N/A | AB8: -
A9: 3170408510000 | C9: Intel Ethernet I350-T4 4-Port 1Gb NIC | D9: RACK -PCs | E9: 395112 | F9: INTEL | H9: 8 | I9: =H9*G9 -> 0 | J9: JGP | K9: 1 | L9: YA SE HA COMPRADO | M9: 45561 | N9: S24B05_S1078 | Q9: N/A | AB9: -
A10: 1708500960000 | C10: GUIA PUESTA TIERRA HORIZONTA 450MM VX/IT | D10: RACK -TESTBENCH | E10: 7113000 | F10: RITTAL | H10: 1 | I10: =H10*G10 -> 0 | J10: JGP | K10: 1 | L10: VIENE CON EL RACK DE RITTAL | M10: 45561 | N10: EV4S02_P1 | Q10: 1101894009 | AB10: -
A11: 3190402380300 | C11: MONITOR TACTIL LCD 22" 1920X1080 FULL HD | D11: RACK -TESTBENCH | E11: E351600 | F11: ELO | H11: 2 | I11: =H11*G11 -> 0 | J11: JGP | K11: 1 | L11: YA SE HA COMPRADO | M11: 45561 | N11: EV4S02_P1 | Q11: 4200583638 | AB11: 1
A12: 3190700971200 | C12: MONITOR IPS 24" FHD 1920X1080 250NITS | D12: DESK-MONITORES | E12: E24 G5 | F12: HP | G12: 120 | H12: 8 | I12: =H12*G12 -> 960 | J12: JGP | K12: 1 | L12: YA SE HA COMPRADO | M12: 45561 | N12: EV4S02_P1 | Q12: 1101786777 | AB12: 1
A13: 1218000070000 | C13: POWER STRIP 9 SOCKETS | D13: RACK - POWER | E13: 60110-202 | F13: SCHROFF | H13: 3 | I13: =H13*G13 -> 0 | J13: JGP | K13: 1 | L13: YA SE HA COMPRADO | M13: 45561 | N13: EV4S02_P1 | AB13: 3
C14: POWER STRIP 9 SOCKETS | D14: RACK - POWER | E14: 60110-202 | F14: SCHROFF | H14: 1 | L14: YA SE HA COMPRADO | M14: 45572 | N14: EV4S02_P1
A15: 3170102910900 | C15: SWITCH 24 PORT 10X100X1000BASE-T SFP+ | D15: RACK - SWITCHES | E15: GSM4328S-100NES | F15: NETGEAR | G15: 1272 | H15: 1 | I15: =H15*G15 -> 1272 | J15: JGP | K15: 1 | L15: COGIDO DEL 135 | M15: 45562 | N15: S24B05_S1078 | Q15: 1101894009 | AB15: -
A16: 3170101514700 | C16: SWITCH 28 PORT 10-GB PRO 4 SFP+ - IG STRG | D16: RACK - SWITCHES | E16: XS728T-100NES | F16: NETGEAR | G16: 1871.67 | H16: 1 | I16: =H16*G16 -> 1871.67 | J16: JGP | K16: 1 | L16: COGIDO DEL 135 | M16: 45562 | N16: EV4S02_P1 | Q16: 1101894009 | AB16: 4
A17: 1229591600905 | C17: Patchcord CAT6A F/UTP RJ45 Blanco LSZH.L: 3m | D17: WIRE-LAN CABLES | E17: LAT-CAT6AF-BL-3 | F17: CUBITEL | G17: 5.4 | H17: 9 | I17: =H17*G17 -> 48.6 | J17: JGP | K17: 1 | L17: YA SE HA COMPRADO | M17: 45565 | N17: EV4S02_P1 | AB17: 2
C18: Patchcord CAT6A F/UTP RJ45 Blanco LSZH.L: 3m | D18: WIRE-LAN CABLES | E18: LAT-CAT6AF-BL-3 | F18: CUBITEL | G18: 5.4 | H18: 1 | I18: =H18*G18 -> 5.4 | J18: JGP | K18: 1 | L18: YA SE HA COMPRADO | M18: 45567 | N18: EV4S02_P1 | AB18: 3
A19: 1229591600901 | C19: Patchcord CAT6A F/UTP RJ45 Negro LSZH L: 3m | D19: WIRE-LAN CABLES | E19: LAT-CAT6AF-NG-3 | F19: CUBITEL | G19: 5.4 | H19: 8 | I19: =H19*G19 -> 43.2 | J19: JGP | K19: 1 | L19: YA SE HA COMPRADO | M19: 45565 | N19: EV4S02_P1 | AB19: 2
A20: 1229591600705 | C20: Patchcord CAT6A F/UTP RJ45 Rojo. LSZH L: 3m | D20: WIRE-LAN CABLES | E20: LAT-CAT6AF-RJ-3 | F20: CUBITEL | G20: 5.4 | H20: 1 | I20: =H20*G20 -> 5.4 | J20: JGP | K20: 1 | L20: YA SE HA COMPRADO | M20: 45565 | N20: EV4S02_P1 | AB20: 2
A21: 1229591600709 | C21: Patchcord CAT6A F/UTP RJ45 Azul. LSZH L: 3m | D21: WIRE-LAN CABLES | E21: LAT-CAT6AF-AZ-3 | F21: CUBITEL | G21: 5.4 | H21: 3 | I21: =H21*G21 -> 16.2 | J21: JGP | K21: 1 | L21: YA SE HA COMPRADO | M21: 45565 | N21: EV4S02_P1 | AB21: 2
A22: 1229590990805 | C22: WIRE HDMI 10 M | D22: WIRE | E22: 182-8476 | F22: RS PRO | H22: 2 | I22: =H22*G22 -> 0 | J22: JGP | K22: 1 | L22: YA SE HA COMPRADO | M22: 45565 | N22: EV4S02_P1 | Q22: 1101789741 | AB22: 2
A23: 3210504910400 | C23: ADAPT DP-MINI-M/HDMI-A-H 2K BLANCO L0.1M | D23: RACK-CONVERSORS | E23: MDP2HD4KSW | F23: STARTECH.COM LTD | H23: 2 | I23: =H23*G23 -> 0 | J23: JGP | K23: 1 | L23: YA SE HA COMPRADO | M23: 45565 | N23: EV4S02_P1 | Q23: 1101789741 | AB23: 2
A24: 3170110330500 | C24: HUB USB | D24: DESK-USB HUB | E24: HB30A3A1CFB | F24: STARTECH.COM LTD | H24: 8 | I24: =H24*G24 -> 0 | J24: JGP | K24: 1 | L24: YA SE HA COMPRADO | M24: 45565 | N24: EV4S02_P1 | AB24: 2
A25: 1229599100008 | C25: WIRE DISPLAY PORT 10 M | D25: WIRE | E25: 182-8890 | F25: RS PRO | H25: 8 | I25: =H25*G25 -> 0 | J25: JGP | K25: 1 | L25: YA SE HA COMPRADO | M25: 45565 | N25: EV4S02_P1 | Q25: 1101789741 | AB25: 2
A26: 1229508276001 | C26: WIRE USB 10M | D26: WIRE | E26: 220-6500 | F26: RS PRO | H26: 8 | I26: =H26*G26 -> 0 | J26: JGP | K26: 1 | L26: YA SE HA COMPRADO | M26: 45567 | N26: EV4S02_P1 | AB26: 3
C27: WIRE USB 10M | D27: WIRE | E27: 220-6500 | F27: RS PRO | H27: 1 | J27: JGP | K27: 1 | L27: YA SE HA COMPRADO | M27: 45572 | N27: EV4S02_P1 | Q27: 1101790686 | AB27: 5
C28: TECLADOS | D28: DESK-MONITORES | H28: 8 | I28: =H28*G28 -> 0 | J28: JGP | K28: 1 | L28: EN SALA FRÍA 03 | M28: 45567 | N28: EV4S02_P1 | AB28: -
C29: RATONES | D29: DESK-MONITORES | H29: 8 | I29: =H29*G29 -> 0 | J29: JGP | K29: 1 | L29: EN SALA FRÍA 03 | M29: 45567 | N29: EV4S02_P1 | AB29: -
A30: 1589903750200 | C30: SOPORTE PANTALLA 2X10-27" VESA=100X100MM | D30: DESK-MONITORES | E30: FPMA-D700DDV | F30: NEWSTAR COMPUTER | H30: 4 | I30: =H30*G30 -> 0 | J30: JGP | K30: 1 | L30: YA SE HA COMPRADO | M30: 45567 | N30: EV4S02_P1 | Q30: 1101805917 | AB30: 4
A31: 1587080101200 | C31: ETIQUETA ADH TRANSF TERM 50,8X38,1MM TLS | D31: LABELS - WIRES | E31: PTL-107-427 | F31: BRADY | H31: 2 | I31: =H31*G31 -> 0 | J31: JGP | K31: 1 | L31: YA SE HA COMPRADO | M31: 45567 | N31: EV4S02_P1 | AB31: 3
A32: 1357060089305 | C32: TINTA PARA ETIQUETADO | D32: LABELS | E32: M7-R4300 | F32: BRADY | H32: 3 | I32: =H32*G32 -> 0 | J32: JGP | K32: 1 | L32: YA SE HA COMPRADO | M32: 45567 | N32: EV4S02_P1 | AB32: 3
A33: 1587090080000 | C33: ETIQUETA ADH POLIESTER METALIZAD CIL9200 | D33: LABELS - EQUIPMENT | E33: 44-LA1416 | F33: BRADY | H33: 35 | I33: =H33*G33 -> 0 | J33: JGP | K33: 1 | L33: YA SE HA COMPRADO | M33: 45567 | N33: EV4S02_P1 | AB33: 4
A34: 9300504880 | C34: @R CAB ADAPT MINIDP M A DISPLAY PORT H | D34: RACK-CONVERSORS | E34: 65030-84330 | F34: STARTECH.COM LTD | H34: 6 | I34: =H34*G34 -> 0 | J34: JGP | K34: 1 | L34: EN SALA FRÍA 03 | M34: 45567 | N34: EV4S02_P1 | AB34: -
A35: DACS | I35: =H35*G35 -> 0
A36: 1351709000800 | C36: MOD INTERFAZ AUDIO 192KHZ 188-CH USB3.0 (1U) | D36: RACK-DACS | E36: FIREFACE UFX III | F36: RME | H36: 1 | I36: =H36*G36 -> 0 | J36: JGP | K36: 1 | L36: YA SE HA COMPRADO | M36: 45572 | N36: EV4S02_P1 | Q36: 1101790686 | AB36: 5
A37: 1312704910100 | C37: MOD CONV D/A 32CH 192KHZ I/O MADI/ADAT (2U) | D37: RACK-DACS | E37: M-32 DA | F37: RME | H37: 1 | I37: =H37*G37 -> 0 | J37: JGP | K37: 1 | L37: YA SE HA COMPRADO | M37: 45572 | N37: EV4S02_P1 | Q37: 1101790686 | AB37: 5
A38: 1250200510200 | C38: PREAMPLIFICADOR MIC 12CH DIGI AVB/MADI (1U) | D38: RACK-DACS | E38: 12MIC | F38: RME | H38: 1 | I38: =H38*G38 -> 0 | J38: JGP | K38: 1 | L38: YA SE HA COMPRADO | M38: 45572 | N38: EV4S02_P1 | Q38: 1101790686 | AB38: 5
A39: 3170412070000 | C39: MOD SFP MADI MULTIMOD C/CBL2M/ACOP-SC-SC | D39: RACK-DACS | E39: 1001059 | F39: RME | H39: 1 | I39: =H39*G39 -> 0 | J39: JGP | K39: 1 | L39: YA SE HA COMPRADO | M39: 45572 | N39: EV4S02_P1 | Q39: 1101790686 | AB39: 5
A40: 1253001110300 | C40: HEADSET DT 297 PV MK II 80R MIC COND | D40: RACK-DACS | E40: 701.467 | F40: BEYERDYNAMIC | H40: 2 | I40: =H40*G40 -> 0 | J40: JGP | K40: 1 | L40: YA SE HA COMPRADO | M40: 45572 | N40: EV4S02_P1 | Q40: 1101790686 | AB40: 5
A41: 1253001119300 | C41: ACC CBL K 190.40 3P XLR L=1.5 P/DT28/29 | D41: RACK-DACS | E41: 445.894 | F41: BEYERDYNAMIC | H41: 2 | I41: =H41*G41 -> 0 | J41: JGP | K41: 1 | L41: YA SE HA COMPRADO | M41: 45572 | N41: EV4S02_P1 | Q41: 1101790686 | AB41: 5
A42: 1229524256300 | C42: MADI CABLE 10M | D42: RACK-DACS | E42: MADI10D | F42: ALVA AUDIO | H42: 1 | I42: =H42*G42 -> 0 | J42: JGP | K42: 2 | L42: YA SE HA COMPRADO | M42: 45572 | N42: EV4S02_P1 | Q42: 1101790686 | AB42: 5
A43: 1250100210600 | C43: ALTAVOZ YAMAHA MSP3A | D43: RACK-DACS | E43: MSP3A | F43: YAMAHA | H43: 2 | I43: =H43*G43 -> 0 | J43: JGP / fgvara | K43: 2 | L43: COMPRA EN MARCHA | M43: 45742 | N43: EV4S02_P1 | AB43: 7
I44: =H44*G44 -> 0 | AB44: 5
A45: 1229500300006 | C45: CBL EQ SFP+10GBE AWG30 3M | D45: RACK-QNAP | E45: CAB-DAC30M-SFPP | F45: OPTCORE | H45: 1 | I45: =H45*G45 -> 0 | J45: JGP | K45: 1 | L45: YA SE HA COMPRADO | M45: 45587 | N45: EV4S02_P1 | Q45: 1101796282 | AB45: 5
A46: 1229500300006 | C46: CBL EQ SFP+10GBE AWG30 3M | D46: RACK-QNAP | E46: CAB-DAC30M-SFPP | F46: OPTCORE | H46: 1 | I46: =H46*G46 -> 0 | J46: JGP | K46: 1 | L46: YA SE HA COMPRADO | M46: 45588 | N46: EV4S02_P1 | Q46: 1101796579 | AB46: 5
A47: 3010201822302 | C47: ORDENADOR ENRACABLE Z4 T1000 (GAMA HIGH PC - TIPO SENCILLO) | D47: RACK -PCs | E47: 52258775 | F47: HP | H47: 2 | I47: =H47*G47 -> 0 | J47: jjzapatera | K47: 1 | L47: YA SE HA COMPRADO | M47: 45624 | N47: S24B05_S1078 | AB47: 5
A48: 3210103403000 | C48: CBL EQ USB2.0 A-M/B-M PVC NEGRO L=15M | D48: MONITORES - TOUCH | E48: USB2HAB50AC | F48: STARTECH.COM | H48: 2 | I48: =H48*G48 -> 0 | J48: JGP | K48: 2 | L48: COMPRA EN MARCHA | M48: 45737 | N48: EV4S02_P1 | AB48: 6
A49: 3210501151200 | C49: ADAPT PCAN/USB OPTO-DECOUPLED | D49: RACK | E49: IPEH-002022 | F49: PEAK SYSTEM TECHNIK | H49: 2 | I49: =H49*G49 -> 0 | J49: fchamarro | K49: 2 | M49: 45922 | N49: EV4S02_P1
I50: =H50*G50 -> 0
I51: =H51*G51 -> 0
I52: =H52*G52 -> 0
I53: =H53*G53 -> 0
I54: =H54*G54 -> 0
